Workbook

Sheet 📋 Overview
A1: NUCLEUS SYSTEMS | NS-CMMF v1.0 — Cybersecurity Maturity Measurement Framework
A2: NIST CSF 2.0 · 187+ Controls · 6 Domains · 32 Frameworks & Regulations · 5-Axis Scoring · Hard Scoring Gates · 2026 · Re-engineered & Modernised
B4: Purpose | C4: NS-CMMF v1.0 is a comprehensive, consultable, and regulatory-aligned cybersecurity maturity framework for mid-market and enterprise organizations operating across multiple jurisdictions—modernizing traditional controls to align with cloud-first, AI-driven, and dynamic operating environments. With 187+ fully re-engineered and modernized controls, a 5-axis scoring model, and mapping to 32 frameworks and regulations, it replaces fragmented compliance checklists and opaque maturity ratings with a single, evidence-based approach to measurement and continuous improvement. This Assessment Tool is the operational layer of NS-CMMF v1.0, covering 187 specific controls across 6 NIST CSF 2.0 domains with automated scoring, roadmap prioritisation, and board-ready reporting.
B7: What Makes NS-CMMF Different | C7: 1. SPECIFICITY — Every control addresses one measurable, auditable outcome. Where legacy frameworks have 'endpoint protection' (one checkbox), NS-CMMF has 7 distinct controls: EDR coverage, CIS hardening, Critical patch SLA, Medium patch SLA, EOL management, application allowlisting, and MDM — each with its own evidence standard and regulatory mapping. 2. REGULATORY ALIGNMENT — Every control maps to specific regulatory articles (not general categories): GDPR Art.33-35, NIS2 Art.20-23, DORA Art.5-19, PCI DSS Req.1-12, HIPAA §164.308-312, SOX §404 & §802, CRA Art.13-14, FedRAMP Rev.5, and NIST SP 800-53 Rev.5. 3. MODERNISED CONTROLS — Re-engineered for cloud-first, AI-driven environments. Includes dedicated AI governance, AI threat detection, shadow AI controls, prompt injection prevention, AI model integrity validation, OT/ICS security, CSPM/CIEM, ZTNA, SASE architecture, and container security. 4. FINANCIAL QUANTIFICATION — Cyber risk expressed as EBITDA impact, regulatory fine exposure, and remediation cost — enabling board-level investment decisions rather than instinct-based ones. 5. CONTINUOUS MEASUREMENT — Designed for repeated assessment with longitudinal tracking, evidence lifecycle management, and a living roadmap — not a point-in-time audit instrument.
B10: 5-Axis Scoring Model | C10: Each control is scored across five independent dimensions: • Design Adequacy (20%) — Is the control well-designed, scoped, and mapped to regulatory obligations? • Implementation Coverage (25%) — Is it deployed across 100% of the in-scope population? • Operating Effectiveness (25%) — Does it run consistently with 3-month operational evidence? • Monitoring & Assurance (20%) — Is it independently tested and reported against defined KPIs? • Automation & Resilience (10%) — Is it automated, self-healing, and continuously evidenced? Composite Score = Design×0.20 + Coverage×0.25 + Operating×0.25 + Monitoring×0.20 + Automation×0.10
B13: Hard Scoring Gates | C13: These gates cap maturity regardless of composite score: • No named owner → Maximum L2 (unowned control is not a control) • No operational evidence over 3-month sample → Maximum L3 (documentation ≠ operation) • No KPI or KRI defined → Maximum L4 (unmeasured control cannot be managed) • No automated telemetry → Maximum L5 (continuous evidence requires automation) • Named regulatory obligation demonstrably unmet → Maximum L2 / High Risk • Interview-only evidence (Tier 3) → Maximum L2 / Unverified • Attestation-only evidence (Tier 4) → Maximum L1.5 / Unverified
B16: Evidence Standards | C16: Tier 1 — Automated tool output + independent third-party validation → Full score weight Tier 2 — Documentary evidence + sample testing → Score reduced by 0.3 across all dimensions Tier 3 — Interview only, no corroboration → Capped at L2 / Unverified Tier 4 — Management attestation, no supporting documentation → Capped at L1.5 / Unverified
B19: Maturity Scale | C19: L1 — Initial: Ad hoc, reactive, undocumented. No named owner. Controls exist only after incidents. L2 — Developing: Basic processes exist but inconsistently applied. Some documentation. Manual evidence. L3 — Defined: Standardised, documented, consistently applied. Named owners. Annual review. Systematic evidence. L4 — Managed: Measured, KPI-driven, risk-integrated. Performance tracked. Exceptions formally managed. L5 — Optimised: Automated, adaptive, continuously improving. Self-healing. Independently assured.
B22: Simplification Recommendations | C22: Based on assessment of legacy frameworks and client feedback, NS-CMMF v1.0 incorporates the following simplifications: 1. CONSOLIDATE VENDOR ASSESSMENT — Combined vendor assessment questionnaire, contractual obligations, and sub-processor mapping into a unified TPRM domain view rather than three separate sheets. 2. UNIFIED JML CONTROLS — Joiners/Movers/Leavers consolidated into three specific controls with clear SLA gates, replacing six overlapping IAM procedures. 3. SINGLE PATCH SLA CONTROL — Critical/High and Medium/Low SLAs unified into one Patch Management control with tiered SLA thresholds, eliminating duplicate evidence collection. 4. AI CONTROLS INTEGRATED — AI governance controls distributed across relevant CSF domains (GV for governance, PR for controls, DE for detection, RC for recovery) rather than siloed in a separate AI workstream. 5. EVIDENCE REGISTER SIMPLIFIED — Evidence tracking uses status tiers (Current/Expiring/Expired/Requested) with automated flagging rather than manual evidence management spreadsheets. 6. ROADMAP AUTO-GENERATION — Priority Score (Gap × Domain Weight) automatically populates the roadmap, eliminating manual prioritisation workshops for standard engagements. 7. REGULATORY MAPPING AT CONTROL LEVEL — Framework alignment embedded in each control row rather than maintained as a separate cross-reference matrix, eliminating the need for mapping reconciliation. 8. SINGLE DROPDOWN PER CONTROL — Replaced separate current/target/evidence dropdowns with a single L1-L5 contextual dropdown that preserves control-specific maturity descriptions.
B25: How to Use This Tool | C25: Step 1: SCOPE — Complete the 🔍 Scoping sheet. Answer all Yes/No questions to auto-scope controls for your context. Step 2: ASSESS — Work through each domain sheet. Describe current state in column F, attach evidence in column G, select maturity rating in column H, and set target in column J. Step 3: REVIEW — Open the 📊 Dashboard for your weighted maturity current vs target with priority signals. Step 4: ROADMAP — Use the 🗺️ Roadmap sheet for auto-generated improvement actions ranked by Priority Score. Step 5: REPORT — The 📄 Board Report auto-populates from your scores for executive communication. Step 6: TRACK — Record each completed assessment in 📅 Assessment History for regulatory evidence of improvement.
B28: Version | C28: Nucleus Systems NS-CMMF v1.0 | Cybersecurity Maturity Measurement Framework | 2026 Edition | Re-engineered & Modernised | www.nucleus-systems.com | Centurion, Gauteng, South Africa

Sheet 🔍 Scoping
A1: 🔍 NS-CMMF v1.0 Cybersecurity Maturity Measurement Framework — ASSESSMENT SCOPING QUESTIONNAIRE
A2: Complete this sheet FIRST — answers auto-scope controls. If unsure, answer Yes (conservative scoping).
B4: Q # | C4: Category | D4: Scoping Question | E4: Answer ▼ | F4: Why This Matters | G4: Controls Affected if No
A5: Regulatory
B6: Q1 | C6: Regulatory | D6: Subject to GDPR (EU data protection)? | E6: Yes | F6: Triggers privacy governance, ROPA, DPIA, data subject rights, and breach notification controls. | G6: 8 controls
B7: Q2 | C7: Regulatory | D7: Subject to NIS2 Directive (EU essential or important entity)? | E7: No | F7: Triggers NIS2 management accountability, incident notification, and supply chain security controls. | G7: 3 controls
B8: Q3 | C8: Regulatory | D8: Subject to DORA (EU Digital Operational Resilience Act)? | E8: No | F8: Triggers DORA ICT risk framework, TPSP register, TLPT, and major incident reporting controls. | G8: 4 controls
B9: Q4 | C9: Regulatory | D9: Subject to PCI DSS (processes, stores, or transmits payment card data)? | E9: Yes | F9: Triggers CDE scoping, cardholder data protection, segmentation validation, and logging controls. | G9: 6 controls
B10: Q5 | C10: Regulatory | D10: Subject to HIPAA (US healthcare — PHI protection)? | E10: No | F10: Triggers HIPAA administrative, technical, and physical safeguards; BAA requirements. | G10: 2 controls
B11: Q6 | C11: Regulatory | D11: Subject to SOX (public company — financial reporting controls)? | E11: No | F11: Triggers IT general controls, audit trail requirements, access certification, and financial monitoring. | G11: 2 controls
B12: Q7 | C12: Regulatory | D12: Subject to CCPA or US state privacy laws? | E12: No | F12: Triggers consumer rights fulfilment, deletion capability, and service provider governance. | G12: None
B13: Q8 | C13: Regulatory | D13: Distribute software products in EU subject to Cyber Resilience Act (CRA)? | E13: No | F13: Triggers SBOM, vulnerability disclosure, security-by-design, and ENISA reporting obligations. | G13: 3 controls
B14: Q9 | C14: Regulatory | D14: Hold or seek FedRAMP authorisation for US federal cloud workloads? | E14: No | F14: Triggers FedRAMP baselines, ZTA mandate, 3PAO assessment, and continuous monitoring controls. | G14: 1 controls
A15: Organisation
B16: Q10 | C16: Organisation | D16: 500+ employees or process data of 100,000+ individuals? | E16: Yes | F16: Larger organisations require formal executive accountability and structured audit infrastructure. | G16: None
B17: Q11 | C17: Organisation | D17: Operate across more than 3 countries or jurisdictions? | E17: No | F17: Requires multi-framework regulatory mapping and cross-border data transfer controls. | G17: 2 controls
B18: Q12 | C18: Organisation | D18: Have an existing ISO 27001, SOC 2, or formal GRC programme? | E18: No | F18: Enables integration of NS-CMMF into existing assurance frameworks. | G18: None
A19: Cloud & Infra
B20: Q13 | C20: Cloud & Infra | D20: Operate workloads on AWS, Azure, or GCP? | E20: Yes | F20: Triggers CSPM, CIEM, shared responsibility, ISO 27017, and cloud-native security controls. | G20: 13 controls
B21: Q14 | C21: Cloud & Infra | D21: Operate OT, ICS, SCADA, or industrial control systems? | E21: No | F21: Triggers OT/ICS security, OT-IT network separation, and specialist continuity controls. | G21: 6 controls
B22: Q15 | C22: Cloud & Infra | D22: Use or provide SaaS applications to external customers? | E22: Yes | F22: Triggers SaaS security, API security, multi-tenant isolation, and CASB controls. | G22: None
A23: App Dev
B24: Q16 | C24: App Dev | D24: Develop, build, or maintain software products distributed externally? | E24: Yes | F24: Triggers SBOM, secure SDLC, NIST SSDF, CRA obligations, and supply chain security. | G24: 14 controls
A25: AI & Emerging
B26: Q17 | C26: AI & Emerging | D26: Develop, train, fine-tune, or deploy AI or ML models? | E26: No | F26: Triggers AI governance committee, asset inventory, training data governance, and adversarial testing. | G26: 12 controls
B27: Q18 | C27: AI & Emerging | D27: Use generative AI, LLMs, or automated decision systems affecting individuals? | E27: No | F27: Triggers prompt injection prevention, AI output monitoring, GDPR Art.22, and EU AI Act controls. | G27: 4 controls
B28: Q19 | C28: AI & Emerging | D28: Employees using third-party AI tools (ChatGPT, Copilot, etc.) for work? | E28: Yes | F28: Triggers shadow AI detection, AI AUP enforcement, and DLP-based AI monitoring controls. | G28: 3 controls
A29: Third Parties
B30: Q20 | C30: Third Parties | D30: Rely on third-party ICT providers for critical operations? | E30: Yes | F30: Triggers TPRM programme, DORA TPSP register, vendor assessments, and supply chain controls. | G30: 7 controls
B31: Q21 | C31: Third Parties | D31: Process personal data as a data processor on behalf of other organisations? | E31: No | F31: Triggers processor obligations under GDPR Art.28, contractual requirements, and sub-processor governance. | G31: None
B32: Q22 | C32: Third Parties | D32: Use managed security services (MSSP, SOC-as-a-service)? | E32: No | F32: Triggers MSSP contract review, shared responsibility for detection, and third-party SLA monitoring. | G32: 1 controls
A33: Financial
B34: Q23 | C34: Financial | D34: Hold, process, or manage significant financial assets or critical financial data? | E34: Yes | F34: Triggers SOX financial monitoring, financial system access controls, and change management controls. | G34: None
B37: ⚙️ HOW SCOPING WORKS: Answer Yes/No above. Controls are auto-excluded in domain sheets when you answer No to a relevant question. Override by setting Scope = Apply in any domain sheet. N/A = question not applicable to your organisation (controls remain in scope).

Sheet 📊 Dashboard
A1: NUCLEUS SYSTEMS | NS-CMMF v1.0 — CYBERSECURITY MATURITY MEASUREMENT DASHBOARD
A2: NIST CSF 2.0 · 188 Controls · 6 Domains · 32 Frameworks & Regulations · 5-Axis Maturity Scoring · L1→L5 · Evidence-Based · 2026
B3: Organisation: | C3: Acacia Financial Services Ltd | F3: Assessment Date: | G3: 04 September 2026 | I3: Assessor: | J3: [Your Name] — Lead Assessor, NS-CMMF v1.0
B4: 📊 DOMAIN MATURITY — CURRENT STATE vs TARGET (Weighted by domain criticality)
C5: Domain | D5: Weight | E5: Current Avg (/5.0) | F5: Maturity % | G5: Level | H5: Target Avg (/5.0) | I5: Target % | J5: Target Level | K5: Gap | L5: Priority Signal | M5: Controls Rated % | N5: Quick Wins Available
B6: 🏛️ | C6: GOVERN — Leadership, Strategy & Risk Governance | D6: 0.16 | E6: =IFERROR('GV Govern'!J2,"") -> 1.1481481 | F6: =IFERROR(IF(E6="","",E6/5),"") -> 0.22962963 | G6: =IFERROR(IF(E6=0,"⬜ Not Assessed",IF(E6<1.5,"🔴 L1 — Initial",IF(E6<2.5,"🟠 L2 — Developing",IF(E6<3.5,"🟡 L3 — Defined",IF(E6<4.5,"🟢 L4 — Managed","💎 L5 — Optimised"))))),"") -> 🔴 L1 — Initial | H6: =IFERROR('GV Govern'!L2,"") -> 3.3703704 | I6: =IFERROR(IF(H6="","",H6/5),"") -> 0.67407407 | J6: =IFERROR(IF(H6=0,"Not Set",IF(H6<1.5,"L1 — Initial",IF(H6<2.5,"L2 — Developing",IF(H6<3.5,"L3 — Defined",IF(H6<4.5,"L4 — Managed","L5 — Optimised"))))),"") -> L3 — Defined | K6: =IFERROR(IF(OR(E6="",H6=""),"—",H6-E6),"—") -> 2.2222222 | L6: =IFERROR(IF(OR(E6="",H6=""),"—",IF(H6-E6>=3,"🔴 Critical — Immediate Action",IF(H6-E6>=2,"🟠 High — Action This Quarter",IF(H6-E6>=1,"🟡 Medium — Plan Within 6 Months",IF(H6-E6>0,"🔵 Low — Schedule & Monitor",IF(H6-E6=0,"✅ Target Met","⬆️ Exceeds Target")))))),"") -> 🟠 High — Action This Quarter | M6: =IFERROR('GV Govern'!N2,"—") -> 27 / 27 applicable | N6: =COUNTIFS('🗺️ Roadmap'!A5:A32,">0",'🗺️ Roadmap'!A5:A32,"<="&16%*1.5) -> 9
B7: 🔍 | C7: IDENTIFY — Assets, Data, Risk & Exposure | D7: 0.1 | E7: =IFERROR('ID Identify'!J2,"") -> 1.3157895 | F7: =IFERROR(IF(E7="","",E7/5),"") -> 0.26315789 | G7: =IFERROR(IF(E7=0,"⬜ Not Assessed",IF(E7<1.5,"🔴 L1 — Initial",IF(E7<2.5,"🟠 L2 — Developing",IF(E7<3.5,"🟡 L3 — Defined",IF(E7<4.5,"🟢 L4 — Managed","💎 L5 — Optimised"))))),"") -> 🔴 L1 — Initial | H7: =IFERROR('ID Identify'!L2,"") -> 3.4736842 | I7: =IFERROR(IF(H7="","",H7/5),"") -> 0.69473684 | J7: =IFERROR(IF(H7=0,"Not Set",IF(H7<1.5,"L1 — Initial",IF(H7<2.5,"L2 — Developing",IF(H7<3.5,"L3 — Defined",IF(H7<4.5,"L4 — Managed","L5 — Optimised"))))),"") -> L3 — Defined | K7: =IFERROR(IF(OR(E7="",H7=""),"—",H7-E7),"—") -> 2.1578947 | L7: =IFERROR(IF(OR(E7="",H7=""),"—",IF(H7-E7>=3,"🔴 Critical — Immediate Action",IF(H7-E7>=2,"🟠 High — Action This Quarter",IF(H7-E7>=1,"🟡 Medium — Plan Within 6 Months",IF(H7-E7>0,"🔵 Low — Schedule & Monitor",IF(H7-E7=0,"✅ Target Met","⬆️ Exceeds Target")))))),"") -> 🟠 High — Action This Quarter | M7: =IFERROR('ID Identify'!N2,"—") -> 19 / 19 applicable | N7: =COUNTIFS('🗺️ Roadmap'!A33:A54,">0",'🗺️ Roadmap'!A33:A54,"<="&10%*1.5) -> 7
B8: 🛡️ | C8: PROTECT — Controls, Architecture & Safeguards | D8: 0.26 | E8: =IFERROR('PR Protect'!J2,"") -> 1.36 | F8: =IFERROR(IF(E8="","",E8/5),"") -> 0.272 | G8: =IFERROR(IF(E8=0,"⬜ Not Assessed",IF(E8<1.5,"🔴 L1 — Initial",IF(E8<2.5,"🟠 L2 — Developing",IF(E8<3.5,"🟡 L3 — Defined",IF(E8<4.5,"🟢 L4 — Managed","💎 L5 — Optimised"))))),"") -> 🔴 L1 — Initial | H8: =IFERROR('PR Protect'!L2,"") -> 3.4666667 | I8: =IFERROR(IF(H8="","",H8/5),"") -> 0.69333333 | J8: =IFERROR(IF(H8=0,"Not Set",IF(H8<1.5,"L1 — Initial",IF(H8<2.5,"L2 — Developing",IF(H8<3.5,"L3 — Defined",IF(H8<4.5,"L4 — Managed","L5 — Optimised"))))),"") -> L3 — Defined | K8: =IFERROR(IF(OR(E8="",H8=""),"—",H8-E8),"—") -> 2.1066667 | L8: =IFERROR(IF(OR(E8="",H8=""),"—",IF(H8-E8>=3,"🔴 Critical — Immediate Action",IF(H8-E8>=2,"🟠 High — Action This Quarter",IF(H8-E8>=1,"🟡 Medium — Plan Within 6 Months",IF(H8-E8>0,"🔵 Low — Schedule & Monitor",IF(H8-E8=0,"✅ Target Met","⬆️ Exceeds Target")))))),"") -> 🟠 High — Action This Quarter | M8: =IFERROR('PR Protect'!N2,"—") -> 78 / 78 applicable | N8: =COUNTIFS('🗺️ Roadmap'!A55:A137,">0",'🗺️ Roadmap'!A55:A137,"<="&26%*1.5) -> 21
B9: 📡 | C9: DETECT — Monitoring, Detection & Threat Intelligence | D9: 0.14 | E9: =IFERROR('DE Detect'!J2,"") -> 1.1111111 | F9: =IFERROR(IF(E9="","",E9/5),"") -> 0.22222222 | G9: =IFERROR(IF(E9=0,"⬜ Not Assessed",IF(E9<1.5,"🔴 L1 — Initial",IF(E9<2.5,"🟠 L2 — Developing",IF(E9<3.5,"🟡 L3 — Defined",IF(E9<4.5,"🟢 L4 — Managed","💎 L5 — Optimised"))))),"") -> 🔴 L1 — Initial | H9: =IFERROR('DE Detect'!L2,"") -> 3.3888889 | I9: =IFERROR(IF(H9="","",H9/5),"") -> 0.67777778 | J9: =IFERROR(IF(H9=0,"Not Set",IF(H9<1.5,"L1 — Initial",IF(H9<2.5,"L2 — Developing",IF(H9<3.5,"L3 — Defined",IF(H9<4.5,"L4 — Managed","L5 — Optimised"))))),"") -> L3 — Defined | K9: =IFERROR(IF(OR(E9="",H9=""),"—",H9-E9),"—") -> 2.2777778 | L9: =IFERROR(IF(OR(E9="",H9=""),"—",IF(H9-E9>=3,"🔴 Critical — Immediate Action",IF(H9-E9>=2,"🟠 High — Action This Quarter",IF(H9-E9>=1,"🟡 Medium — Plan Within 6 Months",IF(H9-E9>0,"🔵 Low — Schedule & Monitor",IF(H9-E9=0,"✅ Target Met","⬆️ Exceeds Target")))))),"") -> 🟠 High — Action This Quarter | M9: =IFERROR('DE Detect'!N2,"—") -> 18 / 18 applicable | N9: =COUNTIFS('🗺️ Roadmap'!A138:A159,">0",'🗺️ Roadmap'!A138:A159,"<="&14%*1.5) -> 3
B10: 🚨 | C10: RESPOND — Incident Management & Regulatory Notification | D10: 0.11 | E10: =IFERROR('RS Respond'!J2,"") -> 1.2857143 | F10: =IFERROR(IF(E10="","",E10/5),"") -> 0.25714286 | G10: =IFERROR(IF(E10=0,"⬜ Not Assessed",IF(E10<1.5,"🔴 L1 — Initial",IF(E10<2.5,"🟠 L2 — Developing",IF(E10<3.5,"🟡 L3 — Defined",IF(E10<4.5,"🟢 L4 — Managed","💎 L5 — Optimised"))))),"") -> 🔴 L1 — Initial | H10: =IFERROR('RS Respond'!L2,"") -> 3.4285714 | I10: =IFERROR(IF(H10="","",H10/5),"") -> 0.68571429 | J10: =IFERROR(IF(H10=0,"Not Set",IF(H10<1.5,"L1 — Initial",IF(H10<2.5,"L2 — Developing",IF(H10<3.5,"L3 — Defined",IF(H10<4.5,"L4 — Managed","L5 — Optimised"))))),"") -> L3 — Defined | K10: =IFERROR(IF(OR(E10="",H10=""),"—",H10-E10),"—") -> 2.1428571 | L10: =IFERROR(IF(OR(E10="",H10=""),"—",IF(H10-E10>=3,"🔴 Critical — Immediate Action",IF(H10-E10>=2,"🟠 High — Action This Quarter",IF(H10-E10>=1,"🟡 Medium — Plan Within 6 Months",IF(H10-E10>0,"🔵 Low — Schedule & Monitor",IF(H10-E10=0,"✅ Target Met","⬆️ Exceeds Target")))))),"") -> 🟠 High — Action This Quarter | M10: =IFERROR('RS Respond'!N2,"—") -> 14 / 14 applicable | N10: =COUNTIFS('🗺️ Roadmap'!A160:A175,">0",'🗺️ Roadmap'!A160:A175,"<="&11%*1.5) -> 6
B11: ♻️ | C11: RECOVER — Resilience, Continuity & Validation | D11: 0.1 | E11: =IFERROR('RC Recover'!J2,"") -> 1.0714286 | F11: =IFERROR(IF(E11="","",E11/5),"") -> 0.21428571 | G11: =IFERROR(IF(E11=0,"⬜ Not Assessed",IF(E11<1.5,"🔴 L1 — Initial",IF(E11<2.5,"🟠 L2 — Developing",IF(E11<3.5,"🟡 L3 — Defined",IF(E11<4.5,"🟢 L4 — Managed","💎 L5 — Optimised"))))),"") -> 🔴 L1 — Initial | H11: =IFERROR('RC Recover'!L2,"") -> 3.2142857 | I11: =IFERROR(IF(H11="","",H11/5),"") -> 0.64285714 | J11: =IFERROR(IF(H11=0,"Not Set",IF(H11<1.5,"L1 — Initial",IF(H11<2.5,"L2 — Developing",IF(H11<3.5,"L3 — Defined",IF(H11<4.5,"L4 — Managed","L5 — Optimised"))))),"") -> L3 — Defined | K11: =IFERROR(IF(OR(E11="",H11=""),"—",H11-E11),"—") -> 2.1428571 | L11: =IFERROR(IF(OR(E11="",H11=""),"—",IF(H11-E11>=3,"🔴 Critical — Immediate Action",IF(H11-E11>=2,"🟠 High — Action This Quarter",IF(H11-E11>=1,"🟡 Medium — Plan Within 6 Months",IF(H11-E11>0,"🔵 Low — Schedule & Monitor",IF(H11-E11=0,"✅ Target Met","⬆️ Exceeds Target")))))),"") -> 🟠 High — Action This Quarter | M11: =IFERROR('RC Recover'!N2,"—") -> 14 / 14 applicable | N11: =COUNTIFS('🗺️ Roadmap'!A176:A192,">0",'🗺️ Roadmap'!A176:A192,"<="&10%*1.5) -> 3
B12: 📊 WEIGHTED OVERALL MATURITY | E12: =IFERROR((E6*D6+E7*D7+E8*D8+E9*D9+E10*D10+E11*D11)/(D6+D7+D8+D9+D10+D11),"") -> 1.2333444 | F12: =IFERROR(IF(E12=0,"",E12/5),"") -> 0.24666888 | G12: =IFERROR(IF(E12=0,"⬜ Not Assessed",IF(E12<1.5,"🔴 L1",IF(E12<2.5,"🟠 L2",IF(E12<3.5,"🟡 L3",IF(E12<4.5,"🟢 L4","💎 L5"))))),"") -> 🔴 L1 | H12: =IFERROR((H6*D6+H7*D7+H8*D8+H9*D9+H10*D10+H11*D11)/(D6+D7+D8+D9+D10+D11),"") -> 3.4034217 | I12: =IFERROR(IF(H12=0,"",H12/5),"") -> 0.68068434 | J12: =IFERROR(IF(H12=0,"Not Set",IF(H12<1.5,"L1",IF(H12<2.5,"L2",IF(H12<3.5,"L3",IF(H12<4.5,"L4","L5"))))),"") -> L3 | K12: =IFERROR(IF(OR(E12="",H12=""),"—",H12-E12),"—") -> 2.1700773 | L12: Weighted maturity across all in-scope assessed controls · Regulatory compliance floors applied
B14: 📌 REGULATORY COMPLIANCE FLOORS — Controls capped due to unmet regulatory obligations
B15: ⚠ NIS2 incident notification capability absent or untested → minimum High Risk (NIS2 essential/important entities)
B16: ⚠ DORA major incident reporting process not established (EU financial entities) → minimum High Risk
B17: ⚠ GDPR ROPA absent or >50% incomplete → minimum High Risk (direct GDPR Art.30 violation)
B18: ⚠ PCI CDE scope unconfirmed or segmentation untested → minimum Critical Risk (PCI DSS non-compliance)
B19: ⚠ HIPAA risk analysis not conducted or >12 months outdated → minimum High Risk
B20: ⚠ FedRAMP ATO expired or not obtained for federal cloud workloads → minimum Critical Risk
B21: ⚠ CRA vulnerability disclosure policy absent for EU-distributed software → minimum High Risk (CRA Art.13)
B22: ⚠ SOX IT general controls not evidenced for in-scope financial systems → minimum High Risk (SOX §404)
B24: 💰 REMEDIATION & IMPROVEMENT COST SUMMARY — From Roadmap Tab (Enter costs in Roadmap → auto-populate here)
B25: Domain | C25: Controls | D25: Weight | E25: Internal Cost (Staff Time) | F25: External Once-Off | G25: External Recurring /yr | H25: Software / Tool Cost | I25: Total Once-Off | J25: Total Annual | K25: Effort Signal | L25: Notes
B26: 🏛️ GOVERN | C26: 28 | D26: 16% | E26: =SUMIF('🗺️ Roadmap'!$B$5:$B$192,"*GV Govern*",'🗺️ Roadmap'!$J$5:$J$192) -> 80250 | F26: =SUMIF('🗺️ Roadmap'!$B$5:$B$192,"*GV Govern*",'🗺️ Roadmap'!$K$5:$K$192) -> 45000 | G26: =SUMIF('🗺️ Roadmap'!$B$5:$B$192,"*GV Govern*",'🗺️ Roadmap'!$L$5:$L$192) -> 0 | H26: =SUMIF('🗺️ Roadmap'!$B$5:$B$192,"*GV Govern*",'🗺️ Roadmap'!$M$5:$M$192) -> 0 | I26: =SUMIF('🗺️ Roadmap'!$B$5:$B$192,"*GV Govern*",'🗺️ Roadmap'!$N$5:$N$192) -> 125250 | J26: =SUMIF('🗺️ Roadmap'!$B$5:$B$192,"*GV Govern*",'🗺️ Roadmap'!$O$5:$O$192) -> 0 | K26: =IF(I26=0,"⬜ Not Estimated",IF(I26<50000,"🟢 Low (< 50K)",IF(I26<200000,"🟡 Medium (50K–200K)",IF(I26<500000,"🟠 High (200K–500K)","🔴 Major (500K+)")))) -> 🟡 Medium (50K–200K)
B27: 🔍 IDENTIFY | C27: 22 | D27: 10% | E27: =SUMIF('🗺️ Roadmap'!$B$5:$B$192,"*ID Identify*",'🗺️ Roadmap'!$J$5:$J$192) -> 59250 | F27: =SUMIF('🗺️ Roadmap'!$B$5:$B$192,"*ID Identify*",'🗺️ Roadmap'!$K$5:$K$192) -> 95000 | G27: =SUMIF('🗺️ Roadmap'!$B$5:$B$192,"*ID Identify*",'🗺️ Roadmap'!$L$5:$L$192) -> 0 | H27: =SUMIF('🗺️ Roadmap'!$B$5:$B$192,"*ID Identify*",'🗺️ Roadmap'!$M$5:$M$192) -> 18000 | I27: =SUMIF('🗺️ Roadmap'!$B$5:$B$192,"*ID Identify*",'🗺️ Roadmap'!$N$5:$N$192) -> 172250 | J27: =SUMIF('🗺️ Roadmap'!$B$5:$B$192,"*ID Identify*",'🗺️ Roadmap'!$O$5:$O$192) -> 0 | K27: =IF(I27=0,"⬜ Not Estimated",IF(I27<50000,"🟢 Low (< 50K)",IF(I27<200000,"🟡 Medium (50K–200K)",IF(I27<500000,"🟠 High (200K–500K)","🔴 Major (500K+)")))) -> 🟡 Medium (50K–200K)
B28: 🛡️ PROTECT | C28: 83 | D28: 26% | E28: =SUMIF('🗺️ Roadmap'!$B$5:$B$192,"*PR Protect*",'🗺️ Roadmap'!$J$5:$J$192) -> 226750 | F28: =SUMIF('🗺️ Roadmap'!$B$5:$B$192,"*PR Protect*",'🗺️ Roadmap'!$K$5:$K$192) -> 55000 | G28: =SUMIF('🗺️ Roadmap'!$B$5:$B$192,"*PR Protect*",'🗺️ Roadmap'!$L$5:$L$192) -> 0 | H28: =SUMIF('🗺️ Roadmap'!$B$5:$B$192,"*PR Protect*",'🗺️ Roadmap'!$M$5:$M$192) -> 112000 | I28: =SUMIF('🗺️ Roadmap'!$B$5:$B$192,"*PR Protect*",'🗺️ Roadmap'!$N$5:$N$192) -> 393750 | J28: =SUMIF('🗺️ Roadmap'!$B$5:$B$192,"*PR Protect*",'🗺️ Roadmap'!$O$5:$O$192) -> 0 | K28: =IF(I28=0,"⬜ Not Estimated",IF(I28<50000,"🟢 Low (< 50K)",IF(I28<200000,"🟡 Medium (50K–200K)",IF(I28<500000,"🟠 High (200K–500K)","🔴 Major (500K+)")))) -> 🟠 High (200K–500K)
B29: 📡 DETECT | C29: 22 | D29: 14% | E29: =SUMIF('🗺️ Roadmap'!$B$5:$B$192,"*DE Detect*",'🗺️ Roadmap'!$J$5:$J$192) -> 64250 | F29: =SUMIF('🗺️ Roadmap'!$B$5:$B$192,"*DE Detect*",'🗺️ Roadmap'!$K$5:$K$192) -> 0 | G29: =SUMIF('🗺️ Roadmap'!$B$5:$B$192,"*DE Detect*",'🗺️ Roadmap'!$L$5:$L$192) -> 36000 | H29: =SUMIF('🗺️ Roadmap'!$B$5:$B$192,"*DE Detect*",'🗺️ Roadmap'!$M$5:$M$192) -> 138000 | I29: =SUMIF('🗺️ Roadmap'!$B$5:$B$192,"*DE Detect*",'🗺️ Roadmap'!$N$5:$N$192) -> 202250 | J29: =SUMIF('🗺️ Roadmap'!$B$5:$B$192,"*DE Detect*",'🗺️ Roadmap'!$O$5:$O$192) -> 36000 | K29: =IF(I29=0,"⬜ Not Estimated",IF(I29<50000,"🟢 Low (< 50K)",IF(I29<200000,"🟡 Medium (50K–200K)",IF(I29<500000,"🟠 High (200K–500K)","🔴 Major (500K+)")))) -> 🟠 High (200K–500K)
B30: 🚨 RESPOND | C30: 16 | D30: 11% | E30: =SUMIF('🗺️ Roadmap'!$B$5:$B$192,"*RS Respond*",'🗺️ Roadmap'!$J$5:$J$192) -> 35000 | F30: =SUMIF('🗺️ Roadmap'!$B$5:$B$192,"*RS Respond*",'🗺️ Roadmap'!$K$5:$K$192) -> 0 | G30: =SUMIF('🗺️ Roadmap'!$B$5:$B$192,"*RS Respond*",'🗺️ Roadmap'!$L$5:$L$192) -> 0 | H30: =SUMIF('🗺️ Roadmap'!$B$5:$B$192,"*RS Respond*",'🗺️ Roadmap'!$M$5:$M$192) -> 0 | I30: =SUMIF('🗺️ Roadmap'!$B$5:$B$192,"*RS Respond*",'🗺️ Roadmap'!$N$5:$N$192) -> 35000 | J30: =SUMIF('🗺️ Roadmap'!$B$5:$B$192,"*RS Respond*",'🗺️ Roadmap'!$O$5:$O$192) -> 0 | K30: =IF(I30=0,"⬜ Not Estimated",IF(I30<50000,"🟢 Low (< 50K)",IF(I30<200000,"🟡 Medium (50K–200K)",IF(I30<500000,"🟠 High (200K–500K)","🔴 Major (500K+)")))) -> 🟢 Low (< 50K)
B31: ♻️ RECOVER | C31: 17 | D31: 10% | E31: =SUMIF('🗺️ Roadmap'!$B$5:$B$192,"*RC Recover*",'🗺️ Roadmap'!$J$5:$J$192) -> 49250 | F31: =SUMIF('🗺️ Roadmap'!$B$5:$B$192,"*RC Recover*",'🗺️ Roadmap'!$K$5:$K$192) -> 28000 | G31: =SUMIF('🗺️ Roadmap'!$B$5:$B$192,"*RC Recover*",'🗺️ Roadmap'!$L$5:$L$192) -> 0 | H31: =SUMIF('🗺️ Roadmap'!$B$5:$B$192,"*RC Recover*",'🗺️ Roadmap'!$M$5:$M$192) -> 0 | I31: =SUMIF('🗺️ Roadmap'!$B$5:$B$192,"*RC Recover*",'🗺️ Roadmap'!$N$5:$N$192) -> 77250 | J31: =SUMIF('🗺️ Roadmap'!$B$5:$B$192,"*RC Recover*",'🗺️ Roadmap'!$O$5:$O$192) -> 0 | K31: =IF(I31=0,"⬜ Not Estimated",IF(I31<50000,"🟢 Low (< 50K)",IF(I31<200000,"🟡 Medium (50K–200K)",IF(I31<500000,"🟠 High (200K–500K)","🔴 Major (500K+)")))) -> 🟡 Medium (50K–200K)
B32: TOTAL — ALL 188 CONTROLS | C32: 188 | D32: 100% | E32: =SUM(E26:E31) -> 514750 | F32: =SUM(F26:F31) -> 223000 | G32: =SUM(G26:G31) -> 36000 | H32: =SUM(H26:H31) -> 268000 | I32: =SUM(I26:I31) -> 1005750 | J32: =SUM(J26:J31) -> 36000 | K32: =IF(I32=0,"⬜ Not Estimated",IF(I32<50000,"🟢 Low (< 50K)",IF(I32<200000,"🟡 Medium (50K–200K)",IF(I32<500000,"🟠 High (200K–500K)","🔴 Major (500K+)")))) -> 🔴 Major (500K+)
B34: 📋 HOW TO USE: Enter cost estimates per control in the Roadmap tab (columns J–M: Internal / External Once-Off / External Recurring / Software). Domain totals and the grand total auto-populate above. Once-Off cost = CAPEX + year-1 implementation. Annual cost = ongoing OPEX + licensing.

Sheet 📄 Board Report
B2: NUCLEUS SYSTEMS | CONFIDENTIAL
B3: CYBERSECURITY MATURITY BOARD REPORT
B4: NS-CMMF v1.0 · 188 Controls · 6 Domains · 32 Frameworks · 5-Axis Scoring · 2026
C6: Organisation: | D6: ='📊 Dashboard'!C3 -> Acacia Financial Services Ltd | F6: Date: | G6: ='📊 Dashboard'!G3 -> 04 September 2026
C8: 📊 MATURITY SUMMARY — Current vs Target by Domain
C9: Domain | D9: Weight | E9: Current Score | F9: Level | G9: Target | H9: Priority
C10: 🏛️ GOVERN — Leadership, Strategy & Risk Governance | D10: ='📊 Dashboard'!D6 -> 0.16 | E10: ='📊 Dashboard'!E6 -> 1.1481481 | F10: ='📊 Dashboard'!G6 -> 🔴 L1 — Initial | G10: ='📊 Dashboard'!H6 -> 3.3703704 | H10: ='📊 Dashboard'!L6 -> 🟠 High — Action This Quarter
C11: 🔍 IDENTIFY — Assets, Data, Risk & Exposure | D11: ='📊 Dashboard'!D7 -> 0.1 | E11: ='📊 Dashboard'!E7 -> 1.3157895 | F11: ='📊 Dashboard'!G7 -> 🔴 L1 — Initial | G11: ='📊 Dashboard'!H7 -> 3.4736842 | H11: ='📊 Dashboard'!L7 -> 🟠 High — Action This Quarter
C12: 🛡️ PROTECT — Controls, Architecture & Safeguards | D12: ='📊 Dashboard'!D8 -> 0.26 | E12: ='📊 Dashboard'!E8 -> 1.36 | F12: ='📊 Dashboard'!G8 -> 🔴 L1 — Initial | G12: ='📊 Dashboard'!H8 -> 3.4666667 | H12: ='📊 Dashboard'!L8 -> 🟠 High — Action This Quarter
C13: 📡 DETECT — Monitoring, Detection & Threat Intelligence | D13: ='📊 Dashboard'!D9 -> 0.14 | E13: ='📊 Dashboard'!E9 -> 1.1111111 | F13: ='📊 Dashboard'!G9 -> 🔴 L1 — Initial | G13: ='📊 Dashboard'!H9 -> 3.3888889 | H13: ='📊 Dashboard'!L9 -> 🟠 High — Action This Quarter
C14: 🚨 RESPOND — Incident Management & Regulatory Notification | D14: ='📊 Dashboard'!D10 -> 0.11 | E14: ='📊 Dashboard'!E10 -> 1.2857143 | F14: ='📊 Dashboard'!G10 -> 🔴 L1 — Initial | G14: ='📊 Dashboard'!H10 -> 3.4285714 | H14: ='📊 Dashboard'!L10 -> 🟠 High — Action This Quarter
C15: ♻️ RECOVER — Resilience, Continuity & Validation | D15: ='📊 Dashboard'!D11 -> 0.1 | E15: ='📊 Dashboard'!E11 -> 1.0714286 | F15: ='📊 Dashboard'!G11 -> 🔴 L1 — Initial | G15: ='📊 Dashboard'!H11 -> 3.2142857 | H15: ='📊 Dashboard'!L11 -> 🟠 High — Action This Quarter
C16: WEIGHTED OVERALL | E16: ='📊 Dashboard'!E12 -> 1.2333444 | F16: ='📊 Dashboard'!G12 -> 🔴 L1 | G16: ='📊 Dashboard'!H12 -> 3.4034217 | H16: ='📊 Dashboard'!J12 -> L3
C18: 📌 BOARD GOVERNANCE NOTES
C19: Domains scoring below L3.0 require executive attention with named remediation owners and defined timelines.
C20: Any domain with Gap ≥ 3.0 levels should be escalated to the Board Risk Committee with a costed remediation plan within 30 days.
C21: Regulatory compliance floors override design maturity — unmet obligations cannot be remediated by documentation alone.
C22: An overall weighted score below 3.0 indicates the organisation has not achieved enterprise baseline and may face insurability challenges.
C23: Security investment must be board-approved annually with quarterly progress reporting against the 5-axis model.
C25: 💰 REMEDIATION COST SUMMARY
C26: Enter cost estimates in the Roadmap tab to auto-populate. All figures in base currency.
C27: Domain | D27: Controls | E27: Once-Off Cost | F27: Annual Cost | G27: Priority | H27: Est. ROI
C28: 🏛️ GOVERN | D28: 28 | E28: ='🗺️ Roadmap'!L194 -> 125250 | F28: ='🗺️ Roadmap'!M194 -> 0 | G28: ='📊 Dashboard'!L6 -> 🟠 High — Action This Quarter | H28: Quantify in Roadmap
C29: 🔍 IDENTIFY | D29: 22 | E29: ='🗺️ Roadmap'!L195 -> 172250 | F29: ='🗺️ Roadmap'!M195 -> 0 | G29: ='📊 Dashboard'!L7 -> 🟠 High — Action This Quarter | H29: Quantify in Roadmap
C30: 🛡️ PROTECT | D30: 83 | E30: ='🗺️ Roadmap'!L196 -> 393750 | F30: ='🗺️ Roadmap'!M196 -> 0 | G30: ='📊 Dashboard'!L8 -> 🟠 High — Action This Quarter | H30: Quantify in Roadmap
C31: 📡 DETECT | D31: 22 | E31: ='🗺️ Roadmap'!L197 -> 202250 | F31: ='🗺️ Roadmap'!M197 -> 36000 | G31: ='📊 Dashboard'!L9 -> 🟠 High — Action This Quarter | H31: Quantify in Roadmap
C32: 🚨 RESPOND | D32: 16 | E32: ='🗺️ Roadmap'!L198 -> 35000 | F32: ='🗺️ Roadmap'!M198 -> 0 | G32: ='📊 Dashboard'!L10 -> 🟠 High — Action This Quarter | H32: Quantify in Roadmap
C33: ♻️ RECOVER | D33: 17 | E33: ='🗺️ Roadmap'!L199 -> 77250 | F33: ='🗺️ Roadmap'!M199 -> 0 | G33: ='📊 Dashboard'!L11 -> 🟠 High — Action This Quarter | H33: Quantify in Roadmap
C34: TOTAL — ALL 188 CONTROLS | E34: ='🗺️ Roadmap'!L201 -> 1005750 | F34: ='🗺️ Roadmap'!M201 -> 36000
C36: 📌 COST GOVERNANCE: The total once-off investment represents the estimated cost to achieve target maturity across all assessed domains. Annual recurring costs represent sustained operational investment required to maintain the target security posture. Boards should approve these costs against regulatory fine exposure and cyber debt risk quantified in the Domain Assessment report.

Sheet 🗺️ Roadmap
A1: NUCLEUS SYSTEMS | NS-CMMF v1.0 — SECURITY IMPROVEMENT ROADMAP — 188 CONTROLS | Cost Model & Prioritisation
A2: Auto-populated from domain ratings · Priority Score = Gap × Domain Weight · Col D = auto-generated recommendation (rate controls in domain tabs first) · Enter costs in J–M · Assign owners in G and target quarters in F
A3: Assessment & Planning | I3: Notes | J3: Cost Inputs — Enter Estimates | N3: Auto-Totals | P3: Assumptions
A4: Priority Score | B4: Domain | C4: Control Name | D4: Recommended Action | E4: Effort Estimate | F4: Target Quarter | G4: Owner | H4: Status | I4: Notes | J4: Internal Cost (Staff Time) | K4: External Once-Off | L4: External Recurring /yr | M4: Software / Tool Cost | N4: Total Once-Off | O4: Total Annual | P4: Cost Assumptions
A5: 0.16 | B5: 🏛️ GV Govern | C5: CISO / Security Leadership | D5: =IFERROR(IF('GV Govern'!P4="⏳ Complete rating and target to generate recommendation.","⏳ Rate this control in the domain sheet to auto-generate.",'GV Govern'!P4),"—") -> Standardise CISO / Security Leadership: formalise all documentation, apply the control consistently across all in-scope assets, close remaining coverage gaps, and ensure evidence is collected routinely. Exceptions must be formally managed with named owners and defined expiry dates. | E5: High (1-3 months) | F5: Q2 2027 | G5: Jean-Paul Nkeng — Managing Director | H5: Not Started | J5: 3000 | K5: 0 | L5: 0 | M5: 0 | N5: =IFERROR(SUM(J5,K5,M5),0) -> 3000 | O5: =IFERROR(SUM(L5),0) -> 0 | P5: Illustrative estimate (USD). Internal cost = staff days x 250/day blended rate. External and tool costs are indicative list pricing, not quotations.
A6: 0.32 | B6: 🏛️ GV Govern | C6: Cybersecurity Strategy & Programme | D6: =IFERROR(IF('GV Govern'!P5="⏳ Complete rating and target to generate recommendation.","⏳ Rate this control in the domain sheet to auto-generate.",'GV Govern'!P5),"—") -> Standardise Cybersecurity Strategy & Programme: formalise all documentation, apply the control consistently across all in-scope assets, close remaining coverage gaps, and ensure evidence is collected routinely. Exceptions must be formally managed with named owners and defined expiry dates. | E6: High (1-3 months) | F6: Q2 2027 | G6: Jean-Paul Nkeng — Managing Director | H6: Not Started | J6: 3000 | N6: =IFERROR(SUM(J6,K6,M6),0) -> 3000 | O6: =IFERROR(SUM(L6),0) -> 0 | P6: Illustrative estimate (USD). Internal cost = staff days x 250/day blended rate. External and tool costs are indicative list pricing, not quotations.
A7: 0.32 | B7: 🏛️ GV Govern | C7: Cyber Budget & Investment Model | D7: =IFERROR(IF('GV Govern'!P6="⏳ Complete rating and target to generate recommendation.","⏳ Rate this control in the domain sheet to auto-generate.",'GV Govern'!P6),"—") -> Standardise Cyber Budget & Investment Model: formalise all documentation, apply the control consistently across all in-scope assets, close remaining coverage gaps, and ensure evidence is collected routinely. Exceptions must be formally managed with named owners and defined expiry dates. | E7: Medium (1-4 weeks) | F7: Q3 2027 | G7: Paul Mbarga — Finance Director | H7: Not Started | J7: 1250 | N7: =IFERROR(SUM(J7,K7,M7),0) -> 1250 | O7: =IFERROR(SUM(L7),0) -> 0 | P7: Illustrative estimate (USD). Internal cost = staff days x 250/day blended rate. External and tool costs are indicative list pricing, not quotations.
A8: 0.16 | B8: 🏛️ GV Govern | C8: Security Organisational Structure | D8: =IFERROR(IF('GV Govern'!P7="⏳ Complete rating and target to generate recommendation.","⏳ Rate this control in the domain sheet to auto-generate.",'GV Govern'!P7),"—") -> Standardise Security Organisational Structure: formalise all documentation, apply the control consistently across all in-scope assets, close remaining coverage gaps, and ensure evidence is collected routinely. Exceptions must be formally managed with named owners and defined expiry dates. | E8: High (1-3 months) | F8: Q2 2027 | G8: Marc Etonde — Head of IT | H8: Not Started | J8: 3000 | N8: =IFERROR(SUM(J8,K8,M8),0) -> 3000 | O8: =IFERROR(SUM(L8),0) -> 0 | P8: Illustrative estimate (USD). Internal cost = staff days x 250/day blended rate. External and tool costs are indicative list pricing, not quotations.
A9: 0.32 | B9: 🏛️ GV Govern | C9: Board-Level Cybersecurity Oversight | D9: =IFERROR(IF('GV Govern'!P8="⏳ Complete rating and target to generate recommendation.","⏳ Rate this control in the domain sheet to auto-generate.",'GV Govern'!P8),"—") -> Standardise Board-Level Cybersecurity Oversight: formalise all documentation, apply the control consistently across all in-scope assets, close remaining coverage gaps, and ensure evidence is collected routinely. Exceptions must be formally managed with named owners and defined expiry dates. | E9: High (1-3 months) | F9: Q2 2027 | G9: Jean-Paul Nkeng — Managing Director | H9: Not Started | J9: 3000 | N9: =IFERROR(SUM(J9,K9,M9),0) -> 3000 | O9: =IFERROR(SUM(L9),0) -> 0 | P9: Illustrative estimate (USD). Internal cost = staff days x 250/day blended rate. External and tool costs are indicative list pricing, not quotations.
A10: 0.16 | B10: 🏛️ GV Govern | C10: Security Policy Framework & Hierarchy | D10: =IFERROR(IF('GV Govern'!P9="⏳ Complete rating and target to generate recommendation.","⏳ Rate this control in the domain sheet to auto-generate.",'GV Govern'!P9),"—") -> Standardise Security Policy Framework & Hierarchy: formalise all documentation, apply the control consistently across all in-scope assets, close remaining coverage gaps, and ensure evidence is collected routinely. Exceptions must be formally managed with named owners and defined expiry dates. | E10: Medium (1-4 weeks) | F10: Q3 2027 | G10: Marie Fotso — Legal & Compliance Counsel | H10: Not Started | J10: 1250 | N10: =IFERROR(SUM(J10,K10,M10),0) -> 1250 | O10: =IFERROR(SUM(L10),0) -> 0 | P10: Illustrative estimate (USD). Internal cost = staff days x 250/day blended rate. External and tool costs are indicative list pricing, not quotations.
A11: 0.16 | B11: 🏛️ GV Govern | C11: Policy Attestation & Enforcement | D11: =IFERROR(IF('GV Govern'!P10="⏳ Complete rating and target to generate recommendation.","⏳ Rate this control in the domain sheet to auto-generate.",'GV Govern'!P10),"—") -> Standardise Policy Attestation & Enforcement: formalise all documentation, apply the control consistently across all in-scope assets, close remaining coverage gaps, and ensure evidence is collected routinely. Exceptions must be formally managed with named owners and defined expiry dates. | E11: Medium (1-4 weeks) | F11: Q3 2027 | G11: Ruth Anong — HR Manager | H11: Not Started | J11: 1250 | N11: =IFERROR(SUM(J11,K11,M11),0) -> 1250 | O11: =IFERROR(SUM(L11),0) -> 0 | P11: Illustrative estimate (USD). Internal cost = staff days x 250/day blended rate. External and tool costs are indicative list pricing, not quotations.
A12: 0.32 | B12: 🏛️ GV Govern | C12: Policy Exception Governance | D12: =IFERROR(IF('GV Govern'!P11="⏳ Complete rating and target to generate recommendation.","⏳ Rate this control in the domain sheet to auto-generate.",'GV Govern'!P11),"—") -> Standardise Policy Exception Governance: formalise all documentation, apply the control consistently across all in-scope assets, close remaining coverage gaps, and ensure evidence is collected routinely. Exceptions must be formally managed with named owners and defined expiry dates. | E12: High (1-3 months) | F12: Q2 2027 | G12: Marc Etonde — Head of IT | H12: Not Started | J12: 3000 | N12: =IFERROR(SUM(J12,K12,M12),0) -> 3000 | O12: =IFERROR(SUM(L12),0) -> 0 | P12: Illustrative estimate (USD). Internal cost = staff days x 250/day blended rate. External and tool costs are indicative list pricing, not quotations.
A13: 0.32 | B13: 🏛️ GV Govern | C13: Control Standards Management | D13: =IFERROR(IF('GV Govern'!P12="⏳ Complete rating and target to generate recommendation.","⏳ Rate this control in the domain sheet to auto-generate.",'GV Govern'!P12),"—") -> Standardise Control Standards Management: formalise all documentation, apply the control consistently across all in-scope assets, close remaining coverage gaps, and ensure evidence is collected routinely. Exceptions must be formally managed with named owners and defined expiry dates. | E13: High (1-3 months) | F13: Q2 2027 | G13: Marc Etonde — Head of IT | H13: Not Started | J13: 3000 | N13: =IFERROR(SUM(J13,K13,M13),0) -> 3000 | O13: =IFERROR(SUM(L13),0) -> 0 | P13: Illustrative estimate (USD). Internal cost = staff days x 250/day blended rate. External and tool costs are indicative list pricing, not quotations.
A14: 0.32 | B14: 🏛️ GV Govern | C14: Regulatory Obligation Register & Mapping | D14: =IFERROR(IF('GV Govern'!P13="⏳ Complete rating and target to generate recommendation.","⏳ Rate this control in the domain sheet to auto-generate.",'GV Govern'!P13),"—") -> Instrument Regulatory Obligation Register & Mapping with measurable KPIs: define performance thresholds (coverage %, SLA adherence, exception count), establish automated telemetry where possible, and integrate reporting into quarterly governance cycles. Evidence must be system-generated and reviewed at each governance cycle. | E14: High (1-3 months) | F14: Q1 2027 | G14: Marie Fotso — Legal & Compliance Counsel | H14: Not Started | J14: 3000 | N14: =IFERROR(SUM(J14,K14,M14),0) -> 3000 | O14: =IFERROR(SUM(L14),0) -> 0 | P14: Illustrative estimate (USD). Internal cost = staff days x 250/day blended rate. External and tool costs are indicative list pricing, not quotations.
A15: 0.48 | B15: 🏛️ GV Govern | C15: Regulatory Change Management | D15: =IFERROR(IF('GV Govern'!P14="⏳ Complete rating and target to generate recommendation.","⏳ Rate this control in the domain sheet to auto-generate.",'GV Govern'!P14),"—") -> Instrument Regulatory Change Management with measurable KPIs: define performance thresholds (coverage %, SLA adherence, exception count), establish automated telemetry where possible, and integrate reporting into quarterly governance cycles. Evidence must be system-generated and reviewed at each governance cycle. | E15: High (1-3 months) | F15: Q1 2027 | G15: Marie Fotso — Legal & Compliance Counsel | H15: Not Started | J15: 3000 | N15: =IFERROR(SUM(J15,K15,M15),0) -> 3000 | O15: =IFERROR(SUM(L15),0) -> 0 | P15: Illustrative estimate (USD). Internal cost = staff days x 250/day blended rate. External and tool costs are indicative list pricing, not quotations.
A16: 0.48 | B16: 🏛️ GV Govern | C16: Security Standards for Third Parties | D16: =IFERROR(IF('GV Govern'!P15="⏳ Complete rating and target to generate recommendation.","⏳ Rate this control in the domain sheet to auto-generate.",'GV Govern'!P15),"—") -> Instrument Security Standards for Third Parties with measurable KPIs: define performance thresholds (coverage %, SLA adherence, exception count), establish automated telemetry where possible, and integrate reporting into quarterly governance cycles. Evidence must be system-generated and reviewed at each governance cycle. | E16: High (1-3 months) | F16: Q1 2027 | G16: Linda Ojo — Procurement Officer | H16: Not Started | J16: 3000 | N16: =IFERROR(SUM(J16,K16,M16),0) -> 3000 | O16: =IFERROR(SUM(L16),0) -> 0 | P16: Illustrative estimate (USD). Internal cost = staff days x 250/day blended rate. External and tool costs are indicative list pricing, not quotations.
A17: 0.16 | B17: 🏛️ GV Govern | C17: Enterprise Risk Framework Integration | D17: =IFERROR(IF('GV Govern'!P16="⏳ Complete rating and target to generate recommendation.","⏳ Rate this control in the domain sheet to auto-generate.",'GV Govern'!P16),"—") -> Standardise Enterprise Risk Framework Integration: formalise all documentation, apply the control consistently across all in-scope assets, close remaining coverage gaps, and ensure evidence is collected routinely. Exceptions must be formally managed with named owners and defined expiry dates. | E17: High (1-3 months) | F17: Q2 2027 | G17: Marc Etonde — Head of IT | H17: Not Started | J17: 3000 | N17: =IFERROR(SUM(J17,K17,M17),0) -> 3000 | O17: =IFERROR(SUM(L17),0) -> 0 | P17: Illustrative estimate (USD). Internal cost = staff days x 250/day blended rate. External and tool costs are indicative list pricing, not quotations.
... A24: 0.48 | B24: 🏛️ GV Govern | C24: Fourth-Party & Sub-Processor Mapping | D24: =IFERROR(IF('GV Govern'!P23="⏳ Complete rating and target to generate recommendation.","⏳ Rate this control in the domain sheet to auto-generate.",'GV Govern'!P23),"—") -> Instrument Fourth-Party & Sub-Processor Mapping with measurable KPIs: define performance thresholds (coverage %, SLA adherence, exception count), establish automated telemetry where possible, and integrate reporting into quarterly governance cycles. Evidence must be system-generated and reviewed at each governance cycle. | E24: High (1-3 months) | F24: Q1 2027 | G24: Linda Ojo — Procurement Officer | H24: Not Started | J24: 3000 | N24: =IFERROR(SUM(J24,K24,M24),0) -> 3000 | O24: =IFERROR(SUM(L24),0) -> 0 | P24: Illustrative estimate (USD). Internal cost = staff days x 250/day blended rate. External and tool costs are indicative list pricing, not quotations.
A25: 0 | B25: 🏛️ GV Govern | C25: DORA TPSP Critical Register | D25: =IFERROR(IF('GV Govern'!P24="⏳ Complete rating and target to generate recommendation.","⏳ Rate this control in the domain sheet to auto-generate.",'GV Govern'!P24),"—") -> ⏳ Rate this control in the domain sheet to auto-generate. | G25: Linda Ojo — Procurement Officer | H25: Deferred | N25: =IFERROR(SUM(J25,K25,M25),0) -> 0 | O25: =IFERROR(SUM(L25),0) -> 0 | P25: Out of scope for this organisation — no cost carried.
A26: 0.16 | B26: 🏛️ GV Govern | C26: Software Supply Chain Security Governance | D26: =IFERROR(IF('GV Govern'!P25="⏳ Complete rating and target to generate recommendation.","⏳ Rate this control in the domain sheet to auto-generate.",'GV Govern'!P25),"—") -> Standardise Software Supply Chain Security Governance: formalise all documentation, apply the control consistently across all in-scope assets, close remaining coverage gaps, and ensure evidence is collected routinely. Exceptions must be formally managed with named owners and defined expiry dates. | E26: High (1-3 months) | F26: Q2 2027 | G26: Tunde Balogun — Lead Software Engineer | H26: Not Started | J26: 3000 | N26: =IFERROR(SUM(J26,K26,M26),0) -> 3000 | O26: =IFERROR(SUM(L26),0) -> 0 | P26: Illustrative estimate (USD). Internal cost = staff days x 250/day blended rate. External and tool costs are indicative list pricing, not quotations.
A27: 0.32 | B27: 🏛️ GV Govern | C27: Supplier Resilience Requirements | D27: =IFERROR(IF('GV Govern'!P26="⏳ Complete rating and target to generate recommendation.","⏳ Rate this control in the domain sheet to auto-generate.",'GV Govern'!P26),"—") -> Standardise Supplier Resilience Requirements: formalise all documentation, apply the control consistently across all in-scope assets, close remaining coverage gaps, and ensure evidence is collected routinely. Exceptions must be formally managed with named owners and defined expiry dates. | E27: High (1-3 months) | F27: Q2 2027 | G27: Linda Ojo — Procurement Officer | H27: Not Started | J27: 3000 | N27: =IFERROR(SUM(J27,K27,M27),0) -> 3000 | O27: =IFERROR(SUM(L27),0) -> 0 | P27: Illustrative estimate (USD). Internal cost = staff days x 250/day blended rate. External and tool costs are indicative list pricing, not quotations.
A28: 0.48 | B28: 🏛️ GV Govern | C28: Privacy Governance & DPO/Privacy Lead | D28: =IFERROR(IF('GV Govern'!P27="⏳ Complete rating and target to generate recommendation.","⏳ Rate this control in the domain sheet to auto-generate.",'GV Govern'!P27),"—") -> Instrument Privacy Governance & DPO/Privacy Lead with measurable KPIs: define performance thresholds (coverage %, SLA adherence, exception count), establish automated telemetry where possible, and integrate reporting into quarterly governance cycles. Evidence must be system-generated and reviewed at each governance cycle. | E28: High (1-3 months) | F28: Q2 2027 | G28: Marie Fotso — Legal & Compliance Counsel | H28: Not Started | J28: 3000 | K28: 0 | L28: 0 | M28: 0 | N28: =IFERROR(SUM(J28,K28,M28),0) -> 3000 | O28: =IFERROR(SUM(L28),0) -> 0 | P28: Illustrative estimate (USD). Internal cost = staff days x 250/day blended rate. External and tool costs are indicative list pricing, not quotations.
A29: 0.32 | B29: 🏛️ GV Govern | C29: Records of Processing Activities (ROPA) | D29: =IFERROR(IF('GV Govern'!P28="⏳ Complete rating and target to generate recommendation.","⏳ Rate this control in the domain sheet to auto-generate.",'GV Govern'!P28),"—") -> Instrument Records of Processing Activities (ROPA) with measurable KPIs: define performance thresholds (coverage %, SLA adherence, exception count), establish automated telemetry where possible, and integrate reporting into quarterly governance cycles. Evidence must be system-generated and reviewed at each governance cycle. | E29: High (1-3 months) | F29: Q1 2027 | G29: Marie Fotso — Legal & Compliance Counsel | H29: Not Started | J29: 3000 | N29: =IFERROR(SUM(J29,K29,M29),0) -> 3000 | O29: =IFERROR(SUM(L29),0) -> 0 | P29: Illustrative estimate (USD). Internal cost = staff days x 250/day blended rate. External and tool costs are indicative list pricing, not quotations.
A30: 0.48 | B30: 🏛️ GV Govern | C30: Data Protection Impact Assessments (DPIAs) | D30: =IFERROR(IF('GV Govern'!P29="⏳ Complete rating and target to generate recommendation.","⏳ Rate this control in the domain sheet to auto-generate.",'GV Govern'!P29),"—") -> Instrument Data Protection Impact Assessments (DPIAs) with measurable KPIs: define performance thresholds (coverage %, SLA adherence, exception count), establish automated telemetry where possible, and integrate reporting into quarterly governance cycles. Evidence must be system-generated and reviewed at each governance cycle. | E30: High (1-3 months) | F30: Q1 2027 | G30: Marie Fotso — Legal & Compliance Counsel | H30: Not Started | J30: 3000 | N30: =IFERROR(SUM(J30,K30,M30),0) -> 3000 | O30: =IFERROR(SUM(L30),0) -> 0 | P30: Illustrative estimate (USD). Internal cost = staff days x 250/day blended rate. External and tool costs are indicative list pricing, not quotations.
A31: 0.48 | B31: 🏛️ GV Govern | C31: Cross-Border Data Transfer Controls | D31: =IFERROR(IF('GV Govern'!P30="⏳ Complete rating and target to generate recommendation.","⏳ Rate this control in the domain sheet to auto-generate.",'GV Govern'!P30),"—") -> Instrument Cross-Border Data Transfer Controls with measurable KPIs: define performance thresholds (coverage %, SLA adherence, exception count), establish automated telemetry where possible, and integrate reporting into quarterly governance cycles. Evidence must be system-generated and reviewed at each governance cycle. | E31: High (1-3 months) | F31: Q1 2027 | G31: Marie Fotso — Legal & Compliance Counsel | H31: Not Started | J31: 3000 | N31: =IFERROR(SUM(J31,K31,M31),0) -> 3000 | O31: =IFERROR(SUM(L31),0) -> 0 | P31: Illustrative estimate (USD). Internal cost = staff days x 250/day blended rate. External and tool costs are indicative list pricing, not quotations.
A32: 0.16 | B32: 🏛️ GV Govern | C32: Internal & External Audit Programme | D32: =IFERROR(IF('GV Govern'!P31="⏳ Complete rating and target to generate recommendation.","⏳ Rate this control in the domain sheet to auto-generate.",'GV Govern'!P31),"—") -> Standardise Internal & External Audit Programme: formalise all documentation, apply the control consistently across all in-scope assets, close remaining coverage gaps, and ensure evidence is collected routinely. Exceptions must be formally managed with named owners and defined expiry dates. | E32: High (1-3 months) | F32: Q2 2027 | G32: Jean-Paul Nkeng — Managing Director | H32: Not Started | J32: 3000 | K32: 45000 | L32: 0 | M32: 0 | N32: =IFERROR(SUM(J32,K32,M32),0) -> 48000 | O32: =IFERROR(SUM(L32),0) -> 0 | P32: Illustrative estimate (USD). Internal cost = staff days x 250/day blended rate. External and tool costs are indicative list pricing, not quotations.
A33: 0.1 | B33: 🔍 ID Identify | C33: IT Hardware Asset Inventory (CMDB) | D33: =IFERROR(IF('ID Identify'!P4="⏳ Complete rating and target to generate recommendation.","⏳ Rate this control in the domain sheet to auto-generate.",'ID Identify'!P4),"—") -> Standardise IT Hardware Asset Inventory (CMDB): formalise all documentation, apply the control consistently across all in-scope assets, close remaining coverage gaps, and ensure evidence is collected routinely. Exceptions must be formally managed with named owners and defined expiry dates. | E33: Medium (1-4 weeks) | F33: Q3 2027 | G33: Grace Ayuk — IT Operations Manager | H33: Not Started | J33: 1250 | N33: =IFERROR(SUM(J33,K33,M33),0) -> 1250 | O33: =IFERROR(SUM(L33),0) -> 0 | P33: Illustrative estimate (USD). Internal cost = staff days x 250/day blended rate. External and tool costs are indicative list pricing, not quotations.
A34: 0.1 | B34: 🔍 ID Identify | C34: Software Asset Inventory | D34: =IFERROR(IF('ID Identify'!P5="⏳ Complete rating and target to generate recommendation.","⏳ Rate this control in the domain sheet to auto-generate.",'ID Identify'!P5),"—") -> Standardise Software Asset Inventory: formalise all documentation, apply the control consistently across all in-scope assets, close remaining coverage gaps, and ensure evidence is collected routinely. Exceptions must be formally managed with named owners and defined expiry dates. | E34: High (1-3 months) | F34: Q3 2027 | G34: Grace Ayuk — IT Operations Manager | H34: Not Started | J34: 3000 | N34: =IFERROR(SUM(J34,K34,M34),0) -> 3000 | O34: =IFERROR(SUM(L34),0) -> 0 | P34: Illustrative estimate (USD). Internal cost = staff days x 250/day blended rate. External and tool costs are indicative list pricing, not quotations.
A35: 0.1 | B35: 🔍 ID Identify | C35: Cloud Infrastructure Asset Inventory | D35: =IFERROR(IF('ID Identify'!P6="⏳ Complete rating and target to generate recommendation.","⏳ Rate this control in the domain sheet to auto-generate.",'ID Identify'!P6),"—") -> Standardise Cloud Infrastructure Asset Inventory: formalise all documentation, apply the control consistently across all in-scope assets, close remaining coverage gaps, and ensure evidence is collected routinely. Exceptions must be formally managed with named owners and defined expiry dates. | E35: Medium (1-4 weeks) | F35: Q3 2027 | G35: Sam Ncube — DevOps Engineer | H35: Not Started | J35: 1250 | N35: =IFERROR(SUM(J35,K35,M35),0) -> 1250 | O35: =IFERROR(SUM(L35),0) -> 0 | P35: Illustrative estimate (USD). Internal cost = staff days x 250/day blended rate. External and tool costs are indicative list pricing, not quotations.
A36: 0.2 | B36: 🔍 ID Identify | C36: SaaS & Shadow IT Discovery | D36: =IFERROR(IF('ID Identify'!P7="⏳ Complete rating and target to generate recommendation.","⏳ Rate this control in the domain sheet to auto-generate.",'ID Identify'!P7),"—") -> Instrument SaaS & Shadow IT Discovery with measurable KPIs: define performance thresholds (coverage %, SLA adherence, exception count), establish automated telemetry where possible, and integrate reporting into quarterly governance cycles. Evidence must be system-generated and reviewed at each governance cycle. | E36: High (1-3 months) | F36: Q2 2027 | G36: Marc Etonde — Head of IT | H36: Not Started | J36: 3000 | N36: =IFERROR(SUM(J36,K36,M36),0) -> 3000 | O36: =IFERROR(SUM(L36),0) -> 0 | P36: Illustrative estimate (USD). Internal cost = staff days x 250/day blended rate. External and tool costs are indicative list pricing, not quotations.
A37: 0 | B37: 🔍 ID Identify | C37: Software Bill of Materials (SBOM) | D37: =IFERROR(IF('ID Identify'!P8="⏳ Complete rating and target to generate recommendation.","⏳ Rate this control in the domain sheet to auto-generate.",'ID Identify'!P8),"—") -> Standardise Software Bill of Materials (SBOM): formalise all documentation, apply the control consistently across all in-scope assets, close remaining coverage gaps, and ensure evidence is collected routinely. Exceptions must be formally managed with named owners and defined expiry dates. | E37: High (1-3 months) | F37: Q3 2027 | G37: Tunde Balogun — Lead Software Engineer | H37: Not Started | J37: 3000 | N37: =IFERROR(SUM(J37,K37,M37),0) -> 3000 | O37: =IFERROR(SUM(L37),0) -> 0 | P37: Illustrative estimate (USD). Internal cost = staff days x 250/day blended rate. External and tool costs are indicative list pricing, not quotations.
A38: 0.3 | B38: 🔍 ID Identify | C38: Network Topology & Architecture Documentation | D38: =IFERROR(IF('ID Identify'!P9="⏳ Complete rating and target to generate recommendation.","⏳ Rate this control in the domain sheet to auto-generate.",'ID Identify'!P9),"—") -> Instrument Network Topology & Architecture Documentation with measurable KPIs: define performance thresholds (coverage %, SLA adherence, exception count), establish automated telemetry where possible, and integrate reporting into quarterly governance cycles. Evidence must be system-generated and reviewed at each governance cycle. | E38: High (1-3 months) | F38: Q3 2027 | G38: Marc Etonde — Head of IT | H38: Not Started | J38: 3000 | N38: =IFERROR(SUM(J38,K38,M38),0) -> 3000 | O38: =IFERROR(SUM(L38),0) -> 0 | P38: Illustrative estimate (USD). Internal cost = staff days x 250/day blended rate. External and tool costs are indicative list pricing, not quotations.
A39: 0.1 | B39: 🔍 ID Identify | C39: Technology Lifecycle Management | D39: =IFERROR(IF('ID Identify'!P10="⏳ Complete rating and target to generate recommendation.","⏳ Rate this control in the domain sheet to auto-generate.",'ID Identify'!P10),"—") -> Standardise Technology Lifecycle Management: formalise all documentation, apply the control consistently across all in-scope assets, close remaining coverage gaps, and ensure evidence is collected routinely. Exceptions must be formally managed with named owners and defined expiry dates. | E39: High (1-3 months) | F39: Q3 2027 | G39: Grace Ayuk — IT Operations Manager | H39: Not Started | J39: 3000 | N39: =IFERROR(SUM(J39,K39,M39),0) -> 3000 | O39: =IFERROR(SUM(L39),0) -> 0 | P39: Illustrative estimate (USD). Internal cost = staff days x 250/day blended rate. External and tool costs are indicative list pricing, not quotations.
A40: 0.3 | B40: 🔍 ID Identify | C40: Data Classification Framework & Implementation | D40: =IFERROR(IF('ID Identify'!P11="⏳ Complete rating and target to generate recommendation.","⏳ Rate this control in the domain sheet to auto-generate.",'ID Identify'!P11),"—") -> Instrument Data Classification Framework & Implementation with measurable KPIs: define performance thresholds (coverage %, SLA adherence, exception count), establish automated telemetry where possible, and integrate reporting into quarterly governance cycles. Evidence must be system-generated and reviewed at each governance cycle. | E40: High (1-3 months) | F40: Q2 2027 | G40: Marie Fotso — Legal & Compliance Counsel | H40: Not Started | J40: 3000 | N40: =IFERROR(SUM(J40,K40,M40),0) -> 3000 | O40: =IFERROR(SUM(L40),0) -> 0 | P40: Illustrative estimate (USD). Internal cost = staff days x 250/day blended rate. External and tool costs are indicative list pricing, not quotations.
A41: 0.3 | B41: 🔍 ID Identify | C41: Sensitive Data Discovery & Mapping | D41: =IFERROR(IF('ID Identify'!P12="⏳ Complete rating and target to generate recommendation.","⏳ Rate this control in the domain sheet to auto-generate.",'ID Identify'!P12),"—") -> Instrument Sensitive Data Discovery & Mapping with measurable KPIs: define performance thresholds (coverage %, SLA adherence, exception count), establish automated telemetry where possible, and integrate reporting into quarterly governance cycles. Evidence must be system-generated and reviewed at each governance cycle. | E41: High (1-3 months) | F41: Q2 2027 | G41: Marie Fotso — Legal & Compliance Counsel | H41: Not Started | J41: 3000 | N41: =IFERROR(SUM(J41,K41,M41),0) -> 3000 | O41: =IFERROR(SUM(L41),0) -> 0 | P41: Illustrative estimate (USD). Internal cost = staff days x 250/day blended rate. External and tool costs are indicative list pricing, not quotations.
A42: 0.2 | B42: 🔍 ID Identify | C42: Data Flow & Transfer Mapping | D42: =IFERROR(IF('ID Identify'!P13="⏳ Complete rating and target to generate recommendation.","⏳ Rate this control in the domain sheet to auto-generate.",'ID Identify'!P13),"—") -> Instrument Data Flow & Transfer Mapping with measurable KPIs: define performance thresholds (coverage %, SLA adherence, exception count), establish automated telemetry where possible, and integrate reporting into quarterly governance cycles. Evidence must be system-generated and reviewed at each governance cycle. | E42: High (1-3 months) | F42: Q2 2027 | G42: Sam Ncube — DevOps Engineer | H42: Not Started | J42: 3000 | N42: =IFERROR(SUM(J42,K42,M42),0) -> 3000 | O42: =IFERROR(SUM(L42),0) -> 0 | P42: Illustrative estimate (USD). Internal cost = staff days x 250/day blended rate. External and tool costs are indicative list pricing, not quotations.
A43: 0.3 | B43: 🔍 ID Identify | C43: Retention Schedule & Disposal Management | D43: =IFERROR(IF('ID Identify'!P14="⏳ Complete rating and target to generate recommendation.","⏳ Rate this control in the domain sheet to auto-generate.",'ID Identify'!P14),"—") -> Instrument Retention Schedule & Disposal Management with measurable KPIs: define performance thresholds (coverage %, SLA adherence, exception count), establish automated telemetry where possible, and integrate reporting into quarterly governance cycles. Evidence must be system-generated and reviewed at each governance cycle. | E43: High (1-3 months) | F43: Q2 2027 | G43: Marie Fotso — Legal & Compliance Counsel | H43: Not Started | J43: 3000 | N43: =IFERROR(SUM(J43,K43,M43),0) -> 3000 | O43: =IFERROR(SUM(L43),0) -> 0 | P43: Illustrative estimate (USD). Internal cost = staff days x 250/day blended rate. External and tool costs are indicative list pricing, not quotations.
A44: 0.3 | B44: 🔍 ID Identify | C44: Payment Data Scoping & CDE Mapping | D44: =IFERROR(IF('ID Identify'!P15="⏳ Complete rating and target to generate recommendation.","⏳ Rate this control in the domain sheet to auto-generate.",'ID Identify'!P15),"—") -> Instrument Payment Data Scoping & CDE Mapping with measurable KPIs: define performance thresholds (coverage %, SLA adherence, exception count), establish automated telemetry where possible, and integrate reporting into quarterly governance cycles. Evidence must be system-generated and reviewed at each governance cycle. | E44: Very High (3+ months) | F44: Q2 2027 | G44: Sam Ncube — DevOps Engineer | H44: Not Started | J44: 7500 | K44: 40000 | L44: 0 | M44: 0 | N44: =IFERROR(SUM(J44,K44,M44),0) -> 47500 | O44: =IFERROR(SUM(L44),0) -> 0 | P44: Illustrative estimate (USD). Internal cost = staff days x 250/day blended rate. External and tool costs are indicative list pricing, not quotations.
A45: 0.1 | B45: 🔍 ID Identify | C45: Business Impact Analysis (BIA) | D45: =IFERROR(IF('ID Identify'!P16="⏳ Complete rating and target to generate recommendation.","⏳ Rate this control in the domain sheet to auto-generate.",'ID Identify'!P16),"—") -> Standardise Business Impact Analysis (BIA): formalise all documentation, apply the control consistently across all in-scope assets, close remaining coverage gaps, and ensure evidence is collected routinely. Exceptions must be formally managed with named owners and defined expiry dates. | E45: High (1-3 months) | F45: Q3 2027 | G45: Grace Ayuk — IT Operations Manager | H45: Not Started | J45: 3000 | N45: =IFERROR(SUM(J45,K45,M45),0) -> 3000 | O45: =IFERROR(SUM(L45),0) -> 0 | P45: Illustrative estimate (USD). Internal cost = staff days x 250/day blended rate. External and tool costs are indicative list pricing, not quotations.
A46: 0.2 | B46: 🔍 ID Identify | C46: Threat Landscape Assessment | D46: =IFERROR(IF('ID Identify'!P17="⏳ Complete rating and target to generate recommendation.","⏳ Rate this control in the domain sheet to auto-generate.",'ID Identify'!P17),"—") -> Standardise Threat Landscape Assessment: formalise all documentation, apply the control consistently across all in-scope assets, close remaining coverage gaps, and ensure evidence is collected routinely. Exceptions must be formally managed with named owners and defined expiry dates. | E46: High (1-3 months) | F46: Q3 2027 | G46: Aicha Bello — Security Analyst | H46: Not Started | J46: 3000 | N46: =IFERROR(SUM(J46,K46,M46),0) -> 3000 | O46: =IFERROR(SUM(L46),0) -> 0 | P46: Illustrative estimate (USD). Internal cost = staff days x 250/day blended rate. External and tool costs are indicative list pricing, not quotations.
A47: 0.3 | B47: 🔍 ID Identify | C47: Vulnerability Management Programme | D47: =IFERROR(IF('ID Identify'!P18="⏳ Complete rating and target to generate recommendation.","⏳ Rate this control in the domain sheet to auto-generate.",'ID Identify'!P18),"—") -> Instrument Vulnerability Management Programme with measurable KPIs: define performance thresholds (coverage %, SLA adherence, exception count), establish automated telemetry where possible, and integrate reporting into quarterly governance cycles. Evidence must be system-generated and reviewed at each governance cycle. | E47: High (1-3 months) | F47: Q3 2027 | G47: Aicha Bello — Security Analyst | H47: Not Started | J47: 3000 | K47: 0 | L47: 0 | M47: 18000 | N47: =IFERROR(SUM(J47,K47,M47),0) -> 21000 | O47: =IFERROR(SUM(L47),0) -> 0 | P47: Illustrative estimate (USD). Internal cost = staff days x 250/day blended rate. External and tool costs are indicative list pricing, not quotations.
A48: 0.2 | B48: 🔍 ID Identify | C48: Penetration Testing Programme | D48: =IFERROR(IF('ID Identify'!P19="⏳ Complete rating and target to generate recommendation.","⏳ Rate this control in the domain sheet to auto-generate.",'ID Identify'!P19),"—") -> Instrument Penetration Testing Programme with measurable KPIs: define performance thresholds (coverage %, SLA adherence, exception count), establish automated telemetry where possible, and integrate reporting into quarterly governance cycles. Evidence must be system-generated and reviewed at each governance cycle. | E48: Medium (1-4 weeks) | F48: Q3 2027 | G48: Aicha Bello — Security Analyst | H48: Not Started | J48: 1250 | N48: =IFERROR(SUM(J48,K48,M48),0) -> 1250 | O48: =IFERROR(SUM(L48),0) -> 0 | P48: Illustrative estimate (USD). Internal cost = staff days x 250/day blended rate. External and tool costs are indicative list pricing, not quotations.
A49: 0.2 | B49: 🔍 ID Identify | C49: Third-Party Security Rating Monitoring | D49: =IFERROR(IF('ID Identify'!P20="⏳ Complete rating and target to generate recommendation.","⏳ Rate this control in the domain sheet to auto-generate.",'ID Identify'!P20),"—") -> Standardise Third-Party Security Rating Monitoring: formalise all documentation, apply the control consistently across all in-scope assets, close remaining coverage gaps, and ensure evidence is collected routinely. Exceptions must be formally managed with named owners and defined expiry dates. | E49: High (1-3 months) | F49: Q3 2027 | G49: Linda Ojo — Procurement Officer | H49: Not Started | J49: 3000 | N49: =IFERROR(SUM(J49,K49,M49),0) -> 3000 | O49: =IFERROR(SUM(L49),0) -> 0 | P49: Illustrative estimate (USD). Internal cost = staff days x 250/day blended rate. External and tool costs are indicative list pricing, not quotations.
A50: 0.1 | B50: 🔍 ID Identify | C50: Critical Asset Identification & Prioritisation | D50: =IFERROR(IF('ID Identify'!P21="⏳ Complete rating and target to generate recommendation.","⏳ Rate this control in the domain sheet to auto-generate.",'ID Identify'!P21),"—") -> Standardise Critical Asset Identification & Prioritisation: formalise all documentation, apply the control consistently across all in-scope assets, close remaining coverage gaps, and ensure evidence is collected routinely. Exceptions must be formally managed with named owners and defined expiry dates. | E50: High (1-3 months) | F50: Q3 2027 | G50: Marc Etonde — Head of IT | H50: Not Started | J50: 3000 | N50: =IFERROR(SUM(J50,K50,M50),0) -> 3000 | O50: =IFERROR(SUM(L50),0) -> 0 | P50: Illustrative estimate (USD). Internal cost = staff days x 250/day blended rate. External and tool costs are indicative list pricing, not quotations.
A51: 0 | B51: 🔍 ID Identify | C51: SOX IT General Controls Assessment | D51: =IFERROR(IF('ID Identify'!P22="⏳ Complete rating and target to generate recommendation.","⏳ Rate this control in the domain sheet to auto-generate.",'ID Identify'!P22),"—") -> ⏳ Rate this control in the domain sheet to auto-generate. | G51: Paul Mbarga — Finance Director | H51: Deferred | N51: =IFERROR(SUM(J51,K51,M51),0) -> 0 | O51: =IFERROR(SUM(L51),0) -> 0 | P51: Out of scope for this organisation — no cost carried.
A52: 0 | B52: 🔍 ID Identify | C52: HIPAA Risk Analysis | D52: =IFERROR(IF('ID Identify'!P23="⏳ Complete rating and target to generate recommendation.","⏳ Rate this control in the domain sheet to auto-generate.",'ID Identify'!P23),"—") -> ⏳ Rate this control in the domain sheet to auto-generate. | G52: Marie Fotso — Legal & Compliance Counsel | H52: Deferred | N52: =IFERROR(SUM(J52,K52,M52),0) -> 0 | O52: =IFERROR(SUM(L52),0) -> 0 | P52: Out of scope for this organisation — no cost carried.
A53: 0.2 | B53: 🔍 ID Identify | C53: Security Metrics & Measurement Framework | D53: =IFERROR(IF('ID Identify'!P24="⏳ Complete rating and target to generate recommendation.","⏳ Rate this control in the domain sheet to auto-generate.",'ID Identify'!P24),"—") -> Standardise Security Metrics & Measurement Framework: formalise all documentation, apply the control consistently across all in-scope assets, close remaining coverage gaps, and ensure evidence is collected routinely. Exceptions must be formally managed with named owners and defined expiry dates. | E53: High (1-3 months) | F53: Q3 2027 | G53: Marc Etonde — Head of IT | H53: Not Started | J53: 3000 | N53: =IFERROR(SUM(J53,K53,M53),0) -> 3000 | O53: =IFERROR(SUM(L53),0) -> 0 | P53: Illustrative estimate (USD). Internal cost = staff days x 250/day blended rate. External and tool costs are indicative list pricing, not quotations.
A54: 0.1 | B54: 🔍 ID Identify | C54: Red Team Programme | D54: =IFERROR(IF('ID Identify'!P25="⏳ Complete rating and target to generate recommendation.","⏳ Rate this control in the domain sheet to auto-generate.",'ID Identify'!P25),"—") -> Standardise Red Team Programme: formalise all documentation, apply the control consistently across all in-scope assets, close remaining coverage gaps, and ensure evidence is collected routinely. Exceptions must be formally managed with named owners and defined expiry dates. | E54: High (1-3 months) | F54: Q3 2027 | G54: Aicha Bello — Security Analyst | H54: Not Started | J54: 3000 | K54: 55000 | L54: 0 | M54: 0 | N54: =IFERROR(SUM(J54,K54,M54),0) -> 58000 | O54: =IFERROR(SUM(L54),0) -> 0 | P54: Illustrative estimate (USD). Internal cost = staff days x 250/day blended rate. External and tool costs are indicative list pricing, not quotations.
A55: 0.52 | B55: 🛡️ PR Protect | C55: Multi-Factor Authentication — All Users | D55: =IFERROR(IF('PR Protect'!P4="⏳ Complete rating and target to generate recommendation.","⏳ Rate this control in the domain sheet to auto-generate.",'PR Protect'!P4),"—") -> Instrument Multi-Factor Authentication — All Users with measurable KPIs: define performance thresholds (coverage %, SLA adherence, exception count), establish automated telemetry where possible, and integrate reporting into quarterly governance cycles. Evidence must be system-generated and reviewed at each governance cycle. | E55: High (1-3 months) | F55: Q4 2026 | G55: Marc Etonde — Head of IT | H55: Not Started | J55: 3000 | N55: =IFERROR(SUM(J55,K55,M55),0) -> 3000 | O55: =IFERROR(SUM(L55),0) -> 0 | P55: Illustrative estimate (USD). Internal cost = staff days x 250/day blended rate. External and tool costs are indicative list pricing, not quotations.
A56: 0.52 | B56: 🛡️ PR Protect | C56: Phishing-Resistant MFA for Privileged Accounts | D56: =IFERROR(IF('PR Protect'!P5="⏳ Complete rating and target to generate recommendation.","⏳ Rate this control in the domain sheet to auto-generate.",'PR Protect'!P5),"—") -> Instrument Phishing-Resistant MFA for Privileged Accounts with measurable KPIs: define performance thresholds (coverage %, SLA adherence, exception count), establish automated telemetry where possible, and integrate reporting into quarterly governance cycles. Evidence must be system-generated and reviewed at each governance cycle. | E56: High (1-3 months) | F56: Q4 2026 | G56: Marc Etonde — Head of IT | H56: Not Started | J56: 3000 | N56: =IFERROR(SUM(J56,K56,M56),0) -> 3000 | O56: =IFERROR(SUM(L56),0) -> 0 | P56: Illustrative estimate (USD). Internal cost = staff days x 250/day blended rate. External and tool costs are indicative list pricing, not quotations.
A57: 0.52 | B57: 🛡️ PR Protect | C57: Privileged Access Management (PAM) | D57: =IFERROR(IF('PR Protect'!P6="⏳ Complete rating and target to generate recommendation.","⏳ Rate this control in the domain sheet to auto-generate.",'PR Protect'!P6),"—") -> Instrument Privileged Access Management (PAM) with measurable KPIs: define performance thresholds (coverage %, SLA adherence, exception count), establish automated telemetry where possible, and integrate reporting into quarterly governance cycles. Evidence must be system-generated and reviewed at each governance cycle. | E57: Very High (3+ months) | F57: Q4 2026 | G57: Marc Etonde — Head of IT | H57: Not Started | J57: 7500 | K57: 12000 | L57: 0 | M57: 22000 | N57: =IFERROR(SUM(J57,K57,M57),0) -> 41500 | O57: =IFERROR(SUM(L57),0) -> 0 | P57: Illustrative estimate (USD). Internal cost = staff days x 250/day blended rate. External and tool costs are indicative list pricing, not quotations.
A58: 0.52 | B58: 🛡️ PR Protect | C58: Identity Lifecycle — Joiners Process | D58: =IFERROR(IF('PR Protect'!P7="⏳ Complete rating and target to generate recommendation.","⏳ Rate this control in the domain sheet to auto-generate.",'PR Protect'!P7),"—") -> Standardise Identity Lifecycle — Joiners Process: formalise all documentation, apply the control consistently across all in-scope assets, close remaining coverage gaps, and ensure evidence is collected routinely. Exceptions must be formally managed with named owners and defined expiry dates. | E58: Medium (1-4 weeks) | F58: Q2 2027 | G58: Ruth Anong — HR Manager | H58: Not Started | J58: 1250 | N58: =IFERROR(SUM(J58,K58,M58),0) -> 1250 | O58: =IFERROR(SUM(L58),0) -> 0 | P58: Illustrative estimate (USD). Internal cost = staff days x 250/day blended rate. External and tool costs are indicative list pricing, not quotations.
A59: 0.52 | B59: 🛡️ PR Protect | C59: Identity Lifecycle — Movers Process | D59: =IFERROR(IF('PR Protect'!P8="⏳ Complete rating and target to generate recommendation.","⏳ Rate this control in the domain sheet to auto-generate.",'PR Protect'!P8),"—") -> Standardise Identity Lifecycle — Movers Process: formalise all documentation, apply the control consistently across all in-scope assets, close remaining coverage gaps, and ensure evidence is collected routinely. Exceptions must be formally managed with named owners and defined expiry dates. | E59: High (1-3 months) | F59: Q4 2026 | G59: Ruth Anong — HR Manager | H59: Not Started | J59: 3000 | N59: =IFERROR(SUM(J59,K59,M59),0) -> 3000 | O59: =IFERROR(SUM(L59),0) -> 0 | P59: Illustrative estimate (USD). Internal cost = staff days x 250/day blended rate. External and tool costs are indicative list pricing, not quotations.
A60: 0.52 | B60: 🛡️ PR Protect | C60: Identity Lifecycle — Leavers Process | D60: =IFERROR(IF('PR Protect'!P9="⏳ Complete rating and target to generate recommendation.","⏳ Rate this control in the domain sheet to auto-generate.",'PR Protect'!P9),"—") -> Instrument Identity Lifecycle — Leavers Process with measurable KPIs: define performance thresholds (coverage %, SLA adherence, exception count), establish automated telemetry where possible, and integrate reporting into quarterly governance cycles. Evidence must be system-generated and reviewed at each governance cycle. | E60: High (1-3 months) | F60: Q4 2026 | G60: Ruth Anong — HR Manager | H60: Not Started | J60: 3000 | N60: =IFERROR(SUM(J60,K60,M60),0) -> 3000 | O60: =IFERROR(SUM(L60),0) -> 0 | P60: Illustrative estimate (USD). Internal cost = staff days x 250/day blended rate. External and tool costs are indicative list pricing, not quotations.
A61: 0.52 | B61: 🛡️ PR Protect | C61: Quarterly Access Reviews (Access Certification) | D61: =IFERROR(IF('PR Protect'!P10="⏳ Complete rating and target to generate recommendation.","⏳ Rate this control in the domain sheet to auto-generate.",'PR Protect'!P10),"—") -> Instrument Quarterly Access Reviews (Access Certification) with measurable KPIs: define performance thresholds (coverage %, SLA adherence, exception count), establish automated telemetry where possible, and integrate reporting into quarterly governance cycles. Evidence must be system-generated and reviewed at each governance cycle. | E61: High (1-3 months) | F61: Q4 2026 | G61: Marc Etonde — Head of IT | H61: Not Started | J61: 3000 | N61: =IFERROR(SUM(J61,K61,M61),0) -> 3000 | O61: =IFERROR(SUM(L61),0) -> 0 | P61: Illustrative estimate (USD). Internal cost = staff days x 250/day blended rate. External and tool costs are indicative list pricing, not quotations.
A62: 0.52 | B62: 🛡️ PR Protect | C62: Single Sign-On (SSO) & Federation | D62: =IFERROR(IF('PR Protect'!P11="⏳ Complete rating and target to generate recommendation.","⏳ Rate this control in the domain sheet to auto-generate.",'PR Protect'!P11),"—") -> Standardise Single Sign-On (SSO) & Federation: formalise all documentation, apply the control consistently across all in-scope assets, close remaining coverage gaps, and ensure evidence is collected routinely. Exceptions must be formally managed with named owners and defined expiry dates. | E62: Medium (1-4 weeks) | F62: Q2 2027 | G62: Marc Etonde — Head of IT | H62: Not Started | J62: 1250 | N62: =IFERROR(SUM(J62,K62,M62),0) -> 1250 | O62: =IFERROR(SUM(L62),0) -> 0 | P62: Illustrative estimate (USD). Internal cost = staff days x 250/day blended rate. External and tool costs are indicative list pricing, not quotations.
A63: 0.78 | B63: 🛡️ PR Protect | C63: Separation of Duties (SoD) Controls | D63: =IFERROR(IF('PR Protect'!P12="⏳ Complete rating and target to generate recommendation.","⏳ Rate this control in the domain sheet to auto-generate.",'PR Protect'!P12),"—") -> Instrument Separation of Duties (SoD) Controls with measurable KPIs: define performance thresholds (coverage %, SLA adherence, exception count), establish automated telemetry where possible, and integrate reporting into quarterly governance cycles. Evidence must be system-generated and reviewed at each governance cycle. | E63: High (1-3 months) | F63: Q4 2026 | G63: Tunde Balogun — Lead Software Engineer | H63: Not Started | J63: 3000 | N63: =IFERROR(SUM(J63,K63,M63),0) -> 3000 | O63: =IFERROR(SUM(L63),0) -> 0 | P63: Illustrative estimate (USD). Internal cost = staff days x 250/day blended rate. External and tool costs are indicative list pricing, not quotations.
A64: 0.52 | B64: 🛡️ PR Protect | C64: Dormant Account Detection & Management | D64: =IFERROR(IF('PR Protect'!P13="⏳ Complete rating and target to generate recommendation.","⏳ Rate this control in the domain sheet to auto-generate.",'PR Protect'!P13),"—") -> Instrument Dormant Account Detection & Management with measurable KPIs: define performance thresholds (coverage %, SLA adherence, exception count), establish automated telemetry where possible, and integrate reporting into quarterly governance cycles. Evidence must be system-generated and reviewed at each governance cycle. | E64: High (1-3 months) | F64: Q4 2026 | G64: Marc Etonde — Head of IT | H64: Not Started | J64: 3000 | N64: =IFERROR(SUM(J64,K64,M64),0) -> 3000 | O64: =IFERROR(SUM(L64),0) -> 0 | P64: Illustrative estimate (USD). Internal cost = staff days x 250/day blended rate. External and tool costs are indicative list pricing, not quotations.
A65: 0.26 | B65: 🛡️ PR Protect | C65: Machine Identity & Service Account Management | D65: =IFERROR(IF('PR Protect'!P14="⏳ Complete rating and target to generate recommendation.","⏳ Rate this control in the domain sheet to auto-generate.",'PR Protect'!P14),"—") -> Standardise Machine Identity & Service Account Management: formalise all documentation, apply the control consistently across all in-scope assets, close remaining coverage gaps, and ensure evidence is collected routinely. Exceptions must be formally managed with named owners and defined expiry dates. | E65: High (1-3 months) | F65: Q4 2026 | G65: Sam Ncube — DevOps Engineer | H65: Not Started | J65: 3000 | N65: =IFERROR(SUM(J65,K65,M65),0) -> 3000 | O65: =IFERROR(SUM(L65),0) -> 0 | P65: Illustrative estimate (USD). Internal cost = staff days x 250/day blended rate. External and tool costs are indicative list pricing, not quotations.
A66: 0.52 | B66: 🛡️ PR Protect | C66: API Key & Secrets Management | D66: =IFERROR(IF('PR Protect'!P15="⏳ Complete rating and target to generate recommendation.","⏳ Rate this control in the domain sheet to auto-generate.",'PR Protect'!P15),"—") -> Standardise API Key & Secrets Management: formalise all documentation, apply the control consistently across all in-scope assets, close remaining coverage gaps, and ensure evidence is collected routinely. Exceptions must be formally managed with named owners and defined expiry dates. | E66: High (1-3 months) | F66: Q4 2026 | G66: Tunde Balogun — Lead Software Engineer | H66: Not Started | J66: 3000 | N66: =IFERROR(SUM(J66,K66,M66),0) -> 3000 | O66: =IFERROR(SUM(L66),0) -> 0 | P66: Illustrative estimate (USD). Internal cost = staff days x 250/day blended rate. External and tool costs are indicative list pricing, not quotations.
A67: 0.26 | B67: 🛡️ PR Protect | C67: Zero Trust Architecture (ZTA) Implementation | D67: =IFERROR(IF('PR Protect'!P16="⏳ Complete rating and target to generate recommendation.","⏳ Rate this control in the domain sheet to auto-generate.",'PR Protect'!P16),"—") -> Standardise Zero Trust Architecture (ZTA) Implementation: formalise all documentation, apply the control consistently across all in-scope assets, close remaining coverage gaps, and ensure evidence is collected routinely. Exceptions must be formally managed with named owners and defined expiry dates. | E67: Very High (3+ months) | F67: Q1 2027 | G67: Marc Etonde — Head of IT | H67: Not Started | J67: 7500 | N67: =IFERROR(SUM(J67,K67,M67),0) -> 7500 | O67: =IFERROR(SUM(L67),0) -> 0 | P67: Illustrative estimate (USD). Internal cost = staff days x 250/day blended rate. External and tool costs are indicative list pricing, not quotations.
A68: 0.52 | B68: 🛡️ PR Protect | C68: Encryption at Rest — Sensitive Data | D68: =IFERROR(IF('PR Protect'!P17="⏳ Complete rating and target to generate recommendation.","⏳ Rate this control in the domain sheet to auto-generate.",'PR Protect'!P17),"—") -> Instrument Encryption at Rest — Sensitive Data with measurable KPIs: define performance thresholds (coverage %, SLA adherence, exception count), establish automated telemetry where possible, and integrate reporting into quarterly governance cycles. Evidence must be system-generated and reviewed at each governance cycle. | E68: High (1-3 months) | F68: Q4 2026 | G68: Sam Ncube — DevOps Engineer | H68: Not Started | J68: 3000 | N68: =IFERROR(SUM(J68,K68,M68),0) -> 3000 | O68: =IFERROR(SUM(L68),0) -> 0 | P68: Illustrative estimate (USD). Internal cost = staff days x 250/day blended rate. External and tool costs are indicative list pricing, not quotations.
A69: 0.52 | B69: 🛡️ PR Protect | C69: Encryption in Transit — TLS Enforcement | D69: =IFERROR(IF('PR Protect'!P18="⏳ Complete rating and target to generate recommendation.","⏳ Rate this control in the domain sheet to auto-generate.",'PR Protect'!P18),"—") -> Instrument Encryption in Transit — TLS Enforcement with measurable KPIs: define performance thresholds (coverage %, SLA adherence, exception count), establish automated telemetry where possible, and integrate reporting into quarterly governance cycles. Evidence must be system-generated and reviewed at each governance cycle. | E69: Medium (1-4 weeks) | F69: Q2 2027 | G69: Sam Ncube — DevOps Engineer | H69: Not Started | J69: 1250 | N69: =IFERROR(SUM(J69,K69,M69),0) -> 1250 | O69: =IFERROR(SUM(L69),0) -> 0 | P69: Illustrative estimate (USD). Internal cost = staff days x 250/day blended rate. External and tool costs are indicative list pricing, not quotations.
A70: 0.78 | B70: 🛡️ PR Protect | C70: Data Loss Prevention (DLP) — Email | D70: =IFERROR(IF('PR Protect'!P19="⏳ Complete rating and target to generate recommendation.","⏳ Rate this control in the domain sheet to auto-generate.",'PR Protect'!P19),"—") -> Instrument Data Loss Prevention (DLP) — Email with measurable KPIs: define performance thresholds (coverage %, SLA adherence, exception count), establish automated telemetry where possible, and integrate reporting into quarterly governance cycles. Evidence must be system-generated and reviewed at each governance cycle. | E70: High (1-3 months) | F70: Q4 2026 | G70: Marc Etonde — Head of IT | H70: Not Started | J70: 3000 | K70: 0 | L70: 0 | M70: 0 | N70: =IFERROR(SUM(J70,K70,M70),0) -> 3000 | O70: =IFERROR(SUM(L70),0) -> 0 | P70: Illustrative estimate (USD). Internal cost = staff days x 250/day blended rate. External and tool costs are indicative list pricing, not quotations.
A71: 0.52 | B71: 🛡️ PR Protect | C71: Data Loss Prevention (DLP) — Endpoint | D71: =IFERROR(IF('PR Protect'!P20="⏳ Complete rating and target to generate recommendation.","⏳ Rate this control in the domain sheet to auto-generate.",'PR Protect'!P20),"—") -> Instrument Data Loss Prevention (DLP) — Endpoint with measurable KPIs: define performance thresholds (coverage %, SLA adherence, exception count), establish automated telemetry where possible, and integrate reporting into quarterly governance cycles. Evidence must be system-generated and reviewed at each governance cycle. | E71: High (1-3 months) | F71: Q4 2026 | G71: Marc Etonde — Head of IT | H71: Not Started | J71: 3000 | N71: =IFERROR(SUM(J71,K71,M71),0) -> 3000 | O71: =IFERROR(SUM(L71),0) -> 0 | P71: Illustrative estimate (USD). Internal cost = staff days x 250/day blended rate. External and tool costs are indicative list pricing, not quotations.
A72: 0.78 | B72: 🛡️ PR Protect | C72: Data Loss Prevention (DLP) — Cloud & SaaS | D72: =IFERROR(IF('PR Protect'!P21="⏳ Complete rating and target to generate recommendation.","⏳ Rate this control in the domain sheet to auto-generate.",'PR Protect'!P21),"—") -> Instrument Data Loss Prevention (DLP) — Cloud & SaaS with measurable KPIs: define performance thresholds (coverage %, SLA adherence, exception count), establish automated telemetry where possible, and integrate reporting into quarterly governance cycles. Evidence must be system-generated and reviewed at each governance cycle. | E72: High (1-3 months) | F72: Q4 2026 | G72: Marc Etonde — Head of IT | H72: Not Started | J72: 3000 | K72: 8000 | L72: 0 | M72: 30000 | N72: =IFERROR(SUM(J72,K72,M72),0) -> 41000 | O72: =IFERROR(SUM(L72),0) -> 0 | P72: Illustrative estimate (USD). Internal cost = staff days x 250/day blended rate. External and tool costs are indicative list pricing, not quotations.
A73: 0.52 | B73: 🛡️ PR Protect | C73: Data Masking & Pseudonymisation | D73: =IFERROR(IF('PR Protect'!P22="⏳ Complete rating and target to generate recommendation.","⏳ Rate this control in the domain sheet to auto-generate.",'PR Protect'!P22),"—") -> Instrument Data Masking & Pseudonymisation with measurable KPIs: define performance thresholds (coverage %, SLA adherence, exception count), establish automated telemetry where possible, and integrate reporting into quarterly governance cycles. Evidence must be system-generated and reviewed at each governance cycle. | E73: High (1-3 months) | F73: Q4 2026 | G73: Tunde Balogun — Lead Software Engineer | H73: Not Started | J73: 3000 | N73: =IFERROR(SUM(J73,K73,M73),0) -> 3000 | O73: =IFERROR(SUM(L73),0) -> 0 | P73: Illustrative estimate (USD). Internal cost = staff days x 250/day blended rate. External and tool costs are indicative list pricing, not quotations.
A74: 0.78 | B74: 🛡️ PR Protect | C74: Payment Card Data (PAN) Protection | D74: =IFERROR(IF('PR Protect'!P23="⏳ Complete rating and target to generate recommendation.","⏳ Rate this control in the domain sheet to auto-generate.",'PR Protect'!P23),"—") -> Instrument Payment Card Data (PAN) Protection with measurable KPIs: define performance thresholds (coverage %, SLA adherence, exception count), establish automated telemetry where possible, and integrate reporting into quarterly governance cycles. Evidence must be system-generated and reviewed at each governance cycle. | E74: High (1-3 months) | F74: Q4 2026 | G74: Sam Ncube — DevOps Engineer | H74: Not Started | J74: 3000 | N74: =IFERROR(SUM(J74,K74,M74),0) -> 3000 | O74: =IFERROR(SUM(L74),0) -> 0 | P74: Illustrative estimate (USD). Internal cost = staff days x 250/day blended rate. External and tool costs are indicative list pricing, not quotations.
A75: 0.26 | B75: 🛡️ PR Protect | C75: Backup — Architecture & Immutability | D75: =IFERROR(IF('PR Protect'!P24="⏳ Complete rating and target to generate recommendation.","⏳ Rate this control in the domain sheet to auto-generate.",'PR Protect'!P24),"—") -> Standardise Backup — Architecture & Immutability: formalise all documentation, apply the control consistently across all in-scope assets, close remaining coverage gaps, and ensure evidence is collected routinely. Exceptions must be formally managed with named owners and defined expiry dates. | E75: Medium (1-4 weeks) | F75: Q2 2027 | G75: Grace Ayuk — IT Operations Manager | H75: Not Started | J75: 1250 | N75: =IFERROR(SUM(J75,K75,M75),0) -> 1250 | O75: =IFERROR(SUM(L75),0) -> 0 | P75: Illustrative estimate (USD). Internal cost = staff days x 250/day blended rate. External and tool costs are indicative list pricing, not quotations.
A76: 0.26 | B76: 🛡️ PR Protect | C76: Backup — Restoration Testing | D76: =IFERROR(IF('PR Protect'!P25="⏳ Complete rating and target to generate recommendation.","⏳ Rate this control in the domain sheet to auto-generate.",'PR Protect'!P25),"—") -> Standardise Backup — Restoration Testing: formalise all documentation, apply the control consistently across all in-scope assets, close remaining coverage gaps, and ensure evidence is collected routinely. Exceptions must be formally managed with named owners and defined expiry dates. | E76: High (1-3 months) | F76: Q4 2026 | G76: Grace Ayuk — IT Operations Manager | H76: Not Started | J76: 3000 | N76: =IFERROR(SUM(J76,K76,M76),0) -> 3000 | O76: =IFERROR(SUM(L76),0) -> 0 | P76: Illustrative estimate (USD). Internal cost = staff days x 250/day blended rate. External and tool costs are indicative list pricing, not quotations.
A77: 0.26 | B77: 🛡️ PR Protect | C77: Email Security — DMARC, DKIM, SPF | D77: =IFERROR(IF('PR Protect'!P26="⏳ Complete rating and target to generate recommendation.","⏳ Rate this control in the domain sheet to auto-generate.",'PR Protect'!P26),"—") -> Standardise Email Security — DMARC, DKIM, SPF: formalise all documentation, apply the control consistently across all in-scope assets, close remaining coverage gaps, and ensure evidence is collected routinely. Exceptions must be formally managed with named owners and defined expiry dates. | E77: Medium (1-4 weeks) | F77: Q3 2027 | G77: Sam Ncube — DevOps Engineer | H77: Not Started | J77: 1250 | N77: =IFERROR(SUM(J77,K77,M77),0) -> 1250 | O77: =IFERROR(SUM(L77),0) -> 0 | P77: Illustrative estimate (USD). Internal cost = staff days x 250/day blended rate. External and tool costs are indicative list pricing, not quotations.
A78: 0.52 | B78: 🛡️ PR Protect | C78: Email Security — Anti-Phishing & Sandboxing | D78: =IFERROR(IF('PR Protect'!P27="⏳ Complete rating and target to generate recommendation.","⏳ Rate this control in the domain sheet to auto-generate.",'PR Protect'!P27),"—") -> Standardise Email Security — Anti-Phishing & Sandboxing: formalise all documentation, apply the control consistently across all in-scope assets, close remaining coverage gaps, and ensure evidence is collected routinely. Exceptions must be formally managed with named owners and defined expiry dates. | E78: Medium (1-4 weeks) | F78: Q3 2027 | G78: Marc Etonde — Head of IT | H78: Not Started | J78: 1250 | N78: =IFERROR(SUM(J78,K78,M78),0) -> 1250 | O78: =IFERROR(SUM(L78),0) -> 0 | P78: Illustrative estimate (USD). Internal cost = staff days x 250/day blended rate. External and tool costs are indicative list pricing, not quotations.
A79: 0.52 | B79: 🛡️ PR Protect | C79: Cryptographic Standards & Key Lifecycle | D79: =IFERROR(IF('PR Protect'!P28="⏳ Complete rating and target to generate recommendation.","⏳ Rate this control in the domain sheet to auto-generate.",'PR Protect'!P28),"—") -> Instrument Cryptographic Standards & Key Lifecycle with measurable KPIs: define performance thresholds (coverage %, SLA adherence, exception count), establish automated telemetry where possible, and integrate reporting into quarterly governance cycles. Evidence must be system-generated and reviewed at each governance cycle. | E79: High (1-3 months) | F79: Q4 2026 | G79: Sam Ncube — DevOps Engineer | H79: Not Started | J79: 3000 | N79: =IFERROR(SUM(J79,K79,M79),0) -> 3000 | O79: =IFERROR(SUM(L79),0) -> 0 | P79: Illustrative estimate (USD). Internal cost = staff days x 250/day blended rate. External and tool costs are indicative list pricing, not quotations.
A80: 0.26 | B80: 🛡️ PR Protect | C80: Endpoint Detection & Response (EDR) | D80: =IFERROR(IF('PR Protect'!P29="⏳ Complete rating and target to generate recommendation.","⏳ Rate this control in the domain sheet to auto-generate.",'PR Protect'!P29),"—") -> Standardise Endpoint Detection & Response (EDR): formalise all documentation, apply the control consistently across all in-scope assets, close remaining coverage gaps, and ensure evidence is collected routinely. Exceptions must be formally managed with named owners and defined expiry dates. | E80: Medium (1-4 weeks) | F80: Q3 2027 | G80: Marc Etonde — Head of IT | H80: Not Started | J80: 1250 | K80: 0 | L80: 0 | M80: 14000 | N80: =IFERROR(SUM(J80,K80,M80),0) -> 15250 | O80: =IFERROR(SUM(L80),0) -> 0 | P80: Illustrative estimate (USD). Internal cost = staff days x 250/day blended rate. External and tool costs are indicative list pricing, not quotations.
A81: 0.26 | B81: 🛡️ PR Protect | C81: Endpoint Hardening & CIS Benchmark Compliance | D81: =IFERROR(IF('PR Protect'!P30="⏳ Complete rating and target to generate recommendation.","⏳ Rate this control in the domain sheet to auto-generate.",'PR Protect'!P30),"—") -> Standardise Endpoint Hardening & CIS Benchmark Compliance: formalise all documentation, apply the control consistently across all in-scope assets, close remaining coverage gaps, and ensure evidence is collected routinely. Exceptions must be formally managed with named owners and defined expiry dates. | E81: High (1-3 months) | F81: Q4 2026 | G81: Grace Ayuk — IT Operations Manager | H81: Not Started | J81: 3000 | N81: =IFERROR(SUM(J81,K81,M81),0) -> 3000 | O81: =IFERROR(SUM(L81),0) -> 0 | P81: Illustrative estimate (USD). Internal cost = staff days x 250/day blended rate. External and tool costs are indicative list pricing, not quotations.
A82: 0.78 | B82: 🛡️ PR Protect | C82: Patch Management — Critical & High Vulnerabilities | D82: =IFERROR(IF('PR Protect'!P31="⏳ Complete rating and target to generate recommendation.","⏳ Rate this control in the domain sheet to auto-generate.",'PR Protect'!P31),"—") -> Instrument Patch Management — Critical & High Vulnerabilities with measurable KPIs: define performance thresholds (coverage %, SLA adherence, exception count), establish automated telemetry where possible, and integrate reporting into quarterly governance cycles. Evidence must be system-generated and reviewed at each governance cycle. | E82: High (1-3 months) | F82: Q4 2026 | G82: Grace Ayuk — IT Operations Manager | H82: Not Started | J82: 3000 | N82: =IFERROR(SUM(J82,K82,M82),0) -> 3000 | O82: =IFERROR(SUM(L82),0) -> 0 | P82: Illustrative estimate (USD). Internal cost = staff days x 250/day blended rate. External and tool costs are indicative list pricing, not quotations.
A83: 0.26 | B83: 🛡️ PR Protect | C83: Patch Management — Medium & Low Vulnerabilities | D83: =IFERROR(IF('PR Protect'!P32="⏳ Complete rating and target to generate recommendation.","⏳ Rate this control in the domain sheet to auto-generate.",'PR Protect'!P32),"—") -> Standardise Patch Management — Medium & Low Vulnerabilities: formalise all documentation, apply the control consistently across all in-scope assets, close remaining coverage gaps, and ensure evidence is collected routinely. Exceptions must be formally managed with named owners and defined expiry dates. | E83: High (1-3 months) | F83: Q4 2026 | G83: Grace Ayuk — IT Operations Manager | H83: Not Started | J83: 3000 | N83: =IFERROR(SUM(J83,K83,M83),0) -> 3000 | O83: =IFERROR(SUM(L83),0) -> 0 | P83: Illustrative estimate (USD). Internal cost = staff days x 250/day blended rate. External and tool costs are indicative list pricing, not quotations.
A84: 0.52 | B84: 🛡️ PR Protect | C84: End-of-Life (EOL) Software & OS Management | D84: =IFERROR(IF('PR Protect'!P33="⏳ Complete rating and target to generate recommendation.","⏳ Rate this control in the domain sheet to auto-generate.",'PR Protect'!P33),"—") -> Standardise End-of-Life (EOL) Software & OS Management: formalise all documentation, apply the control consistently across all in-scope assets, close remaining coverage gaps, and ensure evidence is collected routinely. Exceptions must be formally managed with named owners and defined expiry dates. | E84: High (1-3 months) | F84: Q4 2026 | G84: Grace Ayuk — IT Operations Manager | H84: Not Started | J84: 3000 | N84: =IFERROR(SUM(J84,K84,M84),0) -> 3000 | O84: =IFERROR(SUM(L84),0) -> 0 | P84: Illustrative estimate (USD). Internal cost = staff days x 250/day blended rate. External and tool costs are indicative list pricing, not quotations.
A85: 0.26 | B85: 🛡️ PR Protect | C85: Application Whitelisting / Allowlisting | D85: =IFERROR(IF('PR Protect'!P34="⏳ Complete rating and target to generate recommendation.","⏳ Rate this control in the domain sheet to auto-generate.",'PR Protect'!P34),"—") -> Standardise Application Whitelisting / Allowlisting: formalise all documentation, apply the control consistently across all in-scope assets, close remaining coverage gaps, and ensure evidence is collected routinely. Exceptions must be formally managed with named owners and defined expiry dates. | E85: High (1-3 months) | F85: Q4 2026 | G85: Marc Etonde — Head of IT | H85: Not Started | J85: 3000 | N85: =IFERROR(SUM(J85,K85,M85),0) -> 3000 | O85: =IFERROR(SUM(L85),0) -> 0 | P85: Illustrative estimate (USD). Internal cost = staff days x 250/day blended rate. External and tool costs are indicative list pricing, not quotations.
A86: 0.78 | B86: 🛡️ PR Protect | C86: Removable Media Controls | D86: =IFERROR(IF('PR Protect'!P35="⏳ Complete rating and target to generate recommendation.","⏳ Rate this control in the domain sheet to auto-generate.",'PR Protect'!P35),"—") -> Instrument Removable Media Controls with measurable KPIs: define performance thresholds (coverage %, SLA adherence, exception count), establish automated telemetry where possible, and integrate reporting into quarterly governance cycles. Evidence must be system-generated and reviewed at each governance cycle. | E86: High (1-3 months) | F86: Q4 2026 | G86: Marc Etonde — Head of IT | H86: Not Started | J86: 3000 | N86: =IFERROR(SUM(J86,K86,M86),0) -> 3000 | O86: =IFERROR(SUM(L86),0) -> 0 | P86: Illustrative estimate (USD). Internal cost = staff days x 250/day blended rate. External and tool costs are indicative list pricing, not quotations.
A87: 0.26 | B87: 🛡️ PR Protect | C87: Mobile Device Management (MDM) | D87: =IFERROR(IF('PR Protect'!P36="⏳ Complete rating and target to generate recommendation.","⏳ Rate this control in the domain sheet to auto-generate.",'PR Protect'!P36),"—") -> Standardise Mobile Device Management (MDM): formalise all documentation, apply the control consistently across all in-scope assets, close remaining coverage gaps, and ensure evidence is collected routinely. Exceptions must be formally managed with named owners and defined expiry dates. | E87: Medium (1-4 weeks) | F87: Q3 2027 | G87: Marc Etonde — Head of IT | H87: Not Started | J87: 1250 | N87: =IFERROR(SUM(J87,K87,M87),0) -> 1250 | O87: =IFERROR(SUM(L87),0) -> 0 | P87: Illustrative estimate (USD). Internal cost = staff days x 250/day blended rate. External and tool costs are indicative list pricing, not quotations.
A88: 0.52 | B88: 🛡️ PR Protect | C88: Network Segmentation — Zone Architecture | D88: =IFERROR(IF('PR Protect'!P37="⏳ Complete rating and target to generate recommendation.","⏳ Rate this control in the domain sheet to auto-generate.",'PR Protect'!P37),"—") -> Instrument Network Segmentation — Zone Architecture with measurable KPIs: define performance thresholds (coverage %, SLA adherence, exception count), establish automated telemetry where possible, and integrate reporting into quarterly governance cycles. Evidence must be system-generated and reviewed at each governance cycle. | E88: Very High (3+ months) | F88: Q4 2026 | G88: Marc Etonde — Head of IT | H88: Not Started | J88: 7500 | K88: 35000 | L88: 0 | M88: 0 | N88: =IFERROR(SUM(J88,K88,M88),0) -> 42500 | O88: =IFERROR(SUM(L88),0) -> 0 | P88: Illustrative estimate (USD). Internal cost = staff days x 250/day blended rate. External and tool costs are indicative list pricing, not quotations.
A89: 0.52 | B89: 🛡️ PR Protect | C89: Network Microsegmentation (Cloud & Data Centre) | D89: =IFERROR(IF('PR Protect'!P38="⏳ Complete rating and target to generate recommendation.","⏳ Rate this control in the domain sheet to auto-generate.",'PR Protect'!P38),"—") -> Standardise Network Microsegmentation (Cloud & Data Centre): formalise all documentation, apply the control consistently across all in-scope assets, close remaining coverage gaps, and ensure evidence is collected routinely. Exceptions must be formally managed with named owners and defined expiry dates. | E89: High (1-3 months) | F89: Q4 2026 | G89: Sam Ncube — DevOps Engineer | H89: Not Started | J89: 3000 | N89: =IFERROR(SUM(J89,K89,M89),0) -> 3000 | O89: =IFERROR(SUM(L89),0) -> 0 | P89: Illustrative estimate (USD). Internal cost = staff days x 250/day blended rate. External and tool costs are indicative list pricing, not quotations.
A90: 0.78 | B90: 🛡️ PR Protect | C90: CDE Network Segmentation Validation | D90: =IFERROR(IF('PR Protect'!P39="⏳ Complete rating and target to generate recommendation.","⏳ Rate this control in the domain sheet to auto-generate.",'PR Protect'!P39),"—") -> Instrument CDE Network Segmentation Validation with measurable KPIs: define performance thresholds (coverage %, SLA adherence, exception count), establish automated telemetry where possible, and integrate reporting into quarterly governance cycles. Evidence must be system-generated and reviewed at each governance cycle. | E90: Very High (3+ months) | F90: Q4 2026 | G90: Sam Ncube — DevOps Engineer | H90: Not Started | J90: 7500 | N90: =IFERROR(SUM(J90,K90,M90),0) -> 7500 | O90: =IFERROR(SUM(L90),0) -> 0 | P90: Illustrative estimate (USD). Internal cost = staff days x 250/day blended rate. External and tool costs are indicative list pricing, not quotations.
A91: 0.52 | B91: 🛡️ PR Protect | C91: NGFW & Firewall Rule Management | D91: =IFERROR(IF('PR Protect'!P40="⏳ Complete rating and target to generate recommendation.","⏳ Rate this control in the domain sheet to auto-generate.",'PR Protect'!P40),"—") -> Instrument NGFW & Firewall Rule Management with measurable KPIs: define performance thresholds (coverage %, SLA adherence, exception count), establish automated telemetry where possible, and integrate reporting into quarterly governance cycles. Evidence must be system-generated and reviewed at each governance cycle. | E91: High (1-3 months) | F91: Q4 2026 | G91: Marc Etonde — Head of IT | H91: Not Started | J91: 3000 | N91: =IFERROR(SUM(J91,K91,M91),0) -> 3000 | O91: =IFERROR(SUM(L91),0) -> 0 | P91: Illustrative estimate (USD). Internal cost = staff days x 250/day blended rate. External and tool costs are indicative list pricing, not quotations.
A92: 0.52 | B92: 🛡️ PR Protect | C92: Web Application Firewall (WAF) | D92: =IFERROR(IF('PR Protect'!P41="⏳ Complete rating and target to generate recommendation.","⏳ Rate this control in the domain sheet to auto-generate.",'PR Protect'!P41),"—") -> Instrument Web Application Firewall (WAF) with measurable KPIs: define performance thresholds (coverage %, SLA adherence, exception count), establish automated telemetry where possible, and integrate reporting into quarterly governance cycles. Evidence must be system-generated and reviewed at each governance cycle. | E92: High (1-3 months) | F92: Q4 2026 | G92: Sam Ncube — DevOps Engineer | H92: Not Started | J92: 3000 | N92: =IFERROR(SUM(J92,K92,M92),0) -> 3000 | O92: =IFERROR(SUM(L92),0) -> 0 | P92: Illustrative estimate (USD). Internal cost = staff days x 250/day blended rate. External and tool costs are indicative list pricing, not quotations.
A93: 0.26 | B93: 🛡️ PR Protect | C93: Zero Trust Network Access (ZTNA) | D93: =IFERROR(IF('PR Protect'!P42="⏳ Complete rating and target to generate recommendation.","⏳ Rate this control in the domain sheet to auto-generate.",'PR Protect'!P42),"—") -> Standardise Zero Trust Network Access (ZTNA): formalise all documentation, apply the control consistently across all in-scope assets, close remaining coverage gaps, and ensure evidence is collected routinely. Exceptions must be formally managed with named owners and defined expiry dates. | E93: High (1-3 months) | F93: Q4 2026 | G93: Marc Etonde — Head of IT | H93: Not Started | J93: 3000 | N93: =IFERROR(SUM(J93,K93,M93),0) -> 3000 | O93: =IFERROR(SUM(L93),0) -> 0 | P93: Illustrative estimate (USD). Internal cost = staff days x 250/day blended rate. External and tool costs are indicative list pricing, not quotations.
A94: 0.26 | B94: 🛡️ PR Protect | C94: SASE Architecture | D94: =IFERROR(IF('PR Protect'!P43="⏳ Complete rating and target to generate recommendation.","⏳ Rate this control in the domain sheet to auto-generate.",'PR Protect'!P43),"—") -> Standardise SASE Architecture: formalise all documentation, apply the control consistently across all in-scope assets, close remaining coverage gaps, and ensure evidence is collected routinely. Exceptions must be formally managed with named owners and defined expiry dates. | E94: High (1-3 months) | F94: Q4 2026 | G94: Marc Etonde — Head of IT | H94: Not Started | J94: 3000 | N94: =IFERROR(SUM(J94,K94,M94),0) -> 3000 | O94: =IFERROR(SUM(L94),0) -> 0 | P94: Illustrative estimate (USD). Internal cost = staff days x 250/day blended rate. External and tool costs are indicative list pricing, not quotations.
A95: 0.52 | B95: 🛡️ PR Protect | C95: Protective DNS & DNS Security | D95: =IFERROR(IF('PR Protect'!P44="⏳ Complete rating and target to generate recommendation.","⏳ Rate this control in the domain sheet to auto-generate.",'PR Protect'!P44),"—") -> Standardise Protective DNS & DNS Security: formalise all documentation, apply the control consistently across all in-scope assets, close remaining coverage gaps, and ensure evidence is collected routinely. Exceptions must be formally managed with named owners and defined expiry dates. | E95: High (1-3 months) | F95: Q4 2026 | G95: Marc Etonde — Head of IT | H95: Not Started | J95: 3000 | N95: =IFERROR(SUM(J95,K95,M95),0) -> 3000 | O95: =IFERROR(SUM(L95),0) -> 0 | P95: Illustrative estimate (USD). Internal cost = staff days x 250/day blended rate. External and tool costs are indicative list pricing, not quotations.
A96: 0.52 | B96: 🛡️ PR Protect | C96: Egress Filtering & Allowlisting | D96: =IFERROR(IF('PR Protect'!P45="⏳ Complete rating and target to generate recommendation.","⏳ Rate this control in the domain sheet to auto-generate.",'PR Protect'!P45),"—") -> Standardise Egress Filtering & Allowlisting: formalise all documentation, apply the control consistently across all in-scope assets, close remaining coverage gaps, and ensure evidence is collected routinely. Exceptions must be formally managed with named owners and defined expiry dates. | E96: High (1-3 months) | F96: Q4 2026 | G96: Sam Ncube — DevOps Engineer | H96: Not Started | J96: 3000 | N96: =IFERROR(SUM(J96,K96,M96),0) -> 3000 | O96: =IFERROR(SUM(L96),0) -> 0 | P96: Illustrative estimate (USD). Internal cost = staff days x 250/day blended rate. External and tool costs are indicative list pricing, not quotations.
A97: 0.52 | B97: 🛡️ PR Protect | C97: Network Intrusion Prevention (IPS) | D97: =IFERROR(IF('PR Protect'!P46="⏳ Complete rating and target to generate recommendation.","⏳ Rate this control in the domain sheet to auto-generate.",'PR Protect'!P46),"—") -> Instrument Network Intrusion Prevention (IPS) with measurable KPIs: define performance thresholds (coverage %, SLA adherence, exception count), establish automated telemetry where possible, and integrate reporting into quarterly governance cycles. Evidence must be system-generated and reviewed at each governance cycle. | E97: High (1-3 months) | F97: Q4 2026 | G97: Marc Etonde — Head of IT | H97: Not Started | J97: 3000 | N97: =IFERROR(SUM(J97,K97,M97),0) -> 3000 | O97: =IFERROR(SUM(L97),0) -> 0 | P97: Illustrative estimate (USD). Internal cost = staff days x 250/day blended rate. External and tool costs are indicative list pricing, not quotations.
A98: 0.78 | B98: 🛡️ PR Protect | C98: Remote Administration Security | D98: =IFERROR(IF('PR Protect'!P47="⏳ Complete rating and target to generate recommendation.","⏳ Rate this control in the domain sheet to auto-generate.",'PR Protect'!P47),"—") -> Instrument Remote Administration Security with measurable KPIs: define performance thresholds (coverage %, SLA adherence, exception count), establish automated telemetry where possible, and integrate reporting into quarterly governance cycles. Evidence must be system-generated and reviewed at each governance cycle. | E98: High (1-3 months) | F98: Q4 2026 | G98: Grace Ayuk — IT Operations Manager | H98: Not Started | J98: 3000 | N98: =IFERROR(SUM(J98,K98,M98),0) -> 3000 | O98: =IFERROR(SUM(L98),0) -> 0 | P98: Illustrative estimate (USD). Internal cost = staff days x 250/day blended rate. External and tool costs are indicative list pricing, not quotations.
A99: 0.52 | B99: 🛡️ PR Protect | C99: Wireless Network Security | D99: =IFERROR(IF('PR Protect'!P48="⏳ Complete rating and target to generate recommendation.","⏳ Rate this control in the domain sheet to auto-generate.",'PR Protect'!P48),"—") -> Instrument Wireless Network Security with measurable KPIs: define performance thresholds (coverage %, SLA adherence, exception count), establish automated telemetry where possible, and integrate reporting into quarterly governance cycles. Evidence must be system-generated and reviewed at each governance cycle. | E99: High (1-3 months) | F99: Q4 2026 | G99: Marc Etonde — Head of IT | H99: Not Started | J99: 3000 | N99: =IFERROR(SUM(J99,K99,M99),0) -> 3000 | O99: =IFERROR(SUM(L99),0) -> 0 | P99: Illustrative estimate (USD). Internal cost = staff days x 250/day blended rate. External and tool costs are indicative list pricing, not quotations.
A100: 0 | B100: 🛡️ PR Protect | C100: OT/ICS Network Security | D100: =IFERROR(IF('PR Protect'!P49="⏳ Complete rating and target to generate recommendation.","⏳ Rate this control in the domain sheet to auto-generate.",'PR Protect'!P49),"—") -> ⏳ Rate this control in the domain sheet to auto-generate. | G100: Grace Ayuk — IT Operations Manager | H100: Deferred | N100: =IFERROR(SUM(J100,K100,M100),0) -> 0 | O100: =IFERROR(SUM(L100),0) -> 0 | P100: Out of scope for this organisation — no cost carried.
A101: 0.52 | B101: 🛡️ PR Protect | C101: Secure SDLC — Security Requirements | D101: =IFERROR(IF('PR Protect'!P50="⏳ Complete rating and target to generate recommendation.","⏳ Rate this control in the domain sheet to auto-generate.",'PR Protect'!P50),"—") -> Standardise Secure SDLC — Security Requirements: formalise all documentation, apply the control consistently across all in-scope assets, close remaining coverage gaps, and ensure evidence is collected routinely. Exceptions must be formally managed with named owners and defined expiry dates. | E101: High (1-3 months) | F101: Q4 2026 | G101: Tunde Balogun — Lead Software Engineer | H101: Not Started | J101: 3000 | N101: =IFERROR(SUM(J101,K101,M101),0) -> 3000 | O101: =IFERROR(SUM(L101),0) -> 0 | P101: Illustrative estimate (USD). Internal cost = staff days x 250/day blended rate. External and tool costs are indicative list pricing, not quotations.
A102: 0.78 | B102: 🛡️ PR Protect | C102: Secure SDLC — Static Analysis (SAST) | D102: =IFERROR(IF('PR Protect'!P51="⏳ Complete rating and target to generate recommendation.","⏳ Rate this control in the domain sheet to auto-generate.",'PR Protect'!P51),"—") -> Instrument Secure SDLC — Static Analysis (SAST) with measurable KPIs: define performance thresholds (coverage %, SLA adherence, exception count), establish automated telemetry where possible, and integrate reporting into quarterly governance cycles. Evidence must be system-generated and reviewed at each governance cycle. | E102: High (1-3 months) | F102: Q1 2027 | G102: Tunde Balogun — Lead Software Engineer | H102: Not Started | J102: 3000 | N102: =IFERROR(SUM(J102,K102,M102),0) -> 3000 | O102: =IFERROR(SUM(L102),0) -> 0 | P102: Illustrative estimate (USD). Internal cost = staff days x 250/day blended rate. External and tool costs are indicative list pricing, not quotations.
A103: 0.26 | B103: 🛡️ PR Protect | C103: Secure SDLC — Software Composition Analysis (SCA) | D103: =IFERROR(IF('PR Protect'!P52="⏳ Complete rating and target to generate recommendation.","⏳ Rate this control in the domain sheet to auto-generate.",'PR Protect'!P52),"—") -> Standardise Secure SDLC — Software Composition Analysis (SCA): formalise all documentation, apply the control consistently across all in-scope assets, close remaining coverage gaps, and ensure evidence is collected routinely. Exceptions must be formally managed with named owners and defined expiry dates. | E103: Medium (1-4 weeks) | F103: Q3 2027 | G103: Tunde Balogun — Lead Software Engineer | H103: Not Started | J103: 1250 | N103: =IFERROR(SUM(J103,K103,M103),0) -> 1250 | O103: =IFERROR(SUM(L103),0) -> 0 | P103: Illustrative estimate (USD). Internal cost = staff days x 250/day blended rate. External and tool costs are indicative list pricing, not quotations.
A104: 0.78 | B104: 🛡️ PR Protect | C104: Secure SDLC — Dynamic Analysis (DAST) | D104: =IFERROR(IF('PR Protect'!P53="⏳ Complete rating and target to generate recommendation.","⏳ Rate this control in the domain sheet to auto-generate.",'PR Protect'!P53),"—") -> Instrument Secure SDLC — Dynamic Analysis (DAST) with measurable KPIs: define performance thresholds (coverage %, SLA adherence, exception count), establish automated telemetry where possible, and integrate reporting into quarterly governance cycles. Evidence must be system-generated and reviewed at each governance cycle. | E104: High (1-3 months) | F104: Q4 2026 | G104: Tunde Balogun — Lead Software Engineer | H104: Not Started | J104: 3000 | N104: =IFERROR(SUM(J104,K104,M104),0) -> 3000 | O104: =IFERROR(SUM(L104),0) -> 0 | P104: Illustrative estimate (USD). Internal cost = staff days x 250/day blended rate. External and tool costs are indicative list pricing, not quotations.
A105: 0.78 | B105: 🛡️ PR Protect | C105: Secure SDLC — Release Security Sign-Off | D105: =IFERROR(IF('PR Protect'!P54="⏳ Complete rating and target to generate recommendation.","⏳ Rate this control in the domain sheet to auto-generate.",'PR Protect'!P54),"—") -> Instrument Secure SDLC — Release Security Sign-Off with measurable KPIs: define performance thresholds (coverage %, SLA adherence, exception count), establish automated telemetry where possible, and integrate reporting into quarterly governance cycles. Evidence must be system-generated and reviewed at each governance cycle. | E105: High (1-3 months) | F105: Q4 2026 | G105: Tunde Balogun — Lead Software Engineer | H105: Not Started | J105: 3000 | N105: =IFERROR(SUM(J105,K105,M105),0) -> 3000 | O105: =IFERROR(SUM(L105),0) -> 0 | P105: Illustrative estimate (USD). Internal cost = staff days x 250/day blended rate. External and tool costs are indicative list pricing, not quotations.
A106: 0.52 | B106: 🛡️ PR Protect | C106: API Security — Inventory & Gateway | D106: =IFERROR(IF('PR Protect'!P55="⏳ Complete rating and target to generate recommendation.","⏳ Rate this control in the domain sheet to auto-generate.",'PR Protect'!P55),"—") -> Standardise API Security — Inventory & Gateway: formalise all documentation, apply the control consistently across all in-scope assets, close remaining coverage gaps, and ensure evidence is collected routinely. Exceptions must be formally managed with named owners and defined expiry dates. | E106: High (1-3 months) | F106: Q1 2027 | G106: Tunde Balogun — Lead Software Engineer | H106: Not Started | J106: 3000 | N106: =IFERROR(SUM(J106,K106,M106),0) -> 3000 | O106: =IFERROR(SUM(L106),0) -> 0 | P106: Illustrative estimate (USD). Internal cost = staff days x 250/day blended rate. External and tool costs are indicative list pricing, not quotations.
...

Sheet GV Govern
A1: 🏛️ GOVERN — Leadership, Strategy & Risk Governance · 28 Controls · Domain Weight: 16%
B2: 📝 Col D = Control Description | Col E = Risk & Maturity Impact | Col F = Assessment narrative | Col G = Evidence artefacts | Col H = Evidence Register link | Col I = Rating | Col N = Auto level description | Col S = Override scope (Apply / Exclude) | I2: Current: | J2: =IFERROR(AVERAGEIFS(J4:J31,T4:T31,"✅ Applicable"),"—") -> 1.1481481 | K2: Target: | L2: =IFERROR(AVERAGEIFS(L4:L31,T4:T31,"✅ Applicable"),"—") -> 3.3703704 | M2: Rated: | N2: =IFERROR(COUNTIFS(J4:J31,"<>",T4:T31,"✅ Applicable")&" / "&COUNTIF(T4:T31,"✅ Applicable")&" applicable","—") -> 27 / 27 applicable | P2: Auto-excl.: | Q2: =COUNTIF(T4:T31,"⬛ Auto-Excluded")&" controls (scoping)" -> 0 controls (scoping)
A3: # | B3: Category | C3: Control Name | D3: Control Description | E3: Risk & Maturity Impact (Why This Control Matters) | F3: 📝 Assessment (Current state & key gaps) | G3: 🗂️ Evidence (Artefacts & links) | H3: Evidence Reference | I3: Maturity Rating ▼ Select level | J3: Score (Auto) | K3: Target Level ▼ Select target | L3: Target Score | M3: Gap | N3: Level Description (Auto — control-specific) | O3: 🚦 Status | P3: 💡 Recommendation | Q3: Frameworks & Regulations | R3: Owner | S3: Scope (Apply / Exclude) | T3: ⚙️ Eff. Scope
A4: 1 | B4: Leadership & Strategy | C4: CISO / Security Leadership | D4: CISO / Security Leadership ensures that ciso or equivalent with board access, mandate, documented authority, and annual performance review. Establish a named security leader with board access, formal mandate, budget authority, and KPIs measured quarterly. | E4: Reduces strategic and governance risk by ensuring cybersecurity decisions carry executive authority, board visibility, and accountable ownership. Without CISO / Security Leadership, security investments lack mandate, reporting lacks credibility, and regulatory accountability obligations remain unmet. | F4: No CISO or equivalent. Security accountability sits with the Head of IT alongside infrastructure and service desk delivery, with no documented mandate, no defined authority and no board reporting line. | G4: Org chart (HR, June 2026) showing no security role above analyst level; confirmed in interview with the Managing Director. | H4: =HYPERLINK("#'📎 Evidence Register'!C6","ER-001 → Row 6") -> ER-001 → Row 6 | I4: L1 — Initial | J4: =IF(I4="","",IF(LEFT(I4,2)="L1",1,IF(LEFT(I4,2)="L2",2,IF(LEFT(I4,2)="L3",3,IF(LEFT(I4,2)="L4",4,IF(LEFT(I4,2)="L5",5,"")))))) -> 1 | K4: L3 — Defined | L4: =IF(K4="","",IF(LEFT(K4,2)="L1",1,IF(LEFT(K4,2)="L2",2,IF(LEFT(K4,2)="L3",3,IF(LEFT(K4,2)="L4",4,IF(LEFT(K4,2)="L5",5,"")))))) -> 3 | M4: =IFERROR(IF(OR(J4="",L4=""),"—",L4-J4),"—") -> 2 | N4: =IFERROR(IF(I4="","⏳ Select a maturity rating to see the level description for this specific control.",INDEX(_DV!$1:$5,MATCH(LEFT(I4,2),{"L1","L2","L3","L4","L5"},0),1)),"⏳ Select a maturity rating.") -> L1 — Initial: CISO / Security Leadership is absent or ad hoc. No formal process, no documentation, no named owner. Controls exist only reactively after incidents. | O4: =IF(S4="Exclude","⬛ Not Applicable",IF(T4="⬛ Auto-Excluded","⬛ Not Applicable",IF(I4="","✅ Applicable",IF(J4=1,"🔴 Critical",IF(J4=2,"🟠 Developing",IF(J4=3,"🟡 Defined",IF(J4>=4,"🟢 Managed","✅ Applicable"))))))) -> 🔴 Critical | P4: =IF(OR(J4="",L4=""),"⏳ Complete rating and target to generate recommendation.",IF(L4<=J4,"✅ Target met — sustain evidence and raise target when programme allows.",IFERROR(INDEX(_REC!$B:$B,MATCH(A4&"|"&IF(L4="","",LEFT(TEXT(L4,"0"),1)),_REC!$A:$A,0)),"Recommendation pending — check _REC data."))) -> Standardise CISO / Security Leadership: formalise all documentation, apply the control consistently across all in-scope assets, close remaining coverage gaps, and ensure evidence is collected routinely. Exceptions must be formally managed with named owners and defined expiry dates. | Q4: NIS2 Art.20|DORA Art.5|ISO 27001 A.5.2|NIST CSF GV.OC-01|COBIT APO01 | R4: Jean-Paul Nkeng — Managing Director | S4: Apply | T4: =IF(S4="Exclude","⬛ Excluded",IF(S4="Apply","✅ Applicable","✅ Applicable")) -> ✅ Applicable
A5: 2 | B5: Leadership & Strategy | C5: Cybersecurity Strategy & Programme | D5: Cybersecurity Strategy & Programme ensures that board-approved multi-year security strategy aligned to business objectives and risk appetite. Strategy defines priority risk areas, investment rationale, and business linkage. | E5: Reduces strategic and governance risk by ensuring cybersecurity decisions carry executive authority, board visibility, and accountable ownership. Without Cybersecurity Strategy & Programme, security investments lack mandate, reporting lacks credibility, and regulatory accountability obligations remain unmet. | F5: No security strategy exists. Security work is driven by acquiring bank questionnaires and audit findings rather than by a plan. Nothing has been presented to or approved by the board. | G5: None. Board pack index for FY2025 and FY2026 reviewed — no security agenda item. | H5: =HYPERLINK("#'📎 Evidence Register'!C7","ER-002 → Row 7") -> ER-002 → Row 7 | I5: L1 — Initial | J5: =IF(I5="","",IF(LEFT(I5,2)="L1",1,IF(LEFT(I5,2)="L2",2,IF(LEFT(I5,2)="L3",3,IF(LEFT(I5,2)="L4",4,IF(LEFT(I5,2)="L5",5,"")))))) -> 1 | K5: L3 — Defined | L5: =IF(K5="","",IF(LEFT(K5,2)="L1",1,IF(LEFT(K5,2)="L2",2,IF(LEFT(K5,2)="L3",3,IF(LEFT(K5,2)="L4",4,IF(LEFT(K5,2)="L5",5,"")))))) -> 3 | M5: =IFERROR(IF(OR(J5="",L5=""),"—",L5-J5),"—") -> 2 | N5: =IFERROR(IF(I5="","⏳ Select a maturity rating to see the level description for this specific control.",INDEX(_DV!$1:$5,MATCH(LEFT(I5,2),{"L1","L2","L3","L4","L5"},0),2)),"⏳ Select a maturity rating.") -> L1 — Initial: Cybersecurity Strategy & Programme is absent or ad hoc. No formal process, no documentation, no named owner. Controls exist only reactively after incidents. | O5: =IF(S5="Exclude","⬛ Not Applicable",IF(T5="⬛ Auto-Excluded","⬛ Not Applicable",IF(I5="","✅ Applicable",IF(J5=1,"🔴 Critical",IF(J5=2,"🟠 Developing",IF(J5=3,"🟡 Defined",IF(J5>=4,"🟢 Managed","✅ Applicable"))))))) -> 🔴 Critical | P5: =IF(OR(J5="",L5=""),"⏳ Complete rating and target to generate recommendation.",IF(L5<=J5,"✅ Target met — sustain evidence and raise target when programme allows.",IFERROR(INDEX(_REC!$B:$B,MATCH(A5&"|"&IF(L5="","",LEFT(TEXT(L5,"0"),1)),_REC!$A:$A,0)),"Recommendation pending — check _REC data."))) -> Standardise Cybersecurity Strategy & Programme: formalise all documentation, apply the control consistently across all in-scope assets, close remaining coverage gaps, and ensure evidence is collected routinely. Exceptions must be formally managed with named owners and defined expiry dates. | Q5: NIS2|DORA Art.6|ISO 27001 6.2|NIST CSF GV.OC-04|COBIT APO02 | R5: Jean-Paul Nkeng — Managing Director | T5: =IF(S5="Exclude","⬛ Excluded",IF(S5="Apply","✅ Applicable","✅ Applicable")) -> ✅ Applicable
A6: 3 | B6: Leadership & Strategy | C6: Cyber Budget & Investment Model | D6: Cyber Budget & Investment Model ensures that security budget approved as percentage of it spend with risk-based allocation and tracking. Annual budget approved by board; investment tracked quarterly against risk indicators. | E6: Reduces strategic and governance risk by ensuring cybersecurity decisions carry executive authority, board visibility, and accountable ownership. Without Cyber Budget & Investment Model, security investments lack mandate, reporting lacks credibility, and regulatory accountability obligations remain unmet. | F6: Security spend is approved case by case as part of the IT budget. There is no security line item, no percentage-of-IT-spend basis and no tracking of spend against risk. | G6: FY2026 IT budget spreadsheet showing security tooling embedded in general IT lines — Tier 2, documentary. | H6: =HYPERLINK("#'📎 Evidence Register'!C8","ER-003 → Row 8") -> ER-003 → Row 8 | I6: L2 — Developing | J6: =IF(I6="","",IF(LEFT(I6,2)="L1",1,IF(LEFT(I6,2)="L2",2,IF(LEFT(I6,2)="L3",3,IF(LEFT(I6,2)="L4",4,IF(LEFT(I6,2)="L5",5,"")))))) -> 2 | K6: L3 — Defined | L6: =IF(K6="","",IF(LEFT(K6,2)="L1",1,IF(LEFT(K6,2)="L2",2,IF(LEFT(K6,2)="L3",3,IF(LEFT(K6,2)="L4",4,IF(LEFT(K6,2)="L5",5,"")))))) -> 3 | M6: =IFERROR(IF(OR(J6="",L6=""),"—",L6-J6),"—") -> 1 | N6: =IFERROR(IF(I6="","⏳ Select a maturity rating to see the level description for this specific control.",INDEX(_DV!$1:$5,MATCH(LEFT(I6,2),{"L1","L2","L3","L4","L5"},0),3)),"⏳ Select a maturity rating.") -> L2 — Developing: Cyber Budget & Investment Model has basic controls in place but coverage is incomplete and execution is manual. Not consistently applied across all in-scope assets. Formal governance is absent. | O6: =IF(S6="Exclude","⬛ Not Applicable",IF(T6="⬛ Auto-Excluded","⬛ Not Applicable",IF(I6="","✅ Applicable",IF(J6=1,"🔴 Critical",IF(J6=2,"🟠 Developing",IF(J6=3,"🟡 Defined",IF(J6>=4,"🟢 Managed","✅ Applicable"))))))) -> 🟠 Developing | P6: =IF(OR(J6="",L6=""),"⏳ Complete rating and target to generate recommendation.",IF(L6<=J6,"✅ Target met — sustain evidence and raise target when programme allows.",IFERROR(INDEX(_REC!$B:$B,MATCH(A6&"|"&IF(L6="","",LEFT(TEXT(L6,"0"),1)),_REC!$A:$A,0)),"Recommendation pending — check _REC data."))) -> Standardise Cyber Budget & Investment Model: formalise all documentation, apply the control consistently across all in-scope assets, close remaining coverage gaps, and ensure evidence is collected routinely. Exceptions must be formally managed with named owners and defined expiry dates. | Q6: COBIT 2019|ISO 27001 A.5.31|NIS2|DORA Art.6 | R6: Paul Mbarga — Finance Director | T6: =IF(S6="Exclude","⬛ Excluded",IF(S6="Apply","✅ Applicable","✅ Applicable")) -> ✅ Applicable
A7: 4 | B7: Leadership & Strategy | C7: Security Organisational Structure | D7: Security Organisational Structure ensures that defined roles, responsibilities, and reporting lines for security across the enterprise. All security functions have named backup; RACI documented and current. | E7: Reduces strategic and governance risk by ensuring cybersecurity decisions carry executive authority, board visibility, and accountable ownership. Without Security Organisational Structure, security investments lack mandate, reporting lacks credibility, and regulatory accountability obligations remain unmet. | F7: No documented security roles, responsibilities or reporting lines. Responsibilities are understood informally within a four-person infrastructure team. | G7: None. Confirmed by interview with Head of IT — no RACI or role description exists. | H7: =HYPERLINK("#'📎 Evidence Register'!C9","ER-004 → Row 9") -> ER-004 → Row 9 | I7: L1 — Initial | J7: =IF(I7="","",IF(LEFT(I7,2)="L1",1,IF(LEFT(I7,2)="L2",2,IF(LEFT(I7,2)="L3",3,IF(LEFT(I7,2)="L4",4,IF(LEFT(I7,2)="L5",5,"")))))) -> 1 | K7: L3 — Defined | L7: =IF(K7="","",IF(LEFT(K7,2)="L1",1,IF(LEFT(K7,2)="L2",2,IF(LEFT(K7,2)="L3",3,IF(LEFT(K7,2)="L4",4,IF(LEFT(K7,2)="L5",5,"")))))) -> 3 | M7: =IFERROR(IF(OR(J7="",L7=""),"—",L7-J7),"—") -> 2 | N7: =IFERROR(IF(I7="","⏳ Select a maturity rating to see the level description for this specific control.",INDEX(_DV!$1:$5,MATCH(LEFT(I7,2),{"L1","L2","L3","L4","L5"},0),4)),"⏳ Select a maturity rating.") -> L1 — Initial: Security Organisational Structure is absent or ad hoc. No formal process, no documentation, no named owner. Controls exist only reactively after incidents. | O7: =IF(S7="Exclude","⬛ Not Applicable",IF(T7="⬛ Auto-Excluded","⬛ Not Applicable",IF(I7="","✅ Applicable",IF(J7=1,"🔴 Critical",IF(J7=2,"🟠 Developing",IF(J7=3,"🟡 Defined",IF(J7>=4,"🟢 Managed","✅ Applicable"))))))) -> 🔴 Critical | P7: =IF(OR(J7="",L7=""),"⏳ Complete rating and target to generate recommendation.",IF(L7<=J7,"✅ Target met — sustain evidence and raise target when programme allows.",IFERROR(INDEX(_REC!$B:$B,MATCH(A7&"|"&IF(L7="","",LEFT(TEXT(L7,"0"),1)),_REC!$A:$A,0)),"Recommendation pending — check _REC data."))) -> Standardise Security Organisational Structure: formalise all documentation, apply the control consistently across all in-scope assets, close remaining coverage gaps, and ensure evidence is collected routinely. Exceptions must be formally managed with named owners and defined expiry dates. | Q7: ISO 27001 A.5.2|NIS2 Art.20|NIST CSF GV.OC-01|COBIT APO01 | R7: Marc Etonde — Head of IT | T7: =IF(S7="Exclude","⬛ Excluded",IF(S7="Apply","✅ Applicable","✅ Applicable")) -> ✅ Applicable
A8: 5 | B8: Leadership & Strategy | C8: Board-Level Cybersecurity Oversight | D8: Board-Level Cybersecurity Oversight ensures that board and audit committee engagement with cybersecurity risk, strategy, and investment. Quarterly board reporting on cyber posture and investment. | E8: Reduces strategic and governance risk by ensuring cybersecurity decisions carry executive authority, board visibility, and accountable ownership. Without Board-Level Cybersecurity Oversight, security investments lack mandate, reporting lacks credibility, and regulatory accountability obligations remain unmet. | F8: Cybersecurity has never been a standing board or audit committee item. It reaches the board only when the acquiring bank escalates a finding. | G8: Board minutes 2025–2026 sampled — no recurring cyber item. | H8: =HYPERLINK("#'📎 Evidence Register'!C10","ER-005 → Row 10") -> ER-005 → Row 10 | I8: L1 — Initial | J8: =IF(I8="","",IF(LEFT(I8,2)="L1",1,IF(LEFT(I8,2)="L2",2,IF(LEFT(I8,2)="L3",3,IF(LEFT(I8,2)="L4",4,IF(LEFT(I8,2)="L5",5,"")))))) -> 1 | K8: L3 — Defined | L8: =IF(K8="","",IF(LEFT(K8,2)="L1",1,IF(LEFT(K8,2)="L2",2,IF(LEFT(K8,2)="L3",3,IF(LEFT(K8,2)="L4",4,IF(LEFT(K8,2)="L5",5,"")))))) -> 3 | M8: =IFERROR(IF(OR(J8="",L8=""),"—",L8-J8),"—") -> 2 | N8: =IFERROR(IF(I8="","⏳ Select a maturity rating to see the level description for this specific control.",INDEX(_DV!$1:$5,MATCH(LEFT(I8,2),{"L1","L2","L3","L4","L5"},0),5)),"⏳ Select a maturity rating.") -> L1 — Initial: Board-Level Cybersecurity Oversight is absent or ad hoc. No formal process, no documentation, no named owner. Controls exist only reactively after incidents. | O8: =IF(S8="Exclude","⬛ Not Applicable",IF(T8="⬛ Auto-Excluded","⬛ Not Applicable",IF(I8="","✅ Applicable",IF(J8=1,"🔴 Critical",IF(J8=2,"🟠 Developing",IF(J8=3,"🟡 Defined",IF(J8>=4,"🟢 Managed","✅ Applicable"))))))) -> 🔴 Critical | P8: =IF(OR(J8="",L8=""),"⏳ Complete rating and target to generate recommendation.",IF(L8<=J8,"✅ Target met — sustain evidence and raise target when programme allows.",IFERROR(INDEX(_REC!$B:$B,MATCH(A8&"|"&IF(L8="","",LEFT(TEXT(L8,"0"),1)),_REC!$A:$A,0)),"Recommendation pending — check _REC data."))) -> Standardise Board-Level Cybersecurity Oversight: formalise all documentation, apply the control consistently across all in-scope assets, close remaining coverage gaps, and ensure evidence is collected routinely. Exceptions must be formally managed with named owners and defined expiry dates. | Q8: NIS2 Art.20|DORA Art.5|SOX|COBIT APO01 | R8: Jean-Paul Nkeng — Managing Director | T8: =IF(S8="Exclude","⬛ Excluded",IF(S8="Apply","✅ Applicable","✅ Applicable")) -> ✅ Applicable
A9: 6 | B9: Policy Framework | C9: Security Policy Framework & Hierarchy | D9: Security Policy Framework & Hierarchy ensures that structured policy library with master policy, domain policies, standards, and procedures. Policy hierarchy documented and current (<=12 months). | E9: Reduces policy compliance risk by ensuring security requirements are formally documented, consistently enforced, and regularly reviewed. Without Security Policy Framework & Hierarchy, control obligations are applied inconsistently, creating exploitable gaps and audit exposure. | F9: An Information Security Policy exists, approved 2021, but there are no supporting domain policies, standards or procedures beneath it. The hierarchy is a single document. | G9: Information Security Policy v1.2 (2021), unreviewed since issue — Tier 2, documentary. | H9: =HYPERLINK("#'📎 Evidence Register'!C11","ER-006 → Row 11") -> ER-006 → Row 11 | I9: L2 — Developing | J9: =IF(I9="","",IF(LEFT(I9,2)="L1",1,IF(LEFT(I9,2)="L2",2,IF(LEFT(I9,2)="L3",3,IF(LEFT(I9,2)="L4",4,IF(LEFT(I9,2)="L5",5,"")))))) -> 2 | K9: L3 — Defined | L9: =IF(K9="","",IF(LEFT(K9,2)="L1",1,IF(LEFT(K9,2)="L2",2,IF(LEFT(K9,2)="L3",3,IF(LEFT(K9,2)="L4",4,IF(LEFT(K9,2)="L5",5,"")))))) -> 3 | M9: =IFERROR(IF(OR(J9="",L9=""),"—",L9-J9),"—") -> 1 | N9: =IFERROR(IF(I9="","⏳ Select a maturity rating to see the level description for this specific control.",INDEX(_DV!$1:$5,MATCH(LEFT(I9,2),{"L1","L2","L3","L4","L5"},0),6)),"⏳ Select a maturity rating.") -> L2 — Developing: Security Policy Framework & Hierarchy has basic controls in place but coverage is incomplete and execution is manual. Not consistently applied across all in-scope assets. Formal governance is absent. | O9: =IF(S9="Exclude","⬛ Not Applicable",IF(T9="⬛ Auto-Excluded","⬛ Not Applicable",IF(I9="","✅ Applicable",IF(J9=1,"🔴 Critical",IF(J9=2,"🟠 Developing",IF(J9=3,"🟡 Defined",IF(J9>=4,"🟢 Managed","✅ Applicable"))))))) -> 🟠 Developing | P9: =IF(OR(J9="",L9=""),"⏳ Complete rating and target to generate recommendation.",IF(L9<=J9,"✅ Target met — sustain evidence and raise target when programme allows.",IFERROR(INDEX(_REC!$B:$B,MATCH(A9&"|"&IF(L9="","",LEFT(TEXT(L9,"0"),1)),_REC!$A:$A,0)),"Recommendation pending — check _REC data."))) -> Standardise Security Policy Framework & Hierarchy: formalise all documentation, apply the control consistently across all in-scope assets, close remaining coverage gaps, and ensure evidence is collected routinely. Exceptions must be formally managed with named owners and defined expiry dates. | Q9: ISO 27001 A.5.1|NIS2|DORA|COBIT APO01 | R9: Marie Fotso — Legal & Compliance Counsel | T9: =IF(S9="Exclude","⬛ Excluded",IF(S9="Apply","✅ Applicable","✅ Applicable")) -> ✅ Applicable
A10: 7 | B10: Policy Framework | C10: Policy Attestation & Enforcement | D10: Policy Attestation & Enforcement ensures that staff acknowledgement tracked; non-compliance escalated; breach process active. Annual attestation >=95% completion. | E10: Reduces policy compliance risk by ensuring security requirements are formally documented, consistently enforced, and regularly reviewed. Without Policy Attestation & Enforcement, control obligations are applied inconsistently, creating exploitable gaps and audit exposure. | F10: Policy acknowledgement is captured at onboarding only. There is no annual re-attestation, no completion tracking and no escalation route for non-compliance. | G10: Onboarding acknowledgement forms for 2026 joiners held in HR files — partial population, Tier 2. | H10: =HYPERLINK("#'📎 Evidence Register'!C12","ER-007 → Row 12") -> ER-007 → Row 12 | I10: L2 — Developing | J10: =IF(I10="","",IF(LEFT(I10,2)="L1",1,IF(LEFT(I10,2)="L2",2,IF(LEFT(I10,2)="L3",3,IF(LEFT(I10,2)="L4",4,IF(LEFT(I10,2)="L5",5,"")))))) -> 2 | K10: L3 — Defined | L10: =IF(K10="","",IF(LEFT(K10,2)="L1",1,IF(LEFT(K10,2)="L2",2,IF(LEFT(K10,2)="L3",3,IF(LEFT(K10,2)="L4",4,IF(LEFT(K10,2)="L5",5,"")))))) -> 3 | M10: =IFERROR(IF(OR(J10="",L10=""),"—",L10-J10),"—") -> 1 | N10: =IFERROR(IF(I10="","⏳ Select a maturity rating to see the level description for this specific control.",INDEX(_DV!$1:$5,MATCH(LEFT(I10,2),{"L1","L2","L3","L4","L5"},0),7)),"⏳ Select a maturity rating.") -> L2 — Developing: Policy Attestation & Enforcement has basic controls in place but coverage is incomplete and execution is manual. Not consistently applied across all in-scope assets. Formal governance is absent. | O10: =IF(S10="Exclude","⬛ Not Applicable",IF(T10="⬛ Auto-Excluded","⬛ Not Applicable",IF(I10="","✅ Applicable",IF(J10=1,"🔴 Critical",IF(J10=2,"🟠 Developing",IF(J10=3,"🟡 Defined",IF(J10>=4,"🟢 Managed","✅ Applicable"))))))) -> 🟠 Developing | P10: =IF(OR(J10="",L10=""),"⏳ Complete rating and target to generate recommendation.",IF(L10<=J10,"✅ Target met — sustain evidence and raise target when programme allows.",IFERROR(INDEX(_REC!$B:$B,MATCH(A10&"|"&IF(L10="","",LEFT(TEXT(L10,"0"),1)),_REC!$A:$A,0)),"Recommendation pending — check _REC data."))) -> Standardise Policy Attestation & Enforcement: formalise all documentation, apply the control consistently across all in-scope assets, close remaining coverage gaps, and ensure evidence is collected routinely. Exceptions must be formally managed with named owners and defined expiry dates. | Q10: ISO 27001|HIPAA S164.530|SOX|NIS2 | R10: Ruth Anong — HR Manager | T10: =IF(S10="Exclude","⬛ Excluded",IF(S10="Apply","✅ Applicable","✅ Applicable")) -> ✅ Applicable
A11: 8 | B11: Policy Framework | C11: Policy Exception Governance | D11: Policy Exception Governance ensures that formal exception process with risk acceptance, owner, and expiry for all policy deviations. Exception register maintained; each exception has named owner, expiry date, risk acceptance. | E11: Reduces policy compliance risk by ensuring security requirements are formally documented, consistently enforced, and regularly reviewed. Without Policy Exception Governance, control obligations are applied inconsistently, creating exploitable gaps and audit exposure. | F11: No exception process. Deviations from policy are agreed verbally and not recorded, so there is no register, no risk acceptance and no expiry. | G11: None. No exception register exists. | H11: =HYPERLINK("#'📎 Evidence Register'!C13","ER-008 → Row 13") -> ER-008 → Row 13 | I11: L1 — Initial | J11: =IF(I11="","",IF(LEFT(I11,2)="L1",1,IF(LEFT(I11,2)="L2",2,IF(LEFT(I11,2)="L3",3,IF(LEFT(I11,2)="L4",4,IF(LEFT(I11,2)="L5",5,"")))))) -> 1 | K11: L3 — Defined | L11: =IF(K11="","",IF(LEFT(K11,2)="L1",1,IF(LEFT(K11,2)="L2",2,IF(LEFT(K11,2)="L3",3,IF(LEFT(K11,2)="L4",4,IF(LEFT(K11,2)="L5",5,"")))))) -> 3 | M11: =IFERROR(IF(OR(J11="",L11=""),"—",L11-J11),"—") -> 2 | N11: =IFERROR(IF(I11="","⏳ Select a maturity rating to see the level description for this specific control.",INDEX(_DV!$1:$5,MATCH(LEFT(I11,2),{"L1","L2","L3","L4","L5"},0),8)),"⏳ Select a maturity rating.") -> L1 — Initial: Policy Exception Governance is absent or ad hoc. No formal process, no documentation, no named owner. Controls exist only reactively after incidents. | O11: =IF(S11="Exclude","⬛ Not Applicable",IF(T11="⬛ Auto-Excluded","⬛ Not Applicable",IF(I11="","✅ Applicable",IF(J11=1,"🔴 Critical",IF(J11=2,"🟠 Developing",IF(J11=3,"🟡 Defined",IF(J11>=4,"🟢 Managed","✅ Applicable"))))))) -> 🔴 Critical | P11: =IF(OR(J11="",L11=""),"⏳ Complete rating and target to generate recommendation.",IF(L11<=J11,"✅ Target met — sustain evidence and raise target when programme allows.",IFERROR(INDEX(_REC!$B:$B,MATCH(A11&"|"&IF(L11="","",LEFT(TEXT(L11,"0"),1)),_REC!$A:$A,0)),"Recommendation pending — check _REC data."))) -> Standardise Policy Exception Governance: formalise all documentation, apply the control consistently across all in-scope assets, close remaining coverage gaps, and ensure evidence is collected routinely. Exceptions must be formally managed with named owners and defined expiry dates. | Q11: ISO 27001 A.5.20|NIST SP 800-53 PM-4|NIS2 | R11: Marc Etonde — Head of IT | T11: =IF(S11="Exclude","⬛ Excluded",IF(S11="Apply","✅ Applicable","✅ Applicable")) -> ✅ Applicable
A12: 9 | B12: Policy Framework | C12: Control Standards Management | D12: Control Standards Management ensures that baseline security standards defined per asset class with version control. Standards documented for endpoints, cloud, network, apps. | E12: Reduces policy compliance risk by ensuring security requirements are formally documented, consistently enforced, and regularly reviewed. Without Control Standards Management, control obligations are applied inconsistently, creating exploitable gaps and audit exposure. | F12: No baseline security standards per asset class. Server and endpoint builds are based on the technician's judgement and an informal build checklist. | G12: Informal build checklist held on a shared drive; no version control — Tier 3. | H12: =HYPERLINK("#'📎 Evidence Register'!C14","ER-009 → Row 14") -> ER-009 → Row 14 | I12: L1 — Initial | J12: =IF(I12="","",IF(LEFT(I12,2)="L1",1,IF(LEFT(I12,2)="L2",2,IF(LEFT(I12,2)="L3",3,IF(LEFT(I12,2)="L4",4,IF(LEFT(I12,2)="L5",5,"")))))) -> 1 | K12: L3 — Defined | L12: =IF(K12="","",IF(LEFT(K12,2)="L1",1,IF(LEFT(K12,2)="L2",2,IF(LEFT(K12,2)="L3",3,IF(LEFT(K12,2)="L4",4,IF(LEFT(K12,2)="L5",5,"")))))) -> 3 | M12: =IFERROR(IF(OR(J12="",L12=""),"—",L12-J12),"—") -> 2 | N12: =IFERROR(IF(I12="","⏳ Select a maturity rating to see the level description for this specific control.",INDEX(_DV!$1:$5,MATCH(LEFT(I12,2),{"L1","L2","L3","L4","L5"},0),9)),"⏳ Select a maturity rating.") -> L1 — Initial: Control Standards Management is absent or ad hoc. No formal process, no documentation, no named owner. Controls exist only reactively after incidents. | O12: =IF(S12="Exclude","⬛ Not Applicable",IF(T12="⬛ Auto-Excluded","⬛ Not Applicable",IF(I12="","✅ Applicable",IF(J12=1,"🔴 Critical",IF(J12=2,"🟠 Developing",IF(J12=3,"🟡 Defined",IF(J12>=4,"🟢 Managed","✅ Applicable"))))))) -> 🔴 Critical | P12: =IF(OR(J12="",L12=""),"⏳ Complete rating and target to generate recommendation.",IF(L12<=J12,"✅ Target met — sustain evidence and raise target when programme allows.",IFERROR(INDEX(_REC!$B:$B,MATCH(A12&"|"&IF(L12="","",LEFT(TEXT(L12,"0"),1)),_REC!$A:$A,0)),"Recommendation pending — check _REC data."))) -> Standardise Control Standards Management: formalise all documentation, apply the control consistently across all in-scope assets, close remaining coverage gaps, and ensure evidence is collected routinely. Exceptions must be formally managed with named owners and defined expiry dates. | Q12: CIS Controls v8|ISO 27001|NIST CSF | R12: Marc Etonde — Head of IT | T12: =IF(S12="Exclude","⬛ Excluded",IF(S12="Apply","✅ Applicable","✅ Applicable")) -> ✅ Applicable
A13: 10 | B13: Policy Framework | C13: Regulatory Obligation Register & Mapping | D13: Regulatory Obligation Register & Mapping ensures that complete register of all applicable legal, regulatory, and contractual security obligations. Register maintained with named owner per obligation; control mapping explicit; regulatory change alert active. | E13: Reduces policy compliance risk by ensuring security requirements are formally documented, consistently enforced, and regularly reviewed. Without Regulatory Obligation Register & Mapping, control obligations are applied inconsistently, creating exploitable gaps and audit exposure. | F13: No consolidated register of legal, regulatory and contractual security obligations. PCI DSS and GDPR requirements are tracked in separate email threads and the bank questionnaire responses. | G13: None consolidated. Bank questionnaire response (Oct 2025) used as a proxy. | H13: =HYPERLINK("#'📎 Evidence Register'!C15","ER-010 → Row 15") -> ER-010 → Row 15 | I13: L1 — Initial | J13: =IF(I13="","",IF(LEFT(I13,2)="L1",1,IF(LEFT(I13,2)="L2",2,IF(LEFT(I13,2)="L3",3,IF(LEFT(I13,2)="L4",4,IF(LEFT(I13,2)="L5",5,"")))))) -> 1 | K13: L4 — Managed | L13: =IF(K13="","",IF(LEFT(K13,2)="L1",1,IF(LEFT(K13,2)="L2",2,IF(LEFT(K13,2)="L3",3,IF(LEFT(K13,2)="L4",4,IF(LEFT(K13,2)="L5",5,"")))))) -> 4 | M13: =IFERROR(IF(OR(J13="",L13=""),"—",L13-J13),"—") -> 3 | N13: =IFERROR(IF(I13="","⏳ Select a maturity rating to see the level description for this specific control.",INDEX(_DV!$1:$5,MATCH(LEFT(I13,2),{"L1","L2","L3","L4","L5"},0),10)),"⏳ Select a maturity rating.") -> L1 — Initial: Regulatory Obligation Register & Mapping is absent or ad hoc. No formal process, no documentation, no named owner. Controls exist only reactively after incidents. | O13: =IF(S13="Exclude","⬛ Not Applicable",IF(T13="⬛ Auto-Excluded","⬛ Not Applicable",IF(I13="","✅ Applicable",IF(J13=1,"🔴 Critical",IF(J13=2,"🟠 Developing",IF(J13=3,"🟡 Defined",IF(J13>=4,"🟢 Managed","✅ Applicable"))))))) -> 🔴 Critical | P13: =IF(OR(J13="",L13=""),"⏳ Complete rating and target to generate recommendation.",IF(L13<=J13,"✅ Target met — sustain evidence and raise target when programme allows.",IFERROR(INDEX(_REC!$B:$B,MATCH(A13&"|"&IF(L13="","",LEFT(TEXT(L13,"0"),1)),_REC!$A:$A,0)),"Recommendation pending — check _REC data."))) -> Instrument Regulatory Obligation Register & Mapping with measurable KPIs: define performance thresholds (coverage %, SLA adherence, exception count), establish automated telemetry where possible, and integrate reporting into quarterly governance cycles. Evidence must be system-generated and reviewed at each governance cycle. | Q13: GDPR Art.24|NIS2|DORA Art.6|HIPAA|PCI DSS | R13: Marie Fotso — Legal & Compliance Counsel | T13: =IF(S13="Exclude","⬛ Excluded",IF(S13="Apply","✅ Applicable","✅ Applicable")) -> ✅ Applicable
A14: 11 | B14: Policy Framework | C14: Regulatory Change Management | D14: Regulatory Change Management ensures that process to monitor, assess, and implement changes to applicable regulations. Horizon-scanning subscription active; impact assessment within 30 days of new obligation. | E14: Reduces policy compliance risk by ensuring security requirements are formally documented, consistently enforced, and regularly reviewed. Without Regulatory Change Management, control obligations are applied inconsistently, creating exploitable gaps and audit exposure. | F14: No horizon scanning. Regulatory change reaches the business through the acquiring bank or external counsel, reactively. | G14: None. Confirmed by interview with Legal & Compliance Counsel. | H14: =HYPERLINK("#'📎 Evidence Register'!C16","ER-011 → Row 16") -> ER-011 → Row 16 | I14: L1 — Initial | J14: =IF(I14="","",IF(LEFT(I14,2)="L1",1,IF(LEFT(I14,2)="L2",2,IF(LEFT(I14,2)="L3",3,IF(LEFT(I14,2)="L4",4,IF(LEFT(I14,2)="L5",5,"")))))) -> 1 | K14: L4 — Managed | L14: =IF(K14="","",IF(LEFT(K14,2)="L1",1,IF(LEFT(K14,2)="L2",2,IF(LEFT(K14,2)="L3",3,IF(LEFT(K14,2)="L4",4,IF(LEFT(K14,2)="L5",5,"")))))) -> 4 | M14: =IFERROR(IF(OR(J14="",L14=""),"—",L14-J14),"—") -> 3 | N14: =IFERROR(IF(I14="","⏳ Select a maturity rating to see the level description for this specific control.",INDEX(_DV!$1:$5,MATCH(LEFT(I14,2),{"L1","L2","L3","L4","L5"},0),11)),"⏳ Select a maturity rating.") -> L1 — Initial: Regulatory Change Management is absent or ad hoc. No formal process, no documentation, no named owner. Controls exist only reactively after incidents. | O14: =IF(S14="Exclude","⬛ Not Applicable",IF(T14="⬛ Auto-Excluded","⬛ Not Applicable",IF(I14="","✅ Applicable",IF(J14=1,"🔴 Critical",IF(J14=2,"🟠 Developing",IF(J14=3,"🟡 Defined",IF(J14>=4,"🟢 Managed","✅ Applicable"))))))) -> 🔴 Critical | P14: =IF(OR(J14="",L14=""),"⏳ Complete rating and target to generate recommendation.",IF(L14<=J14,"✅ Target met — sustain evidence and raise target when programme allows.",IFERROR(INDEX(_REC!$B:$B,MATCH(A14&"|"&IF(L14="","",LEFT(TEXT(L14,"0"),1)),_REC!$A:$A,0)),"Recommendation pending — check _REC data."))) -> Instrument Regulatory Change Management with measurable KPIs: define performance thresholds (coverage %, SLA adherence, exception count), establish automated telemetry where possible, and integrate reporting into quarterly governance cycles. Evidence must be system-generated and reviewed at each governance cycle. | Q14: NIS2|DORA|CRA|GDPR|CCPA | R14: Marie Fotso — Legal & Compliance Counsel | T14: =IF(S14="Exclude","⬛ Excluded",IF(S14="Apply","✅ Applicable","✅ Applicable")) -> ✅ Applicable
A15: 12 | B15: Policy Framework | C15: Security Standards for Third Parties | D15: Security Standards for Third Parties ensures that minimum security standards contractually imposed on all suppliers and partners. Standard security schedule in all vendor contracts. | E15: Reduces policy compliance risk by ensuring security requirements are formally documented, consistently enforced, and regularly reviewed. Without Security Standards for Third Parties, control obligations are applied inconsistently, creating exploitable gaps and audit exposure. | F15: No minimum security standards are imposed on suppliers. Contracts use the standard commercial template with no security schedule. | G15: Sample of five supplier contracts reviewed — none contains security clauses. Tier 2. | H15: =HYPERLINK("#'📎 Evidence Register'!C17","ER-012 → Row 17") -> ER-012 → Row 17 | I15: L1 — Initial | J15: =IF(I15="","",IF(LEFT(I15,2)="L1",1,IF(LEFT(I15,2)="L2",2,IF(LEFT(I15,2)="L3",3,IF(LEFT(I15,2)="L4",4,IF(LEFT(I15,2)="L5",5,"")))))) -> 1 | K15: L4 — Managed | L15: =IF(K15="","",IF(LEFT(K15,2)="L1",1,IF(LEFT(K15,2)="L2",2,IF(LEFT(K15,2)="L3",3,IF(LEFT(K15,2)="L4",4,IF(LEFT(K15,2)="L5",5,"")))))) -> 4 | M15: =IFERROR(IF(OR(J15="",L15=""),"—",L15-J15),"—") -> 3 | N15: =IFERROR(IF(I15="","⏳ Select a maturity rating to see the level description for this specific control.",INDEX(_DV!$1:$5,MATCH(LEFT(I15,2),{"L1","L2","L3","L4","L5"},0),12)),"⏳ Select a maturity rating.") -> L1 — Initial: Security Standards for Third Parties is absent or ad hoc. No formal process, no documentation, no named owner. Controls exist only reactively after incidents. | O15: =IF(S15="Exclude","⬛ Not Applicable",IF(T15="⬛ Auto-Excluded","⬛ Not Applicable",IF(I15="","✅ Applicable",IF(J15=1,"🔴 Critical",IF(J15=2,"🟠 Developing",IF(J15=3,"🟡 Defined",IF(J15>=4,"🟢 Managed","✅ Applicable"))))))) -> 🔴 Critical | P15: =IF(OR(J15="",L15=""),"⏳ Complete rating and target to generate recommendation.",IF(L15<=J15,"✅ Target met — sustain evidence and raise target when programme allows.",IFERROR(INDEX(_REC!$B:$B,MATCH(A15&"|"&IF(L15="","",LEFT(TEXT(L15,"0"),1)),_REC!$A:$A,0)),"Recommendation pending — check _REC data."))) -> Instrument Security Standards for Third Parties with measurable KPIs: define performance thresholds (coverage %, SLA adherence, exception count), establish automated telemetry where possible, and integrate reporting into quarterly governance cycles. Evidence must be system-generated and reviewed at each governance cycle. | Q15: GDPR Art.28|DORA Art.30|NIS2 Art.21 | R15: Linda Ojo — Procurement Officer | T15: =IF(S15="Exclude","⬛ Excluded",IF(S15="Apply","✅ Applicable","✅ Applicable")) -> ✅ Applicable
A16: 13 | B16: Risk Management | C16: Enterprise Risk Framework Integration | D16: Enterprise Risk Framework Integration ensures that cyber risk integrated into erm with consistent methodology and shared taxonomy. Cyber risk on enterprise risk register; shared risk taxonomy; CISO attends risk committee. | E16: Reduces risk management blind spots by ensuring threats and treatment obligations are formally tracked, quantified, and governed. Without Enterprise Risk Framework Integration, risk decisions are reactive and unquantified, preventing board-level risk reporting and investment justification. | F16: Cyber risk is not represented in the enterprise risk framework. The corporate risk register carries a single line item, 'IT risk', with no owner or treatment plan. | G16: Corporate risk register (Q2 2026) — one undefined IT entry. Tier 2. | H16: =HYPERLINK("#'📎 Evidence Register'!C18","ER-013 → Row 18") -> ER-013 → Row 18 | I16: L1 — Initial | J16: =IF(I16="","",IF(LEFT(I16,2)="L1",1,IF(LEFT(I16,2)="L2",2,IF(LEFT(I16,2)="L3",3,IF(LEFT(I16,2)="L4",4,IF(LEFT(I16,2)="L5",5,"")))))) -> 1 | K16: L3 — Defined | L16: =IF(K16="","",IF(LEFT(K16,2)="L1",1,IF(LEFT(K16,2)="L2",2,IF(LEFT(K16,2)="L3",3,IF(LEFT(K16,2)="L4",4,IF(LEFT(K16,2)="L5",5,"")))))) -> 3 | M16: =IFERROR(IF(OR(J16="",L16=""),"—",L16-J16),"—") -> 2 | N16: =IFERROR(IF(I16="","⏳ Select a maturity rating to see the level description for this specific control.",INDEX(_DV!$1:$5,MATCH(LEFT(I16,2),{"L1","L2","L3","L4","L5"},0),13)),"⏳ Select a maturity rating.") -> L1 — Initial: Enterprise Risk Framework Integration is absent or ad hoc. No formal process, no documentation, no named owner. Controls exist only reactively after incidents. | O16: =IF(S16="Exclude","⬛ Not Applicable",IF(T16="⬛ Auto-Excluded","⬛ Not Applicable",IF(I16="","✅ Applicable",IF(J16=1,"🔴 Critical",IF(J16=2,"🟠 Developing",IF(J16=3,"🟡 Defined",IF(J16>=4,"🟢 Managed","✅ Applicable"))))))) -> 🔴 Critical | P16: =IF(OR(J16="",L16=""),"⏳ Complete rating and target to generate recommendation.",IF(L16<=J16,"✅ Target met — sustain evidence and raise target when programme allows.",IFERROR(INDEX(_REC!$B:$B,MATCH(A16&"|"&IF(L16="","",LEFT(TEXT(L16,"0"),1)),_REC!$A:$A,0)),"Recommendation pending — check _REC data."))) -> Standardise Enterprise Risk Framework Integration: formalise all documentation, apply the control consistently across all in-scope assets, close remaining coverage gaps, and ensure evidence is collected routinely. Exceptions must be formally managed with named owners and defined expiry dates. | Q16: ISO 31000|COSO|DORA Art.6|NIS2 | R16: Marc Etonde — Head of IT | T16: =IF(S16="Exclude","⬛ Excluded",IF(S16="Apply","✅ Applicable","✅ Applicable")) -> ✅ Applicable
A17: 14 | B17: Risk Management | C17: Risk Appetite & Tolerance Thresholds | D17: Risk Appetite & Tolerance Thresholds ensures that documented risk appetite with quantified tolerance thresholds and escalation triggers. Board-approved appetite statement with quantified thresholds per risk type. | E17: Reduces risk management blind spots by ensuring threats and treatment obligations are formally tracked, quantified, and governed. Without Risk Appetite & Tolerance Thresholds, risk decisions are reactive and unquantified, preventing board-level risk reporting and investment justification. | F17: No documented risk appetite or tolerance thresholds for cyber risk. No escalation triggers defined. | G17: None. | H17: =HYPERLINK("#'📎 Evidence Register'!C19","ER-014 → Row 19") -> ER-014 → Row 19 | I17: L1 — Initial | J17: =IF(I17="","",IF(LEFT(I17,2)="L1",1,IF(LEFT(I17,2)="L2",2,IF(LEFT(I17,2)="L3",3,IF(LEFT(I17,2)="L4",4,IF(LEFT(I17,2)="L5",5,"")))))) -> 1 | K17: L3 — Defined | L17: =IF(K17="","",IF(LEFT(K17,2)="L1",1,IF(LEFT(K17,2)="L2",2,IF(LEFT(K17,2)="L3",3,IF(LEFT(K17,2)="L4",4,IF(LEFT(K17,2)="L5",5,"")))))) -> 3 | M17: =IFERROR(IF(OR(J17="",L17=""),"—",L17-J17),"—") -> 2 | N17: =IFERROR(IF(I17="","⏳ Select a maturity rating to see the level description for this specific control.",INDEX(_DV!$1:$5,MATCH(LEFT(I17,2),{"L1","L2","L3","L4","L5"},0),14)),"⏳ Select a maturity rating.") -> L1 — Initial: Risk Appetite & Tolerance Thresholds is absent or ad hoc. No formal process, no documentation, no named owner. Controls exist only reactively after incidents. | O17: =IF(S17="Exclude","⬛ Not Applicable",IF(T17="⬛ Auto-Excluded","⬛ Not Applicable",IF(I17="","✅ Applicable",IF(J17=1,"🔴 Critical",IF(J17=2,"🟠 Developing",IF(J17=3,"🟡 Defined",IF(J17>=4,"🟢 Managed","✅ Applicable"))))))) -> 🔴 Critical | P17: =IF(OR(J17="",L17=""),"⏳ Complete rating and target to generate recommendation.",IF(L17<=J17,"✅ Target met — sustain evidence and raise target when programme allows.",IFERROR(INDEX(_REC!$B:$B,MATCH(A17&"|"&IF(L17="","",LEFT(TEXT(L17,"0"),1)),_REC!$A:$A,0)),"Recommendation pending — check _REC data."))) -> Standardise Risk Appetite & Tolerance Thresholds: formalise all documentation, apply the control consistently across all in-scope assets, close remaining coverage gaps, and ensure evidence is collected routinely. Exceptions must be formally managed with named owners and defined expiry dates. | Q17: ISO 27001 A.6.1.1|DORA Art.6|COBIT 2019 | R17: Jean-Paul Nkeng — Managing Director | T17: =IF(S17="Exclude","⬛ Excluded",IF(S17="Apply","✅ Applicable","✅ Applicable")) -> ✅ Applicable
A18: 15 | B18: Risk Management | C18: Risk Register Management & Reporting | D18: Risk Register Management & Reporting ensures that active risk register with owners, treatment plans, and board reporting. Monthly risk register update; each risk has named owner and treatment plan; quarterly board report. | E18: Reduces risk management blind spots by ensuring threats and treatment obligations are formally tracked, quantified, and governed. Without Risk Register Management & Reporting, risk decisions are reactive and unquantified, preventing board-level risk reporting and investment justification. | F18: No security risk register. Risks surface as penetration test findings and bank questionnaire gaps, tracked in separate spreadsheets with no ownership or treatment plan. | G18: Pentest findings tracker (Excel, last updated March 2026) — Tier 2, partial. | H18: =HYPERLINK("#'📎 Evidence Register'!C20","ER-015 → Row 20") -> ER-015 → Row 20 | I18: L1 — Initial | J18: =IF(I18="","",IF(LEFT(I18,2)="L1",1,IF(LEFT(I18,2)="L2",2,IF(LEFT(I18,2)="L3",3,IF(LEFT(I18,2)="L4",4,IF(LEFT(I18,2)="L5",5,"")))))) -> 1 | K18: L3 — Defined | L18: =IF(K18="","",IF(LEFT(K18,2)="L1",1,IF(LEFT(K18,2)="L2",2,IF(LEFT(K18,2)="L3",3,IF(LEFT(K18,2)="L4",4,IF(LEFT(K18,2)="L5",5,"")))))) -> 3 | M18: =IFERROR(IF(OR(J18="",L18=""),"—",L18-J18),"—") -> 2 | N18: =IFERROR(IF(I18="","⏳ Select a maturity rating to see the level description for this specific control.",INDEX(_DV!$1:$5,MATCH(LEFT(I18,2),{"L1","L2","L3","L4","L5"},0),15)),"⏳ Select a maturity rating.") -> L1 — Initial: Risk Register Management & Reporting is absent or ad hoc. No formal process, no documentation, no named owner. Controls exist only reactively after incidents. | O18: =IF(S18="Exclude","⬛ Not Applicable",IF(T18="⬛ Auto-Excluded","⬛ Not Applicable",IF(I18="","✅ Applicable",IF(J18=1,"🔴 Critical",IF(J18=2,"🟠 Developing",IF(J18=3,"🟡 Defined",IF(J18>=4,"🟢 Managed","✅ Applicable"))))))) -> 🔴 Critical | P18: =IF(OR(J18="",L18=""),"⏳ Complete rating and target to generate recommendation.",IF(L18<=J18,"✅ Target met — sustain evidence and raise target when programme allows.",IFERROR(INDEX(_REC!$B:$B,MATCH(A18&"|"&IF(L18="","",LEFT(TEXT(L18,"0"),1)),_REC!$A:$A,0)),"Recommendation pending — check _REC data."))) -> Standardise Risk Register Management & Reporting: formalise all documentation, apply the control consistently across all in-scope assets, close remaining coverage gaps, and ensure evidence is collected routinely. Exceptions must be formally managed with named owners and defined expiry dates. | Q18: ISO 27001|DORA Art.6|NIS2 | R18: Marc Etonde — Head of IT | T18: =IF(S18="Exclude","⬛ Excluded",IF(S18="Apply","✅ Applicable","✅ Applicable")) -> ✅ Applicable
A19: 16 | B19: Risk Management | C19: Cyber Risk Quantification | D19: Cyber Risk Quantification ensures that financial quantification of cyber risk scenarios to support investment decisions. At least 3 scenarios quantified in financial terms (FAIR or equivalent); annual refresh. | E19: Reduces risk management blind spots by ensuring threats and treatment obligations are formally tracked, quantified, and governed. Without Cyber Risk Quantification, risk decisions are reactive and unquantified, preventing board-level risk reporting and investment justification. | F19: No financial quantification of cyber risk. Investment decisions are made on cost and bank pressure rather than modelled loss exposure. | G19: None. | H19: =HYPERLINK("#'📎 Evidence Register'!C21","ER-016 → Row 21") -> ER-016 → Row 21 | I19: L1 — Initial | J19: =IF(I19="","",IF(LEFT(I19,2)="L1",1,IF(LEFT(I19,2)="L2",2,IF(LEFT(I19,2)="L3",3,IF(LEFT(I19,2)="L4",4,IF(LEFT(I19,2)="L5",5,"")))))) -> 1 | K19: L3 — Defined | L19: =IF(K19="","",IF(LEFT(K19,2)="L1",1,IF(LEFT(K19,2)="L2",2,IF(LEFT(K19,2)="L3",3,IF(LEFT(K19,2)="L4",4,IF(LEFT(K19,2)="L5",5,"")))))) -> 3 | M19: =IFERROR(IF(OR(J19="",L19=""),"—",L19-J19),"—") -> 2 | N19: =IFERROR(IF(I19="","⏳ Select a maturity rating to see the level description for this specific control.",INDEX(_DV!$1:$5,MATCH(LEFT(I19,2),{"L1","L2","L3","L4","L5"},0),16)),"⏳ Select a maturity rating.") -> L1 — Initial: Cyber Risk Quantification is absent or ad hoc. No formal process, no documentation, no named owner. Controls exist only reactively after incidents. | O19: =IF(S19="Exclude","⬛ Not Applicable",IF(T19="⬛ Auto-Excluded","⬛ Not Applicable",IF(I19="","✅ Applicable",IF(J19=1,"🔴 Critical",IF(J19=2,"🟠 Developing",IF(J19=3,"🟡 Defined",IF(J19>=4,"🟢 Managed","✅ Applicable"))))))) -> 🔴 Critical | P19: =IF(OR(J19="",L19=""),"⏳ Complete rating and target to generate recommendation.",IF(L19<=J19,"✅ Target met — sustain evidence and raise target when programme allows.",IFERROR(INDEX(_REC!$B:$B,MATCH(A19&"|"&IF(L19="","",LEFT(TEXT(L19,"0"),1)),_REC!$A:$A,0)),"Recommendation pending — check _REC data."))) -> Standardise Cyber Risk Quantification: formalise all documentation, apply the control consistently across all in-scope assets, close remaining coverage gaps, and ensure evidence is collected routinely. Exceptions must be formally managed with named owners and defined expiry dates. | Q19: DORA Art.6|ISO 27005|NIST CSF GV.RM | R19: Paul Mbarga — Finance Director | T19: =IF(S19="Exclude","⬛ Excluded",IF(S19="Apply","✅ Applicable","✅ Applicable")) -> ✅ Applicable
A20: 17 | B20: Third-Party & Supply Chain | C20: Third-Party Risk Management (TPRM) Programme | D20: Third-Party Risk Management (TPRM) Programme ensures that structured programme to assess and manage cybersecurity risk across the supplier ecosystem. TPRM policy with tiered classification; annual assessments for critical suppliers; risk register active. | E20: Reduces supplier-introduced risk by ensuring third-party security obligations are assessed, contracted, and continuously monitored. Without Third-Party Risk Management (TPRM) Programme, the attack surface extends invisibly through vendor relationships, creating unmanaged concentration and supply chain risk. | F20: No TPRM programme. Suppliers are onboarded on commercial terms; security is not assessed at any stage of the lifecycle. | G20: None. Confirmed by interview with Procurement Officer. | H20: =HYPERLINK("#'📎 Evidence Register'!C22","ER-017 → Row 22") -> ER-017 → Row 22 | I20: L1 — Initial | J20: =IF(I20="","",IF(LEFT(I20,2)="L1",1,IF(LEFT(I20,2)="L2",2,IF(LEFT(I20,2)="L3",3,IF(LEFT(I20,2)="L4",4,IF(LEFT(I20,2)="L5",5,"")))))) -> 1 | K20: L4 — Managed | L20: =IF(K20="","",IF(LEFT(K20,2)="L1",1,IF(LEFT(K20,2)="L2",2,IF(LEFT(K20,2)="L3",3,IF(LEFT(K20,2)="L4",4,IF(LEFT(K20,2)="L5",5,"")))))) -> 4 | M20: =IFERROR(IF(OR(J20="",L20=""),"—",L20-J20),"—") -> 3 | N20: =IFERROR(IF(I20="","⏳ Select a maturity rating to see the level description for this specific control.",INDEX(_DV!$1:$5,MATCH(LEFT(I20,2),{"L1","L2","L3","L4","L5"},0),17)),"⏳ Select a maturity rating.") -> L1 — Initial: Third-Party Risk Management (TPRM) Programme is absent or ad hoc. No formal process, no documentation, no named owner. Controls exist only reactively after incidents. | O20: 🔴 Critical | P20: =IF(OR(J20="",L20=""),"⏳ Complete rating and target to generate recommendation.",IF(L20<=J20,"✅ Target met — sustain evidence and raise target when programme allows.",IFERROR(INDEX(_REC!$B:$B,MATCH(A20&"|"&IF(L20="","",LEFT(TEXT(L20,"0"),1)),_REC!$A:$A,0)),"Recommendation pending — check _REC data."))) -> Instrument Third-Party Risk Management (TPRM) Programme with measurable KPIs: define performance thresholds (coverage %, SLA adherence, exception count), establish automated telemetry where possible, and integrate reporting into quarterly governance cycles. Evidence must be system-generated and reviewed at each governance cycle. | Q20: GDPR Art.28|DORA Art.28-44|NIS2 Art.21 | R20: Linda Ojo — Procurement Officer | T20: =IF(S20="Exclude","⬛ Excluded",IF(S20="Apply","✅ Applicable",IF((('🔍 Scoping'!$E$30="No"))>0,"⬛ Auto-Excluded","✅ Applicable"))) -> ✅ Applicable
A21: 18 | B21: Third-Party & Supply Chain | C21: Vendor Security Assessment Process | D21: Vendor Security Assessment Process ensures that security assessments conducted before onboarding and annually for critical vendors. Questionnaire and evidence review for Tier 1 vendors; right-to-audit clause; findings tracked to closure. | E21: Reduces supplier-introduced risk by ensuring third-party security obligations are assessed, contracted, and continuously monitored. Without Vendor Security Assessment Process, the attack surface extends invisibly through vendor relationships, creating unmanaged concentration and supply chain risk. | F21: No vendor security assessment process. The only security review performed on a supplier in the last two years was of the core banking provider, at the acquiring bank's request. | G21: Single completed questionnaire for the core banking provider (2025) — Tier 2, isolated instance. | H21: =HYPERLINK("#'📎 Evidence Register'!C23","ER-018 → Row 23") -> ER-018 → Row 23 | I21: L1 — Initial | J21: =IF(I21="","",IF(LEFT(I21,2)="L1",1,IF(LEFT(I21,2)="L2",2,IF(LEFT(I21,2)="L3",3,IF(LEFT(I21,2)="L4",4,IF(LEFT(I21,2)="L5",5,"")))))) -> 1 | K21: L3 — Defined | L21: =IF(K21="","",IF(LEFT(K21,2)="L1",1,IF(LEFT(K21,2)="L2",2,IF(LEFT(K21,2)="L3",3,IF(LEFT(K21,2)="L4",4,IF(LEFT(K21,2)="L5",5,"")))))) -> 3 | M21: =IFERROR(IF(OR(J21="",L21=""),"—",L21-J21),"—") -> 2 | N21: =IFERROR(IF(I21="","⏳ Select a maturity rating to see the level description for this specific control.",INDEX(_DV!$1:$5,MATCH(LEFT(I21,2),{"L1","L2","L3","L4","L5"},0),18)),"⏳ Select a maturity rating.") -> L1 — Initial: Vendor Security Assessment Process is absent or ad hoc. No formal process, no documentation, no named owner. Controls exist only reactively after incidents. | O21: 🟠 Developing | P21: =IF(OR(J21="",L21=""),"⏳ Complete rating and target to generate recommendation.",IF(L21<=J21,"✅ Target met — sustain evidence and raise target when programme allows.",IFERROR(INDEX(_REC!$B:$B,MATCH(A21&"|"&IF(L21="","",LEFT(TEXT(L21,"0"),1)),_REC!$A:$A,0)),"Recommendation pending — check _REC data."))) -> Standardise Vendor Security Assessment Process: formalise all documentation, apply the control consistently across all in-scope assets, close remaining coverage gaps, and ensure evidence is collected routinely. Exceptions must be formally managed with named owners and defined expiry dates. | Q21: DORA Art.28|ISO 27001 A.5.19|NIS2 | R21: Linda Ojo — Procurement Officer | T21: =IF(S21="Exclude","⬛ Excluded",IF(S21="Apply","✅ Applicable",IF((('🔍 Scoping'!$E$30="No"))>0,"⬛ Auto-Excluded","✅ Applicable"))) -> ✅ Applicable
A22: 19 | B22: Third-Party & Supply Chain | C22: Vendor Contractual Security Obligations | D22: Vendor Contractual Security Obligations ensures that security requirements contractually embedded in all supplier agreements. Standard security schedule in all contracts; DPA for processors; DORA TPSP obligations in EU financial entity contracts. | E22: Reduces supplier-introduced risk by ensuring third-party security obligations are assessed, contracted, and continuously monitored. Without Vendor Contractual Security Obligations, the attack surface extends invisibly through vendor relationships, creating unmanaged concentration and supply chain risk. | F22: Security obligations are not embedded in supplier agreements. Two cloud contracts carry data protection clauses inherited from the provider's own terms; nothing is imposed by Acacia. | G22: AWS and Microsoft standard terms on file — supplier-imposed, not Acacia-imposed. Tier 2. | H22: =HYPERLINK("#'📎 Evidence Register'!C24","ER-019 → Row 24") -> ER-019 → Row 24 | I22: L1 — Initial | J22: =IF(I22="","",IF(LEFT(I22,2)="L1",1,IF(LEFT(I22,2)="L2",2,IF(LEFT(I22,2)="L3",3,IF(LEFT(I22,2)="L4",4,IF(LEFT(I22,2)="L5",5,"")))))) -> 1 | K22: L4 — Managed | L22: =IF(K22="","",IF(LEFT(K22,2)="L1",1,IF(LEFT(K22,2)="L2",2,IF(LEFT(K22,2)="L3",3,IF(LEFT(K22,2)="L4",4,IF(LEFT(K22,2)="L5",5,"")))))) -> 4 | M22: =IFERROR(IF(OR(J22="",L22=""),"—",L22-J22),"—") -> 3 | N22: =IFERROR(IF(I22="","⏳ Select a maturity rating to see the level description for this specific control.",INDEX(_DV!$1:$5,MATCH(LEFT(I22,2),{"L1","L2","L3","L4","L5"},0),19)),"⏳ Select a maturity rating.") -> L1 — Initial: Vendor Contractual Security Obligations is absent or ad hoc. No formal process, no documentation, no named owner. Controls exist only reactively after incidents. | O22: 🟠 Developing | P22: =IF(OR(J22="",L22=""),"⏳ Complete rating and target to generate recommendation.",IF(L22<=J22,"✅ Target met — sustain evidence and raise target when programme allows.",IFERROR(INDEX(_REC!$B:$B,MATCH(A22&"|"&IF(L22="","",LEFT(TEXT(L22,"0"),1)),_REC!$A:$A,0)),"Recommendation pending — check _REC data."))) -> Instrument Vendor Contractual Security Obligations with measurable KPIs: define performance thresholds (coverage %, SLA adherence, exception count), establish automated telemetry where possible, and integrate reporting into quarterly governance cycles. Evidence must be system-generated and reviewed at each governance cycle. | Q22: GDPR Art.28|DORA Art.30|NIS2 | R22: Marie Fotso — Legal & Compliance Counsel | T22: =IF(S22="Exclude","⬛ Excluded",IF(S22="Apply","✅ Applicable",IF((('🔍 Scoping'!$E$30="No"))>0,"⬛ Auto-Excluded","✅ Applicable"))) -> ✅ Applicable
A23: 20 | B23: Third-Party & Supply Chain | C23: Fourth-Party & Sub-Processor Mapping | D23: Fourth-Party & Sub-Processor Mapping ensures that visibility of critical fourth parties and their risk profiles. Critical fourth-party map maintained; GDPR sub-processor register current; key sub-dependencies reviewed annually. | E23: Reduces supplier-introduced risk by ensuring third-party security obligations are assessed, contracted, and continuously monitored. Without Fourth-Party & Sub-Processor Mapping, the attack surface extends invisibly through vendor relationships, creating unmanaged concentration and supply chain risk. | F23: No visibility of fourth parties or sub-processors. Sub-processor lists published by AWS and Microsoft have not been reviewed or mapped. | G23: None. | H23: =HYPERLINK("#'📎 Evidence Register'!C25","ER-020 → Row 25") -> ER-020 → Row 25 | I23: L1 — Initial | J23: =IF(I23="","",IF(LEFT(I23,2)="L1",1,IF(LEFT(I23,2)="L2",2,IF(LEFT(I23,2)="L3",3,IF(LEFT(I23,2)="L4",4,IF(LEFT(I23,2)="L5",5,"")))))) -> 1 | K23: L4 — Managed | L23: =IF(K23="","",IF(LEFT(K23,2)="L1",1,IF(LEFT(K23,2)="L2",2,IF(LEFT(K23,2)="L3",3,IF(LEFT(K23,2)="L4",4,IF(LEFT(K23,2)="L5",5,"")))))) -> 4 | M23: =IFERROR(IF(OR(J23="",L23=""),"—",L23-J23),"—") -> 3 | N23: =IFERROR(IF(I23="","⏳ Select a maturity rating to see the level description for this specific control.",INDEX(_DV!$1:$5,MATCH(LEFT(I23,2),{"L1","L2","L3","L4","L5"},0),20)),"⏳ Select a maturity rating.") -> L1 — Initial: Fourth-Party & Sub-Processor Mapping is absent or ad hoc. No formal process, no documentation, no named owner. Controls exist only reactively after incidents. | O23: 🔴 Critical | P23: =IF(OR(J23="",L23=""),"⏳ Complete rating and target to generate recommendation.",IF(L23<=J23,"✅ Target met — sustain evidence and raise target when programme allows.",IFERROR(INDEX(_REC!$B:$B,MATCH(A23&"|"&IF(L23="","",LEFT(TEXT(L23,"0"),1)),_REC!$A:$A,0)),"Recommendation pending — check _REC data."))) -> Instrument Fourth-Party & Sub-Processor Mapping with measurable KPIs: define performance thresholds (coverage %, SLA adherence, exception count), establish automated telemetry where possible, and integrate reporting into quarterly governance cycles. Evidence must be system-generated and reviewed at each governance cycle. | Q23: GDPR Art.28(2)|DORA Art.28|NIS2 | R23: Linda Ojo — Procurement Officer | T23: =IF(S23="Exclude","⬛ Excluded",IF(S23="Apply","✅ Applicable",IF((('🔍 Scoping'!$E$30="No"))>0,"⬛ Auto-Excluded","✅ Applicable"))) -> ✅ Applicable
A24: 21 | B24: Third-Party & Supply Chain | C24: DORA TPSP Critical Register | D24: DORA TPSP Critical Register ensures that dora-mandated register of critical ict third-party service providers. ICT TPSP register maintained with DORA Art. | E24: Reduces supplier-introduced risk by ensuring third-party security obligations are assessed, contracted, and continuously monitored. Without DORA TPSP Critical Register, the attack surface extends invisibly through vendor relationships, creating unmanaged concentration and supply chain risk. | H24: =HYPERLINK("#'📎 Evidence Register'!C26","ER-021 → Row 26") -> ER-021 → Row 26 | J24: =IF(I24="","",IF(LEFT(I24,2)="L1",1,IF(LEFT(I24,2)="L2",2,IF(LEFT(I24,2)="L3",3,IF(LEFT(I24,2)="L4",4,IF(LEFT(I24,2)="L5",5,"")))))) | L24: =IF(K24="","",IF(LEFT(K24,2)="L1",1,IF(LEFT(K24,2)="L2",2,IF(LEFT(K24,2)="L3",3,IF(LEFT(K24,2)="L4",4,IF(LEFT(K24,2)="L5",5,"")))))) | M24: =IFERROR(IF(OR(J24="",L24=""),"—",L24-J24),"—") -> — | N24: =IFERROR(IF(I24="","⏳ Select a maturity rating to see the level description for this specific control.",INDEX(_DV!$1:$5,MATCH(LEFT(I24,2),{"L1","L2","L3","L4","L5"},0),21)),"⏳ Select a maturity rating.") -> ⏳ Select a maturity rating to see the level description for this specific control. | O24: ⬛ Not Applicable | P24: =IF(OR(J24="",L24=""),"⏳ Complete rating and target to generate recommendation.",IF(L24<=J24,"✅ Target met — sustain evidence and raise target when programme allows.",IFERROR(INDEX(_REC!$B:$B,MATCH(A24&"|"&IF(L24="","",LEFT(TEXT(L24,"0"),1)),_REC!$A:$A,0)),"Recommendation pending — check _REC data."))) -> ⏳ Complete rating and target to generate recommendation. | Q24: DORA Art.28-44 | S24: Exclude | T24: =IF(S24="Exclude","⬛ Excluded",IF(S24="Apply","✅ Applicable",IF((('🔍 Scoping'!$E$8="No"))>0,"⬛ Auto-Excluded","✅ Applicable"))) -> ⬛ Excluded
A25: 22 | B25: Third-Party & Supply Chain | C25: Software Supply Chain Security Governance | D25: Software Supply Chain Security Governance ensures that governance of open-source components, sboms, and software dependencies. SBOM policy active; open-source component register maintained; SCA tooling in SDLC. | E25: Reduces supplier-introduced risk by ensuring third-party security obligations are assessed, contracted, and continuously monitored. Without Software Supply Chain Security Governance, the attack surface extends invisibly through vendor relationships, creating unmanaged concentration and supply chain risk. | F25: No governance over open-source components. Dependencies are added by engineers at will; no SBOM policy, no approved-component list, no licence review. | G25: package.json and requirements.txt files in GitHub reviewed — no governance artefacts. Tier 2. | H25: =HYPERLINK("#'📎 Evidence Register'!C27","ER-022 → Row 27") -> ER-022 → Row 27 | I25: L1 — Initial | J25: =IF(I25="","",IF(LEFT(I25,2)="L1",1,IF(LEFT(I25,2)="L2",2,IF(LEFT(I25,2)="L3",3,IF(LEFT(I25,2)="L4",4,IF(LEFT(I25,2)="L5",5,"")))))) -> 1 | K25: L3 — Defined | L25: =IF(K25="","",IF(LEFT(K25,2)="L1",1,IF(LEFT(K25,2)="L2",2,IF(LEFT(K25,2)="L3",3,IF(LEFT(K25,2)="L4",4,IF(LEFT(K25,2)="L5",5,"")))))) -> 3 | M25: =IFERROR(IF(OR(J25="",L25=""),"—",L25-J25),"—") -> 2 | N25: =IFERROR(IF(I25="","⏳ Select a maturity rating to see the level description for this specific control.",INDEX(_DV!$1:$5,MATCH(LEFT(I25,2),{"L1","L2","L3","L4","L5"},0),22)),"⏳ Select a maturity rating.") -> L1 — Initial: Software Supply Chain Security Governance is absent or ad hoc. No formal process, no documentation, no named owner. Controls exist only reactively after incidents. | O25: 🟠 Developing | P25: =IF(OR(J25="",L25=""),"⏳ Complete rating and target to generate recommendation.",IF(L25<=J25,"✅ Target met — sustain evidence and raise target when programme allows.",IFERROR(INDEX(_REC!$B:$B,MATCH(A25&"|"&IF(L25="","",LEFT(TEXT(L25,"0"),1)),_REC!$A:$A,0)),"Recommendation pending — check _REC data."))) -> Standardise Software Supply Chain Security Governance: formalise all documentation, apply the control consistently across all in-scope assets, close remaining coverage gaps, and ensure evidence is collected routinely. Exceptions must be formally managed with named owners and defined expiry dates. | Q25: CRA Art.13|NIST SSDF|NIS2 Art.21 | R25: Tunde Balogun — Lead Software Engineer | T25: =IF(S25="Exclude","⬛ Excluded",IF(S25="Apply","✅ Applicable",IF((('🔍 Scoping'!$E$30="No"))>0,"⬛ Auto-Excluded","✅ Applicable"))) -> ✅ Applicable
A26: 23 | B26: Third-Party & Supply Chain | C26: Supplier Resilience Requirements | D26: Supplier Resilience Requirements ensures that business continuity and resilience requirements imposed on critical suppliers. Critical supplier BCP requirements in contracts; annual BCP evidence reviewed; DR capability confirmed. | E26: Reduces supplier-introduced risk by ensuring third-party security obligations are assessed, contracted, and continuously monitored. Without Supplier Resilience Requirements, the attack surface extends invisibly through vendor relationships, creating unmanaged concentration and supply chain risk. | F26: No resilience or continuity requirements imposed on critical suppliers. Provider availability is assumed from marketing SLAs. | G26: None. | H26: =HYPERLINK("#'📎 Evidence Register'!C28","ER-023 → Row 28") -> ER-023 → Row 28 | I26: L1 — Initial | J26: =IF(I26="","",IF(LEFT(I26,2)="L1",1,IF(LEFT(I26,2)="L2",2,IF(LEFT(I26,2)="L3",3,IF(LEFT(I26,2)="L4",4,IF(LEFT(I26,2)="L5",5,"")))))) -> 1 | K26: L3 — Defined | L26: =IF(K26="","",IF(LEFT(K26,2)="L1",1,IF(LEFT(K26,2)="L2",2,IF(LEFT(K26,2)="L3",3,IF(LEFT(K26,2)="L4",4,IF(LEFT(K26,2)="L5",5,"")))))) -> 3 | M26: =IFERROR(IF(OR(J26="",L26=""),"—",L26-J26),"—") -> 2 | N26: =IFERROR(IF(I26="","⏳ Select a maturity rating to see the level description for this specific control.",INDEX(_DV!$1:$5,MATCH(LEFT(I26,2),{"L1","L2","L3","L4","L5"},0),23)),"⏳ Select a maturity rating.") -> L1 — Initial: Supplier Resilience Requirements is absent or ad hoc. No formal process, no documentation, no named owner. Controls exist only reactively after incidents. | O26: 🔴 Critical | P26: =IF(OR(J26="",L26=""),"⏳ Complete rating and target to generate recommendation.",IF(L26<=J26,"✅ Target met — sustain evidence and raise target when programme allows.",IFERROR(INDEX(_REC!$B:$B,MATCH(A26&"|"&IF(L26="","",LEFT(TEXT(L26,"0"),1)),_REC!$A:$A,0)),"Recommendation pending — check _REC data."))) -> Standardise Supplier Resilience Requirements: formalise all documentation, apply the control consistently across all in-scope assets, close remaining coverage gaps, and ensure evidence is collected routinely. Exceptions must be formally managed with named owners and defined expiry dates. | Q26: DORA Art.28|ISO 22301|NIS2 | R26: Linda Ojo — Procurement Officer | T26: =IF(S26="Exclude","⬛ Excluded",IF(S26="Apply","✅ Applicable",IF((('🔍 Scoping'!$E$30="No"))>0,"⬛ Auto-Excluded","✅ Applicable"))) -> ✅ Applicable
A27: 24 | B27: Privacy & Compliance | C27: Privacy Governance & DPO/Privacy Lead | D27: Privacy Governance & DPO/Privacy Lead ensures that designated privacy function with authority, resources, and board access. Named DPO or Privacy Lead with documented authority; independent of operational processing; DPA-notified where required. | E27: Reduces regulatory privacy risk by ensuring personal data processing is governed, documented, and legally defensible. Without Privacy Governance & DPO/Privacy Lead, regulatory examination can immediately identify material non-compliance, triggering enforcement action under GDPR, HIPAA, or CCPA. | F27: No DPO appointed. Legal & Compliance Counsel handles privacy queries informally alongside a full commercial caseload, without a documented mandate, budget or board access. | G27: Job description for Legal & Compliance Counsel — no privacy responsibilities recorded. Tier 3. | H27: =HYPERLINK("#'📎 Evidence Register'!C29","ER-024 → Row 29") -> ER-024 → Row 29 | I27: L2 — Developing | J27: =IF(I27="","",IF(LEFT(I27,2)="L1",1,IF(LEFT(I27,2)="L2",2,IF(LEFT(I27,2)="L3",3,IF(LEFT(I27,2)="L4",4,IF(LEFT(I27,2)="L5",5,"")))))) -> 2 | K27: L4 — Managed | L27: =IF(K27="","",IF(LEFT(K27,2)="L1",1,IF(LEFT(K27,2)="L2",2,IF(LEFT(K27,2)="L3",3,IF(LEFT(K27,2)="L4",4,IF(LEFT(K27,2)="L5",5,"")))))) -> 4 | M27: =IFERROR(IF(OR(J27="",L27=""),"—",L27-J27),"—") -> 2 | N27: =IFERROR(IF(I27="","⏳ Select a maturity rating to see the level description for this specific control.",INDEX(_DV!$1:$5,MATCH(LEFT(I27,2),{"L1","L2","L3","L4","L5"},0),24)),"⏳ Select a maturity rating.") -> L2 — Developing: Privacy Governance & DPO/Privacy Lead has basic controls in place but coverage is incomplete and execution is manual. Not consistently applied across all in-scope assets. Formal governance is absent. | O27: 🔴 Critical | P27: =IF(OR(J27="",L27=""),"⏳ Complete rating and target to generate recommendation.",IF(L27<=J27,"✅ Target met — sustain evidence and raise target when programme allows.",IFERROR(INDEX(_REC!$B:$B,MATCH(A27&"|"&IF(L27="","",LEFT(TEXT(L27,"0"),1)),_REC!$A:$A,0)),"Recommendation pending — check _REC data."))) -> Instrument Privacy Governance & DPO/Privacy Lead with measurable KPIs: define performance thresholds (coverage %, SLA adherence, exception count), establish automated telemetry where possible, and integrate reporting into quarterly governance cycles. Evidence must be system-generated and reviewed at each governance cycle. | Q27: GDPR Art.37-39|HIPAA S164.530|CCPA | R27: Marie Fotso — Legal & Compliance Counsel | T27: =IF(S27="Exclude","⬛ Excluded",IF(S27="Apply","✅ Applicable",IF((('🔍 Scoping'!$E$6="No"))>0,"⬛ Auto-Excluded","✅ Applicable"))) -> ✅ Applicable
A28: 25 | B28: Privacy & Compliance | C28: Records of Processing Activities (ROPA) | D28: Records of Processing Activities (ROPA) ensures that complete and current ropa covering all personal data processing activities. ROPA >=90% complete; reviewed annually; new processing activities added within 30 days. | E28: Reduces regulatory privacy risk by ensuring personal data processing is governed, documented, and legally defensible. Without Records of Processing Activities (ROPA), regulatory examination can immediately identify material non-compliance, triggering enforcement action under GDPR, HIPAA, or CCPA. | F28: No Records of Processing Activities. Personal data processing is undocumented across the wallet platform, the merchant portal and the CRM. | G28: None. This is a direct GDPR Article 30 gap. | H28: =HYPERLINK("#'📎 Evidence Register'!C30","ER-025 → Row 30") -> ER-025 → Row 30 | I28: L1 — Initial | J28: =IF(I28="","",IF(LEFT(I28,2)="L1",1,IF(LEFT(I28,2)="L2",2,IF(LEFT(I28,2)="L3",3,IF(LEFT(I28,2)="L4",4,IF(LEFT(I28,2)="L5",5,"")))))) -> 1 | K28: L4 — Managed | L28: =IF(K28="","",IF(LEFT(K28,2)="L1",1,IF(LEFT(K28,2)="L2",2,IF(LEFT(K28,2)="L3",3,IF(LEFT(K28,2)="L4",4,IF(LEFT(K28,2)="L5",5,"")))))) -> 4 | M28: =IFERROR(IF(OR(J28="",L28=""),"—",L28-J28),"—") -> 3 | N28: =IFERROR(IF(I28="","⏳ Select a maturity rating to see the level description for this specific control.",INDEX(_DV!$1:$5,MATCH(LEFT(I28,2),{"L1","L2","L3","L4","L5"},0),25)),"⏳ Select a maturity rating.") -> L1 — Initial: Records of Processing Activities (ROPA) is absent or ad hoc. No formal process, no documentation, no named owner. Controls exist only reactively after incidents. | O28: 🟠 Developing | P28: =IF(OR(J28="",L28=""),"⏳ Complete rating and target to generate recommendation.",IF(L28<=J28,"✅ Target met — sustain evidence and raise target when programme allows.",IFERROR(INDEX(_REC!$B:$B,MATCH(A28&"|"&IF(L28="","",LEFT(TEXT(L28,"0"),1)),_REC!$A:$A,0)),"Recommendation pending — check _REC data."))) -> Instrument Records of Processing Activities (ROPA) with measurable KPIs: define performance thresholds (coverage %, SLA adherence, exception count), establish automated telemetry where possible, and integrate reporting into quarterly governance cycles. Evidence must be system-generated and reviewed at each governance cycle. | Q28: GDPR Art.30|HIPAA S164.514 | R28: Marie Fotso — Legal & Compliance Counsel | T28: =IF(S28="Exclude","⬛ Excluded",IF(S28="Apply","✅ Applicable",IF((('🔍 Scoping'!$E$6="No"))>0,"⬛ Auto-Excluded","✅ Applicable"))) -> ✅ Applicable
A29: 26 | B29: Privacy & Compliance | C29: Data Protection Impact Assessments (DPIAs) | D29: Data Protection Impact Assessments (DPIAs) ensures that dpias conducted for all high-risk processing activities. DPIA process documented; mandatory triggers list; DPIAs completed for all high-risk processing; DPO sign-off. | E29: Reduces regulatory privacy risk by ensuring personal data processing is governed, documented, and legally defensible. Without Data Protection Impact Assessments (DPIAs), regulatory examination can immediately identify material non-compliance, triggering enforcement action under GDPR, HIPAA, or CCPA. | F29: No DPIA process. The consumer wallet and its device-fingerprinting feature were launched without any assessment. | G29: None. | H29: =HYPERLINK("#'📎 Evidence Register'!C31","ER-026 → Row 31") -> ER-026 → Row 31 | I29: L1 — Initial | J29: =IF(I29="","",IF(LEFT(I29,2)="L1",1,IF(LEFT(I29,2)="L2",2,IF(LEFT(I29,2)="L3",3,IF(LEFT(I29,2)="L4",4,IF(LEFT(I29,2)="L5",5,"")))))) -> 1 | K29: L4 — Managed | L29: =IF(K29="","",IF(LEFT(K29,2)="L1",1,IF(LEFT(K29,2)="L2",2,IF(LEFT(K29,2)="L3",3,IF(LEFT(K29,2)="L4",4,IF(LEFT(K29,2)="L5",5,"")))))) -> 4 | M29: =IFERROR(IF(OR(J29="",L29=""),"—",L29-J29),"—") -> 3 | N29: =IFERROR(IF(I29="","⏳ Select a maturity rating to see the level description for this specific control.",INDEX(_DV!$1:$5,MATCH(LEFT(I29,2),{"L1","L2","L3","L4","L5"},0),26)),"⏳ Select a maturity rating.") -> L1 — Initial: Data Protection Impact Assessments (DPIAs) is absent or ad hoc. No formal process, no documentation, no named owner. Controls exist only reactively after incidents. | O29: 🔴 Critical | P29: =IF(OR(J29="",L29=""),"⏳ Complete rating and target to generate recommendation.",IF(L29<=J29,"✅ Target met — sustain evidence and raise target when programme allows.",IFERROR(INDEX(_REC!$B:$B,MATCH(A29&"|"&IF(L29="","",LEFT(TEXT(L29,"0"),1)),_REC!$A:$A,0)),"Recommendation pending — check _REC data."))) -> Instrument Data Protection Impact Assessments (DPIAs) with measurable KPIs: define performance thresholds (coverage %, SLA adherence, exception count), establish automated telemetry where possible, and integrate reporting into quarterly governance cycles. Evidence must be system-generated and reviewed at each governance cycle. | Q29: GDPR Art.35-36|NIS2|HIPAA | R29: Marie Fotso — Legal & Compliance Counsel | T29: =IF(S29="Exclude","⬛ Excluded",IF(S29="Apply","✅ Applicable",IF((('🔍 Scoping'!$E$6="No"))>0,"⬛ Auto-Excluded","✅ Applicable"))) -> ✅ Applicable
A30: 27 | B30: Privacy & Compliance | C30: Cross-Border Data Transfer Controls | D30: Cross-Border Data Transfer Controls ensures that legal basis and technical controls for all international personal data transfers. Transfer mapping complete; SCCs/BCRs or adequacy decisions in place; Schrems II compliance documented. | E30: Reduces regulatory privacy risk by ensuring personal data processing is governed, documented, and legally defensible. Without Cross-Border Data Transfer Controls, regulatory examination can immediately identify material non-compliance, triggering enforcement action under GDPR, HIPAA, or CCPA. | F30: EU merchant data is processed in eu-west-1, but transfers between the Douala office, the Lagos office and AWS have never been mapped and no transfer mechanism has been documented. | G30: None. Data residency assumed from AWS region selection only. Tier 3. | H30: =HYPERLINK("#'📎 Evidence Register'!C32","ER-027 → Row 32") -> ER-027 → Row 32 | I30: L1 — Initial | J30: =IF(I30="","",IF(LEFT(I30,2)="L1",1,IF(LEFT(I30,2)="L2",2,IF(LEFT(I30,2)="L3",3,IF(LEFT(I30,2)="L4",4,IF(LEFT(I30,2)="L5",5,"")))))) -> 1 | K30: L4 — Managed | L30: =IF(K30="","",IF(LEFT(K30,2)="L1",1,IF(LEFT(K30,2)="L2",2,IF(LEFT(K30,2)="L3",3,IF(LEFT(K30,2)="L4",4,IF(LEFT(K30,2)="L5",5,"")))))) -> 4 | M30: =IFERROR(IF(OR(J30="",L30=""),"—",L30-J30),"—") -> 3 | N30: =IFERROR(IF(I30="","⏳ Select a maturity rating to see the level description for this specific control.",INDEX(_DV!$1:$5,MATCH(LEFT(I30,2),{"L1","L2","L3","L4","L5"},0),27)),"⏳ Select a maturity rating.") -> L1 — Initial: Cross-Border Data Transfer Controls is absent or ad hoc. No formal process, no documentation, no named owner. Controls exist only reactively after incidents. | O30: 🔴 Critical | P30: =IF(OR(J30="",L30=""),"⏳ Complete rating and target to generate recommendation.",IF(L30<=J30,"✅ Target met — sustain evidence and raise target when programme allows.",IFERROR(INDEX(_REC!$B:$B,MATCH(A30&"|"&IF(L30="","",LEFT(TEXT(L30,"0"),1)),_REC!$A:$A,0)),"Recommendation pending — check _REC data."))) -> Instrument Cross-Border Data Transfer Controls with measurable KPIs: define performance thresholds (coverage %, SLA adherence, exception count), establish automated telemetry where possible, and integrate reporting into quarterly governance cycles. Evidence must be system-generated and reviewed at each governance cycle. | Q30: GDPR Art.44-49|CCPA|PDPA|PIPL | R30: Marie Fotso — Legal & Compliance Counsel | T30: =IF(S30="Exclude","⬛ Excluded",IF(S30="Apply","✅ Applicable",IF((('🔍 Scoping'!$E$6="No"))>0,"⬛ Auto-Excluded","✅ Applicable"))) -> ✅ Applicable
A31: 28 | B31: Audit & Assurance | C31: Internal & External Audit Programme | D31: Internal & External Audit Programme ensures that comprehensive audit programme covering security controls, regulatory compliance, and maturity. Annual internal audit; external certification (ISO 27001/SOC 2) every 2 years at minimum; findings tracked. | E31: Reduces residual risk from undetected control failures by ensuring security posture is independently validated. Without Internal & External Audit Programme, control degradation goes undetected between incidents, creating regulatory evidence gaps and false assurance at board level. | F31: No internal audit function and no security audit programme. The only external review is the annual penetration test, which is technical in scope and does not cover controls or compliance. | G31: Pentest report (2025) — technical scope only. Tier 2. | H31: =HYPERLINK("#'📎 Evidence Register'!C33","ER-028 → Row 33") -> ER-028 → Row 33 | I31: L1 — Initial | J31: =IF(I31="","",IF(LEFT(I31,2)="L1",1,IF(LEFT(I31,2)="L2",2,IF(LEFT(I31,2)="L3",3,IF(LEFT(I31,2)="L4",4,IF(LEFT(I31,2)="L5",5,"")))))) -> 1 | K31: L3 — Defined | L31: =IF(K31="","",IF(LEFT(K31,2)="L1",1,IF(LEFT(K31,2)="L2",2,IF(LEFT(K31,2)="L3",3,IF(LEFT(K31,2)="L4",4,IF(LEFT(K31,2)="L5",5,"")))))) -> 3 | M31: =IFERROR(IF(OR(J31="",L31=""),"—",L31-J31),"—") -> 2 | N31: =IFERROR(IF(I31="","⏳ Select a maturity rating to see the level description for this specific control.",INDEX(_DV!$1:$5,MATCH(LEFT(I31,2),{"L1","L2","L3","L4","L5"},0),28)),"⏳ Select a maturity rating.") -> L1 — Initial: Internal & External Audit Programme is absent or ad hoc. No formal process, no documentation, no named owner. Controls exist only reactively after incidents. | O31: 🟠 Developing | P31: =IF(OR(J31="",L31=""),"⏳ Complete rating and target to generate recommendation.",IF(L31<=J31,"✅ Target met — sustain evidence and raise target when programme allows.",IFERROR(INDEX(_REC!$B:$B,MATCH(A31&"|"&IF(L31="","",LEFT(TEXT(L31,"0"),1)),_REC!$A:$A,0)),"Recommendation pending — check _REC data."))) -> Standardise Internal & External Audit Programme: formalise all documentation, apply the control consistently across all in-scope assets, close remaining coverage gaps, and ensure evidence is collected routinely. Exceptions must be formally managed with named owners and defined expiry dates. | Q31: ISO 27001 A.9.1|SOX|DORA Art.24|NIS2 | R31: Jean-Paul Nkeng — Managing Director | T31: =IF(S31="Exclude","⬛ Excluded",IF(S31="Apply","✅ Applicable","✅ Applicable")) -> ✅ Applicable

Sheet ID Identify
A1: 🔍 IDENTIFY — Assets, Data, Risk & Exposure · 22 Controls · Domain Weight: 10%
B2: 📝 Col D = Control Description | Col E = Risk & Maturity Impact | Col F = Assessment narrative | Col G = Evidence artefacts | Col H = Evidence Register link | Col I = Rating | Col N = Auto level description | Col S = Override scope (Apply / Exclude) | I2: Current: | J2: =IFERROR(AVERAGEIFS(J4:J25,T4:T25,"✅ Applicable"),"—") -> 1.3157895 | K2: Target: | L2: =IFERROR(AVERAGEIFS(L4:L25,T4:T25,"✅ Applicable"),"—") -> 3.4736842 | M2: Rated: | N2: =IFERROR(COUNTIFS(J4:J25,"<>",T4:T25,"✅ Applicable")&" / "&COUNTIF(T4:T25,"✅ Applicable")&" applicable","—") -> 19 / 19 applicable | P2: Auto-excl.: | Q2: =COUNTIF(T4:T25,"⬛ Auto-Excluded")&" controls (scoping)" -> 0 controls (scoping)
A3: # | B3: Category | C3: Control Name | D3: Control Description | E3: Risk & Maturity Impact (Why This Control Matters) | F3: 📝 Assessment (Current state & key gaps) | G3: 🗂️ Evidence (Artefacts & links) | H3: Evidence Reference | I3: Maturity Rating ▼ Select level | J3: Score (Auto) | K3: Target Level ▼ Select target | L3: Target Score | M3: Gap | N3: Level Description (Auto — control-specific) | O3: 🚦 Status | P3: 💡 Recommendation | Q3: Frameworks & Regulations | R3: Owner | S3: Scope (Apply / Exclude) | T3: ⚙️ Eff. Scope
A4: 29 | B4: Asset Management | C4: IT Hardware Asset Inventory (CMDB) | D4: IT Hardware Asset Inventory (CMDB) ensures that complete, current cmdb covering all managed hardware assets with lifecycle status. CMDB >=98% completeness verified by scan; automated discovery integrated; asset lifecycle tracked. | E4: Reduces exposure from unknown or unmanaged assets by ensuring the full scope of what must be protected is visible and governed. Without IT Hardware Asset Inventory (CMDB), attackers can exploit assets outside the security programme's visibility — the most common initial access vector. | F4: An asset register exists in Freshservice covering laptops and servers, populated at procurement. It is not reconciled against the network, and lifecycle status is not tracked. Estimated completeness around 70%. | G4: Freshservice asset export (August 2026), 312 records — Tier 2, sample-tested against 20 physical devices. | H4: =HYPERLINK("#'📎 Evidence Register'!C34","ER-029 → Row 34") -> ER-029 → Row 34 | I4: L2 — Developing | J4: =IF(I4="","",IF(LEFT(I4,2)="L1",1,IF(LEFT(I4,2)="L2",2,IF(LEFT(I4,2)="L3",3,IF(LEFT(I4,2)="L4",4,IF(LEFT(I4,2)="L5",5,"")))))) -> 2 | K4: L3 — Defined | L4: =IF(K4="","",IF(LEFT(K4,2)="L1",1,IF(LEFT(K4,2)="L2",2,IF(LEFT(K4,2)="L3",3,IF(LEFT(K4,2)="L4",4,IF(LEFT(K4,2)="L5",5,"")))))) -> 3 | M4: =IFERROR(IF(OR(J4="",L4=""),"—",L4-J4),"—") -> 1 | N4: =IFERROR(IF(I4="","⏳ Select a maturity rating to see the level description for this specific control.",INDEX(_DV!$1:$5,MATCH(LEFT(I4,2),{"L1","L2","L3","L4","L5"},0),29)),"⏳ Select a maturity rating.") -> L2 — Developing: IT Hardware Asset Inventory (CMDB) has basic controls in place but coverage is incomplete and execution is manual. Not consistently applied across all in-scope assets. Formal governance is absent. | O4: =IF(S4="Exclude","⬛ Not Applicable",IF(T4="⬛ Auto-Excluded","⬛ Not Applicable",IF(I4="","✅ Applicable",IF(J4=1,"🔴 Critical",IF(J4=2,"🟠 Developing",IF(J4=3,"🟡 Defined",IF(J4>=4,"🟢 Managed","✅ Applicable"))))))) -> 🟠 Developing | P4: =IF(OR(J4="",L4=""),"⏳ Complete rating and target to generate recommendation.",IF(L4<=J4,"✅ Target met — sustain evidence and raise target when programme allows.",IFERROR(INDEX(_REC!$B:$B,MATCH(A4&"|"&IF(L4="","",LEFT(TEXT(L4,"0"),1)),_REC!$A:$A,0)),"Recommendation pending — check _REC data."))) -> Standardise IT Hardware Asset Inventory (CMDB): formalise all documentation, apply the control consistently across all in-scope assets, close remaining coverage gaps, and ensure evidence is collected routinely. Exceptions must be formally managed with named owners and defined expiry dates. | Q4: CIS Controls v8.1|ISO 27001 A.8.1|DORA Art.8 | R4: Grace Ayuk — IT Operations Manager | T4: =IF(S4="Exclude","⬛ Excluded",IF(S4="Apply","✅ Applicable","✅ Applicable")) -> ✅ Applicable
